{"TARA_PSE_MAG_00114_000000000001": [2955, 5, [[[["superkingdom", "d__Bacteria"], ["phylum", "p__Bacteroidota"], ["class", "c__Bacteroidia"], ["order", "o__Flavobacteriales"], ["family", "f__Flavobacteriaceae"], ["genus", "g__Salegentibacter"]], 5]]], "TARA_PSE_MAG_00114_000000000002": [2546, 1, []], "TARA_PSE_MAG_00114_000000000003": [6202, 2, []], "TARA_PSE_MAG_00114_000000000004": [3647, 1, [[[["superkingdom", "d__Bacteria"], ["phylum", "p__Proteobacteria"], ["class", "c__Alphaproteobacteria"], ["order", "o__Nisaeales"], ["family", "f__Nisaeaceae"], ["genus", "g__UBA7326"]], 1]]], "TARA_PSE_MAG_00114_000000000005": [5817, 6, []], "TARA_PSE_MAG_00114_000000000006": [3840, 4, []], "TARA_PSE_MAG_00114_000000000007": [5708, 4, []], "TARA_PSE_MAG_00114_000000000008": [3211, 7, [[[["superkingdom", "d__Bacteria"], ["phylum", "p__Bacteroidota"], ["class", "c__Bacteroidia"], ["order", "o__Flavobacteriales"], ["family", "f__Crocinitomicaceae"], ["genus", "g__UBA952"]], 1]]], "TARA_PSE_MAG_00114_000000000009": [2514, 4, []], "TARA_PSE_MAG_00114_000000000010": [4221, 1, []], "TARA_PSE_MAG_00114_000000000011": [3825, 3, []], "TARA_PSE_MAG_00114_000000000012": [3708, 4, []], "TARA_PSE_MAG_00114_000000000013": [3090, 5, []], "TARA_PSE_MAG_00114_000000000014": [3959, 6, []], "TARA_PSE_MAG_00114_000000000015": [9592, 13, [[[["superkingdom", "d__Bacteria"], ["phylum", "p__Bacteroidota"], ["class", "c__Bacteroidia"], ["order", "o__Flavobacteriales"], ["family", "f__Flavobacteriaceae"], ["genus", "g__Salegentibacter"]], 13]]], "TARA_PSE_MAG_00114_000000000016": [3396, 5, []], "TARA_PSE_MAG_00114_000000000017": [3463, 5, []], "TARA_PSE_MAG_00114_000000000018": [3527, 1, []], "TARA_PSE_MAG_00114_000000000019": [3070, 5, []], "TARA_PSE_MAG_00114_000000000020": [2534, 2, []], "TARA_PSE_MAG_00114_000000000021": [3739, 5, []], "TARA_PSE_MAG_00114_000000000022": [3180, 2, [[[["superkingdom", "d__Bacteria"], ["phylum", "p__Bacteroidota"], ["class", "c__Bacteroidia"], ["order", "o__Flavobacteriales"], ["family", "f__Flavobacteriaceae"], ["genus", "g__Salegentibacter"]], 2]]], "TARA_PSE_MAG_00114_000000000023": [2508, 3, []], "TARA_PSE_MAG_00114_000000000024": [2601, 3, [[[["superkingdom", "d__Bacteria"], ["phylum", "p__Proteobacteria"], ["class", "c__Alphaproteobacteria"], ["order", "o__Nisaeales"], ["family", "f__Nisaeaceae"], ["genus", "g__UBA7326"]], 2]]], "TARA_PSE_MAG_00114_000000000025": [2676, 3, []], "TARA_PSE_MAG_00114_000000000026": [3045, 1, []], "TARA_PSE_MAG_00114_000000000027": [3986, 6, []], "TARA_PSE_MAG_00114_000000000028": [4141, 5, []], "TARA_PSE_MAG_00114_000000000029": [3237, 5, []], "TARA_PSE_MAG_00114_000000000030": [3376, 3, [[[["superkingdom", "d__Bacteria"], ["phylum", "p__Bacteroidota"], ["class", "c__Bacteroidia"], ["order", "o__Flavobacteriales"], ["family", "f__Flavobacteriaceae"], ["genus", "g__Leeuwenhoekiella"]], 1]]], "TARA_PSE_MAG_00114_000000000031": [4230, 1, []], "TARA_PSE_MAG_00114_000000000032": [4059, 6, []], "TARA_PSE_MAG_00114_000000000033": [4347, 6, []], "TARA_PSE_MAG_00114_000000000034": [4651, 6, []], "TARA_PSE_MAG_00114_000000000035": [3876, 3, []], "TARA_PSE_MAG_00114_000000000036": [4909, 4, []], "TARA_PSE_MAG_00114_000000000037": [4857, 4, []], "TARA_PSE_MAG_00114_000000000038": [3590, 2, [[[["superkingdom", "d__Bacteria"], ["phylum", "p__Bacteroidota"], ["class", "c__Bacteroidia"], ["order", "o__Flavobacteriales"], ["family", "f__Flavobacteriaceae"], ["genus", "g__Flavobacterium"]], 2]]], "TARA_PSE_MAG_00114_000000000039": [2609, 4, []], "TARA_PSE_MAG_00114_000000000040": [6462, 8, []], "TARA_PSE_MAG_00114_000000000041": [6430, 3, []], "TARA_PSE_MAG_00114_000000000042": [3690, 1, []], "TARA_PSE_MAG_00114_000000000043": [3466, 3, []], "TARA_PSE_MAG_00114_000000000044": [4181, 0, []], "TARA_PSE_MAG_00114_000000000045": [3352, 3, []], "TARA_PSE_MAG_00114_000000000046": [3157, 8, [[[["superkingdom", "d__Bacteria"], ["phylum", "p__Bacteroidota"], ["class", "c__Bacteroidia"], ["order", "o__Flavobacteriales"], ["family", "f__Crocinitomicaceae"], ["genus", "g__UBA952"]], 1]]], "TARA_PSE_MAG_00114_000000000047": [3363, 2, []], "TARA_PSE_MAG_00114_000000000048": [6169, 4, []], "TARA_PSE_MAG_00114_000000000049": [3218, 2, [[[["superkingdom", "d__Bacteria"], ["phylum", "p__Proteobacteria"], ["class", "c__Alphaproteobacteria"], ["order", "o__Nisaeales"], ["family", "f__Nisaeaceae"], ["genus", "g__UBA7326"]], 1]]], "TARA_PSE_MAG_00114_000000000050": [3215, 4, []], "TARA_PSE_MAG_00114_000000000051": [2855, 1, []], "TARA_PSE_MAG_00114_000000000052": [4603, 7, []], "TARA_PSE_MAG_00114_000000000053": [3563, 2, []], "TARA_PSE_MAG_00114_000000000054": [3186, 1, []], "TARA_PSE_MAG_00114_000000000055": [4319, 7, [[[["superkingdom", "d__Bacteria"], ["phylum", "p__Bacteroidota"], ["class", "c__Bacteroidia"], ["order", "o__Flavobacteriales"], ["family", "f__Crocinitomicaceae"], ["genus", "g__UBA952"]], 1]]], "TARA_PSE_MAG_00114_000000000056": [4492, 3, []], "TARA_PSE_MAG_00114_000000000057": [5048, 7, []], "TARA_PSE_MAG_00114_000000000058": [3867, 5, [[[["superkingdom", "d__Bacteria"], ["phylum", "p__Bacteroidota"], ["class", "c__Bacteroidia"], ["order", "o__Flavobacteriales"], ["family", "f__Flavobacteriaceae"], ["genus", "g__Muricauda"]], 5]]], "TARA_PSE_MAG_00114_000000000059": [4725, 4, []], "TARA_PSE_MAG_00114_000000000060": [6068, 9, []], "TARA_PSE_MAG_00114_000000000061": [2548, 3, []], "TARA_PSE_MAG_00114_000000000062": [2611, 3, []], "TARA_PSE_MAG_00114_000000000063": [3661, 4, []], "TARA_PSE_MAG_00114_000000000064": [4160, 1, []], "TARA_PSE_MAG_00114_000000000065": [4945, 2, []], "TARA_PSE_MAG_00114_000000000066": [2588, 5, []], "TARA_PSE_MAG_00114_000000000067": [4428, 5, []], "TARA_PSE_MAG_00114_000000000068": [3538, 1, []], "TARA_PSE_MAG_00114_000000000069": [5111, 5, []], "TARA_PSE_MAG_00114_000000000070": [3209, 3, [[[["superkingdom", "d__Bacteria"], ["phylum", "p__Proteobacteria"], ["class", "c__Alphaproteobacteria"], ["order", "o__Nisaeales"], ["family", "f__Nisaeaceae"], ["genus", "g__UBA7326"]], 3]]], "TARA_PSE_MAG_00114_000000000071": [7223, 10, []], "TARA_PSE_MAG_00114_000000000072": [3648, 5, []], "TARA_PSE_MAG_00114_000000000073": [2759, 4, []], "TARA_PSE_MAG_00114_000000000074": [2743, 3, []], "TARA_PSE_MAG_00114_000000000075": [6165, 10, []], "TARA_PSE_MAG_00114_000000000076": [3843, 2, []], "TARA_PSE_MAG_00114_000000000077": [5362, 8, [[[["superkingdom", "d__Bacteria"], ["phylum", "p__Proteobacteria"], ["class", "c__Gammaproteobacteria"], ["order", "o__Woeseiales"], ["family", "f__Woeseiaceae"], ["genus", "g__GCA-2685275"]], 4]]], "TARA_PSE_MAG_00114_000000000078": [4700, 2, []], "TARA_PSE_MAG_00114_000000000079": [3429, 2, []], "TARA_PSE_MAG_00114_000000000080": [4891, 6, []], "TARA_PSE_MAG_00114_000000000081": [3325, 3, []], "TARA_PSE_MAG_00114_000000000082": [4110, 4, []], "TARA_PSE_MAG_00114_000000000083": [3936, 5, []], "TARA_PSE_MAG_00114_000000000084": [3258, 4, []], "TARA_PSE_MAG_00114_000000000085": [3887, 2, []], "TARA_PSE_MAG_00114_000000000086": [3500, 4, [[[["superkingdom", "d__Bacteria"], ["phylum", "p__Bacteroidota"], ["class", "c__Bacteroidia"], ["order", "o__Flavobacteriales"], ["family", "f__Flavobacteriaceae"], ["genus", "g__SCGC-AAA160-P02"]], 1]]], "TARA_PSE_MAG_00114_000000000087": [2754, 2, []], "TARA_PSE_MAG_00114_000000000088": [4143, 6, []], "TARA_PSE_MAG_00114_000000000089": [6559, 10, []], "TARA_PSE_MAG_00114_000000000090": [4083, 4, []], "TARA_PSE_MAG_00114_000000000091": [2559, 3, []], "TARA_PSE_MAG_00114_000000000092": [5052, 2, []], "TARA_PSE_MAG_00114_000000000093": [3392, 3, []], "TARA_PSE_MAG_00114_000000000094": [3160, 3, []], "TARA_PSE_MAG_00114_000000000095": [2606, 1, []], "TARA_PSE_MAG_00114_000000000096": [3122, 3, []], "TARA_PSE_MAG_00114_000000000097": [4319, 5, []], "TARA_PSE_MAG_00114_000000000098": [2710, 2, []], "TARA_PSE_MAG_00114_000000000099": [3998, 6, []], "TARA_PSE_MAG_00114_000000000100": [2745, 4, []], "TARA_PSE_MAG_00114_000000000101": [5980, 9, []], "TARA_PSE_MAG_00114_000000000102": [4442, 2, []], "TARA_PSE_MAG_00114_000000000103": [5704, 2, []], "TARA_PSE_MAG_00114_000000000104": [4107, 7, []], "TARA_PSE_MAG_00114_000000000105": [3928, 3, []], "TARA_PSE_MAG_00114_000000000106": [2982, 1, []], "TARA_PSE_MAG_00114_000000000107": [3537, 1, []], "TARA_PSE_MAG_00114_000000000108": [3655, 1, []], "TARA_PSE_MAG_00114_000000000109": [3204, 2, []], "TARA_PSE_MAG_00114_000000000110": [10875, 8, []], "TARA_PSE_MAG_00114_000000000111": [3950, 9, []], "TARA_PSE_MAG_00114_000000000112": [2922, 1, [[[["superkingdom", "d__Bacteria"], ["phylum", "p__Bacteroidota"], ["class", "c__Bacteroidia"], ["order", "o__Flavobacteriales"], ["family", "f__Flavobacteriaceae"], ["genus", "g__Zunongwangia"]], 1]]], "TARA_PSE_MAG_00114_000000000113": [3598, 7, []], "TARA_PSE_MAG_00114_000000000114": [4027, 8, []], "TARA_PSE_MAG_00114_000000000115": [5972, 6, []], "TARA_PSE_MAG_00114_000000000116": [3873, 11, []], "TARA_PSE_MAG_00114_000000000117": [4608, 6, []], "TARA_PSE_MAG_00114_000000000118": [4927, 1, []], "TARA_PSE_MAG_00114_000000000119": [3089, 0, []], "TARA_PSE_MAG_00114_000000000120": [3307, 3, []], "TARA_PSE_MAG_00114_000000000121": [8983, 10, []], "TARA_PSE_MAG_00114_000000000122": [7421, 8, []], "TARA_PSE_MAG_00114_000000000123": [3220, 5, []], "TARA_PSE_MAG_00114_000000000124": [3158, 4, []], "TARA_PSE_MAG_00114_000000000125": [7698, 8, []], "TARA_PSE_MAG_00114_000000000126": [4697, 5, []], "TARA_PSE_MAG_00114_000000000127": [3957, 5, [[[["superkingdom", "d__Bacteria"], ["phylum", "p__Proteobacteria"], ["class", "c__Gammaproteobacteria"], ["order", "o__Pseudomonadales"], ["family", "f__Porticoccaceae"], ["genus", "g__Porticoccus"]], 5]]], "TARA_PSE_MAG_00114_000000000128": [4268, 5, []], "TARA_PSE_MAG_00114_000000000129": [2830, 3, []], "TARA_PSE_MAG_00114_000000000130": [3270, 4, []], "TARA_PSE_MAG_00114_000000000131": [7508, 9, []], "TARA_PSE_MAG_00114_000000000132": [4345, 10, []], "TARA_PSE_MAG_00114_000000000133": [4438, 3, []], "TARA_PSE_MAG_00114_000000000134": [6051, 5, []], "TARA_PSE_MAG_00114_000000000135": [3193, 2, []], "TARA_PSE_MAG_00114_000000000136": [4280, 3, []], "TARA_PSE_MAG_00114_000000000137": [2798, 4, []], "TARA_PSE_MAG_00114_000000000138": [4337, 6, []], "TARA_PSE_MAG_00114_000000000139": [4401, 6, [[[["superkingdom", "d__Bacteria"], ["phylum", "p__Bacteroidota"], ["class", "c__Bacteroidia"], ["order", "o__Flavobacteriales"], ["family", "f__Flavobacteriaceae"], ["genus", "g__Maribacter"]], 2], [[["superkingdom", "d__Bacteria"], ["phylum", "p__Bacteroidota"], ["class", "c__Bacteroidia"], ["order", "o__Flavobacteriales"], ["family", "f__Flavobacteriaceae"], ["genus", "g__LPB0138"]], 1]]], "TARA_PSE_MAG_00114_000000000140": [2707, 2, []], "TARA_PSE_MAG_00114_000000000141": [2851, 3, []], "TARA_PSE_MAG_00114_000000000142": [5292, 3, []], "TARA_PSE_MAG_00114_000000000143": [2753, 2, []], "TARA_PSE_MAG_00114_000000000144": [4554, 5, []], "TARA_PSE_MAG_00114_000000000145": [8625, 8, []], "TARA_PSE_MAG_00114_000000000146": [8483, 6, []], "TARA_PSE_MAG_00114_000000000147": [11405, 18, []], "TARA_PSE_MAG_00114_000000000148": [4412, 4, []], "TARA_PSE_MAG_00114_000000000149": [8940, 6, []], "TARA_PSE_MAG_00114_000000000150": [12298, 8, []], "TARA_PSE_MAG_00114_000000000151": [4051, 7, []], "TARA_PSE_MAG_00114_000000000152": [6912, 12, []], "TARA_PSE_MAG_00114_000000000153": [4144, 4, []], "TARA_PSE_MAG_00114_000000000154": [2896, 2, []], "TARA_PSE_MAG_00114_000000000155": [4196, 2, []], "TARA_PSE_MAG_00114_000000000156": [6541, 12, []], "TARA_PSE_MAG_00114_000000000157": [7308, 4, []], "TARA_PSE_MAG_00114_000000000158": [2602, 5, []], "TARA_PSE_MAG_00114_000000000159": [3711, 10, []], "TARA_PSE_MAG_00114_000000000160": [4160, 3, []], "TARA_PSE_MAG_00114_000000000161": [2632, 3, []], "TARA_PSE_MAG_00114_000000000162": [2912, 2, []], "TARA_PSE_MAG_00114_000000000163": [3845, 7, []], "TARA_PSE_MAG_00114_000000000164": [2569, 1, []], "TARA_PSE_MAG_00114_000000000165": [2895, 1, []], "TARA_PSE_MAG_00114_000000000166": [2893, 2, []], "TARA_PSE_MAG_00114_000000000167": [3509, 3, []], "TARA_PSE_MAG_00114_000000000168": [2878, 4, []], "TARA_PSE_MAG_00114_000000000169": [2943, 2, []], "TARA_PSE_MAG_00114_000000000170": [3233, 6, []], "TARA_PSE_MAG_00114_000000000171": [3635, 3, []], "TARA_PSE_MAG_00114_000000000172": [4698, 5, []], "TARA_PSE_MAG_00114_000000000173": [3748, 7, []], "TARA_PSE_MAG_00114_000000000174": [2574, 4, []], "TARA_PSE_MAG_00114_000000000175": [2784, 1, []], "TARA_PSE_MAG_00114_000000000176": [2627, 1, []], "TARA_PSE_MAG_00114_000000000177": [4227, 7, [[[["superkingdom", "d__Bacteria"], ["phylum", "p__Bacteroidota"], ["class", "c__Bacteroidia"], ["order", "o__Flavobacteriales"], ["family", "f__Flavobacteriaceae"], ["genus", "g__Sinomicrobium"]], 2], [[["superkingdom", "d__Bacteria"], ["phylum", "p__Bacteroidota"], ["class", "c__Bacteroidia"], ["order", "o__Flavobacteriales"], ["family", "f__Flavobacteriaceae"], ["genus", "g__Zunongwangia"]], 1]]], "TARA_PSE_MAG_00114_000000000178": [5772, 9, []], "TARA_PSE_MAG_00114_000000000179": [4235, 8, []], "TARA_PSE_MAG_00114_000000000180": [4884, 4, [[[["superkingdom", "d__Bacteria"], ["phylum", "p__Proteobacteria"], ["class", "c__Alphaproteobacteria"], ["order", "o__Nisaeales"], ["family", "f__Nisaeaceae"], ["genus", "g__UBA7326"]], 4]]], "TARA_PSE_MAG_00114_000000000181": [4919, 6, []], "TARA_PSE_MAG_00114_000000000182": [3437, 4, []], "TARA_PSE_MAG_00114_000000000183": [3889, 3, []], "TARA_PSE_MAG_00114_000000000184": [8189, 8, [[[["superkingdom", "d__Bacteria"], ["phylum", "p__Bacteroidota"], ["class", "c__Bacteroidia"], ["order", "o__Flavobacteriales"], ["family", "f__Flavobacteriaceae"], ["genus", "g__LPB0138"]], 1]]], "TARA_PSE_MAG_00114_000000000185": [2572, 1, []], "TARA_PSE_MAG_00114_000000000186": [4426, 9, []], "TARA_PSE_MAG_00114_000000000187": [3395, 4, []], "TARA_PSE_MAG_00114_000000000188": [3303, 2, []], "TARA_PSE_MAG_00114_000000000189": [2617, 4, []], "TARA_PSE_MAG_00114_000000000190": [4664, 6, []], "TARA_PSE_MAG_00114_000000000191": [8869, 11, []], "TARA_PSE_MAG_00114_000000000192": [7402, 9, []], "TARA_PSE_MAG_00114_000000000193": [5214, 7, []], "TARA_PSE_MAG_00114_000000000194": [4164, 2, []], "TARA_PSE_MAG_00114_000000000195": [11161, 12, []], "TARA_PSE_MAG_00114_000000000196": [3323, 3, []], "TARA_PSE_MAG_00114_000000000197": [2929, 4, []], "TARA_PSE_MAG_00114_000000000198": [3021, 3, []], "TARA_PSE_MAG_00114_000000000199": [7299, 9, []], "TARA_PSE_MAG_00114_000000000200": [2927, 3, []], "TARA_PSE_MAG_00114_000000000201": [6541, 8, []], "TARA_PSE_MAG_00114_000000000202": [3046, 3, []], "TARA_PSE_MAG_00114_000000000203": [3233, 3, []], "TARA_PSE_MAG_00114_000000000204": [5775, 3, []], "TARA_PSE_MAG_00114_000000000205": [18915, 21, [[[["superkingdom", "d__Bacteria"], ["phylum", "p__Bacteroidota"], ["class", "c__Bacteroidia"], ["order", "o__Flavobacteriales"], ["family", "f__Flavobacteriaceae"], ["genus", "g__Muricauda"]], 21]]], "TARA_PSE_MAG_00114_000000000206": [3257, 5, []], "TARA_PSE_MAG_00114_000000000207": [3720, 5, []], "TARA_PSE_MAG_00114_000000000208": [3163, 3, []], "TARA_PSE_MAG_00114_000000000209": [6087, 6, []], "TARA_PSE_MAG_00114_000000000210": [3305, 2, []], "TARA_PSE_MAG_00114_000000000211": [5658, 6, []], "TARA_PSE_MAG_00114_000000000212": [5346, 5, []], "TARA_PSE_MAG_00114_000000000213": [2968, 2, []], "TARA_PSE_MAG_00114_000000000214": [3339, 3, []], "TARA_PSE_MAG_00114_000000000215": [4961, 2, []], "TARA_PSE_MAG_00114_000000000216": [2569, 5, []], "TARA_PSE_MAG_00114_000000000217": [2524, 2, []], "TARA_PSE_MAG_00114_000000000218": [2755, 4, []], "TARA_PSE_MAG_00114_000000000219": [4015, 5, []], "TARA_PSE_MAG_00114_000000000220": [2506, 5, []], "TARA_PSE_MAG_00114_000000000221": [3351, 5, []], "TARA_PSE_MAG_00114_000000000222": [2623, 1, []], "TARA_PSE_MAG_00114_000000000223": [4330, 5, []], "TARA_PSE_MAG_00114_000000000224": [4252, 4, []], "TARA_PSE_MAG_00114_000000000225": [4500, 6, []], "TARA_PSE_MAG_00114_000000000226": [6048, 6, []], "TARA_PSE_MAG_00114_000000000227": [5946, 4, []], "TARA_PSE_MAG_00114_000000000228": [2727, 3, []], "TARA_PSE_MAG_00114_000000000229": [5644, 4, []], "TARA_PSE_MAG_00114_000000000230": [2643, 3, []], "TARA_PSE_MAG_00114_000000000231": [3364, 2, []], "TARA_PSE_MAG_00114_000000000232": [2781, 2, []], "TARA_PSE_MAG_00114_000000000233": [3294, 5, []], "TARA_PSE_MAG_00114_000000000234": [6215, 7, []], "TARA_PSE_MAG_00114_000000000235": [2564, 3, []], "TARA_PSE_MAG_00114_000000000236": [3134, 3, [[[["superkingdom", "d__Bacteria"], ["phylum", "p__Proteobacteria"], ["class", "c__Alphaproteobacteria"], ["order", "o__Nisaeales"], ["family", "f__Nisaeaceae"], ["genus", "g__UBA7326"]], 2]]], "TARA_PSE_MAG_00114_000000000237": [3087, 1, []], "TARA_PSE_MAG_00114_000000000238": [2921, 3, []], "TARA_PSE_MAG_00114_000000000239": [10994, 7, []], "TARA_PSE_MAG_00114_000000000240": [3066, 8, []], "TARA_PSE_MAG_00114_000000000241": [7446, 5, []], "TARA_PSE_MAG_00114_000000000242": [4053, 5, []], "TARA_PSE_MAG_00114_000000000243": [2511, 1, []], "TARA_PSE_MAG_00114_000000000244": [3226, 3, []], "TARA_PSE_MAG_00114_000000000245": [4021, 2, []], "TARA_PSE_MAG_00114_000000000246": [3427, 2, []], "TARA_PSE_MAG_00114_000000000247": [7180, 6, []], "TARA_PSE_MAG_00114_000000000248": [6168, 3, []], "TARA_PSE_MAG_00114_000000000249": [9929, 8, []], "TARA_PSE_MAG_00114_000000000250": [3129, 2, []], "TARA_PSE_MAG_00114_000000000251": [5622, 3, []], "TARA_PSE_MAG_00114_000000000252": [4299, 1, []], "TARA_PSE_MAG_00114_000000000253": [5578, 4, []], "TARA_PSE_MAG_00114_000000000254": [4226, 3, []], "TARA_PSE_MAG_00114_000000000255": [3157, 2, []], "TARA_PSE_MAG_00114_000000000256": [4086, 4, []], "TARA_PSE_MAG_00114_000000000257": [3584, 2, []], "TARA_PSE_MAG_00114_000000000258": [4728, 5, [[[["superkingdom", "d__Bacteria"], ["phylum", "p__Proteobacteria"], ["class", "c__Alphaproteobacteria"], ["order", "o__Nisaeales"], ["family", "f__Nisaeaceae"], ["genus", "g__UBA7326"]], 4]]], "TARA_PSE_MAG_00114_000000000259": [3928, 1, []], "TARA_PSE_MAG_00114_000000000260": [9195, 4, []], "TARA_PSE_MAG_00114_000000000261": [2997, 3, [[[["superkingdom", "d__Bacteria"], ["phylum", "p__Bacteroidota"], ["class", "c__Bacteroidia"], ["order", "o__Flavobacteriales"], ["family", "f__Flavobacteriaceae"], ["genus", "g__Zunongwangia"]], 1]]], "TARA_PSE_MAG_00114_000000000262": [6191, 6, []], "TARA_PSE_MAG_00114_000000000263": [3053, 2, []], "TARA_PSE_MAG_00114_000000000264": [3261, 2, []], "TARA_PSE_MAG_00114_000000000265": [4634, 5, []], "TARA_PSE_MAG_00114_000000000266": [2761, 2, []], "TARA_PSE_MAG_00114_000000000267": [4049, 2, []], "TARA_PSE_MAG_00114_000000000268": [2592, 1, []], "TARA_PSE_MAG_00114_000000000269": [4941, 4, []], "TARA_PSE_MAG_00114_000000000270": [5959, 8, []], "TARA_PSE_MAG_00114_000000000271": [3420, 3, []], "TARA_PSE_MAG_00114_000000000272": [5253, 2, []], "TARA_PSE_MAG_00114_000000000273": [3697, 1, []], "TARA_PSE_MAG_00114_000000000274": [3862, 7, []], "TARA_PSE_MAG_00114_000000000275": [3884, 8, []], "TARA_PSE_MAG_00114_000000000276": [4660, 5, []], "TARA_PSE_MAG_00114_000000000277": [2796, 3, []], "TARA_PSE_MAG_00114_000000000278": [4879, 11, []], "TARA_PSE_MAG_00114_000000000279": [2984, 4, []], "TARA_PSE_MAG_00114_000000000280": [2972, 4, []], "TARA_PSE_MAG_00114_000000000281": [3538, 2, []], "TARA_PSE_MAG_00114_000000000282": [6977, 11, []], "TARA_PSE_MAG_00114_000000000283": [3346, 4, []], "TARA_PSE_MAG_00114_000000000284": [3119, 6, []], "TARA_PSE_MAG_00114_000000000285": [3156, 4, []], "TARA_PSE_MAG_00114_000000000286": [4433, 7, []], "TARA_PSE_MAG_00114_000000000287": [2989, 1, []], "TARA_PSE_MAG_00114_000000000288": [3651, 3, [[[["superkingdom", "d__Bacteria"], ["phylum", "p__Bacteroidota"], ["class", "c__Bacteroidia"], ["order", "o__Flavobacteriales"], ["family", "f__Flavobacteriaceae"], ["genus", "g__Maribacter"]], 3]]], "TARA_PSE_MAG_00114_000000000289": [2847, 4, []], "TARA_PSE_MAG_00114_000000000290": [3534, 6, []], "TARA_PSE_MAG_00114_000000000291": [4659, 3, []], "TARA_PSE_MAG_00114_000000000292": [3173, 5, []], "TARA_PSE_MAG_00114_000000000293": [3942, 5, []], "TARA_PSE_MAG_00114_000000000294": [4003, 3, []], "TARA_PSE_MAG_00114_000000000295": [3844, 5, []], "TARA_PSE_MAG_00114_000000000296": [6999, 5, []], "TARA_PSE_MAG_00114_000000000297": [7569, 6, []], "TARA_PSE_MAG_00114_000000000298": [4405, 4, []], "TARA_PSE_MAG_00114_000000000299": [2823, 5, []], "TARA_PSE_MAG_00114_000000000300": [3421, 6, [[[["superkingdom", "d__Bacteria"], ["phylum", "p__Bacteroidota"], ["class", "c__Bacteroidia"], ["order", "o__Flavobacteriales"], ["family", "f__Flavobacteriaceae"], ["genus", "g__SCGC-AAA160-P02"]], 1]]], "TARA_PSE_MAG_00114_000000000301": [4883, 2, []], "TARA_PSE_MAG_00114_000000000302": [3802, 8, []], "TARA_PSE_MAG_00114_000000000303": [3613, 4, []], "TARA_PSE_MAG_00114_000000000304": [3251, 3, []], "TARA_PSE_MAG_00114_000000000305": [3720, 1, [[[["superkingdom", "d__Bacteria"], ["phylum", "p__Bacteroidota"], ["class", "c__Bacteroidia"], ["order", "o__Flavobacteriales"], ["family", "f__Flavobacteriaceae"], ["genus", "g__Salegentibacter"]], 1]]], "TARA_PSE_MAG_00114_000000000306": [2609, 3, []], "TARA_PSE_MAG_00114_000000000307": [4406, 3, []], "TARA_PSE_MAG_00114_000000000308": [3920, 4, []], "TARA_PSE_MAG_00114_000000000309": [3988, 3, []], "TARA_PSE_MAG_00114_000000000310": [5451, 2, []], "TARA_PSE_MAG_00114_000000000311": [4484, 4, []], "TARA_PSE_MAG_00114_000000000312": [3811, 4, []], "TARA_PSE_MAG_00114_000000000313": [2991, 2, []], "TARA_PSE_MAG_00114_000000000314": [3610, 3, []], "TARA_PSE_MAG_00114_000000000315": [5328, 4, []], "TARA_PSE_MAG_00114_000000000316": [3813, 3, []], "TARA_PSE_MAG_00114_000000000317": [2888, 2, []], "TARA_PSE_MAG_00114_000000000318": [3267, 6, []], "TARA_PSE_MAG_00114_000000000319": [4479, 3, []], "TARA_PSE_MAG_00114_000000000320": [3553, 2, []], "TARA_PSE_MAG_00114_000000000321": [2565, 1, []], "TARA_PSE_MAG_00114_000000000322": [4270, 4, []], "TARA_PSE_MAG_00114_000000000323": [4702, 7, []], "TARA_PSE_MAG_00114_000000000324": [3461, 2, []], "TARA_PSE_MAG_00114_000000000325": [5663, 9, []], "TARA_PSE_MAG_00114_000000000326": [4979, 8, []], "TARA_PSE_MAG_00114_000000000327": [4143, 5, []], "TARA_PSE_MAG_00114_000000000328": [6992, 7, []], "TARA_PSE_MAG_00114_000000000329": [4470, 2, []], "TARA_PSE_MAG_00114_000000000330": [11696, 11, [[[["superkingdom", "d__Bacteria"], ["phylum", "p__Bacteroidota"], ["class", "c__Bacteroidia"], ["order", "o__Flavobacteriales"], ["family", "f__Flavobacteriaceae"], ["genus", "g__Salegentibacter"]], 10]]], "TARA_PSE_MAG_00114_000000000331": [9866, 12, []], "TARA_PSE_MAG_00114_000000000332": [2937, 3, []], "TARA_PSE_MAG_00114_000000000333": [2743, 2, []], "TARA_PSE_MAG_00114_000000000334": [2806, 4, []], "TARA_PSE_MAG_00114_000000000335": [5775, 5, []], "TARA_PSE_MAG_00114_000000000336": [3167, 2, []], "TARA_PSE_MAG_00114_000000000337": [3441, 4, []], "TARA_PSE_MAG_00114_000000000338": [4587, 6, []], "TARA_PSE_MAG_00114_000000000339": [5272, 8, []], "TARA_PSE_MAG_00114_000000000340": [2678, 1, []], "TARA_PSE_MAG_00114_000000000341": [6276, 6, []], "TARA_PSE_MAG_00114_000000000342": [9813, 13, []], "TARA_PSE_MAG_00114_000000000343": [4783, 1, []], "TARA_PSE_MAG_00114_000000000344": [2778, 2, [[[["superkingdom", "d__Bacteria"], ["phylum", "p__Proteobacteria"], ["class", "c__Alphaproteobacteria"], ["order", "o__Nisaeales"], ["family", "f__Nisaeaceae"], ["genus", "g__UBA7326"]], 2]]], "TARA_PSE_MAG_00114_000000000345": [3849, 7, []], "TARA_PSE_MAG_00114_000000000346": [2866, 0, []], "TARA_PSE_MAG_00114_000000000347": [2919, 5, []], "TARA_PSE_MAG_00114_000000000348": [3968, 6, []], "TARA_PSE_MAG_00114_000000000349": [5928, 4, []], "TARA_PSE_MAG_00114_000000000350": [2948, 2, []], "TARA_PSE_MAG_00114_000000000351": [5847, 5, []], "TARA_PSE_MAG_00114_000000000352": [5996, 6, [[[["superkingdom", "d__Bacteria"], ["phylum", "p__Bacteroidota"], ["class", "c__Bacteroidia"], ["order", "o__Flavobacteriales"], ["family", "f__Flavobacteriaceae"], ["genus", "g__Muricauda"]], 6]]], "TARA_PSE_MAG_00114_000000000353": [3923, 6, []], "TARA_PSE_MAG_00114_000000000354": [2937, 1, []], "TARA_PSE_MAG_00114_000000000355": [2615, 2, [[[["superkingdom", "d__Bacteria"], ["phylum", "p__Proteobacteria"], ["class", "c__Alphaproteobacteria"], ["order", "o__Nisaeales"], ["family", "f__Nisaeaceae"], ["genus", "g__UBA7326"]], 2]]], "TARA_PSE_MAG_00114_000000000356": [13304, 10, [[[["superkingdom", "d__Bacteria"], ["phylum", "p__Bacteroidota"], ["class", "c__Bacteroidia"], ["order", "o__Flavobacteriales"], ["family", "f__Flavobacteriaceae"], ["genus", "g__Zunongwangia"]], 1]]], "TARA_PSE_MAG_00114_000000000357": [5118, 5, []], "TARA_PSE_MAG_00114_000000000358": [2542, 1, [[[["superkingdom", "d__Bacteria"], ["phylum", "p__Bacteroidota"], ["class", "c__Bacteroidia"], ["order", "o__Flavobacteriales"], ["family", "f__UBA7430"], ["genus", "g__UBA6772"]], 1]]], "TARA_PSE_MAG_00114_000000000359": [5291, 6, []], "TARA_PSE_MAG_00114_000000000360": [3523, 6, []], "TARA_PSE_MAG_00114_000000000361": [3658, 4, []], "TARA_PSE_MAG_00114_000000000362": [4136, 4, []], "TARA_PSE_MAG_00114_000000000363": [9560, 11, []], "TARA_PSE_MAG_00114_000000000364": [4023, 4, []], "TARA_PSE_MAG_00114_000000000365": [2684, 1, []], "TARA_PSE_MAG_00114_000000000366": [2872, 3, []], "TARA_PSE_MAG_00114_000000000367": [3475, 0, []], "TARA_PSE_MAG_00114_000000000368": [8264, 12, [[[["superkingdom", "d__Bacteria"], ["phylum", "p__Bacteroidota"], ["class", "c__Bacteroidia"], ["order", "o__Flavobacteriales"], ["family", "f__Flavobacteriaceae"], ["genus", "g__Zunongwangia"]], 12]]], "TARA_PSE_MAG_00114_000000000369": [4033, 3, []], "TARA_PSE_MAG_00114_000000000370": [2630, 2, []], "TARA_PSE_MAG_00114_000000000371": [4715, 5, []], "TARA_PSE_MAG_00114_000000000372": [3717, 5, []], "TARA_PSE_MAG_00114_000000000373": [2973, 3, [[[["superkingdom", "d__Bacteria"], ["phylum", "p__Bacteroidota"], ["class", "c__Bacteroidia"], ["order", "o__Flavobacteriales"], ["family", "f__Flavobacteriaceae"], ["genus", "g__Sinomicrobium"]], 1]]], "TARA_PSE_MAG_00114_000000000374": [3110, 0, []], "TARA_PSE_MAG_00114_000000000375": [2728, 3, []], "TARA_PSE_MAG_00114_000000000376": [2693, 1, [[[["superkingdom", "d__Bacteria"], ["phylum", "p__Proteobacteria"], ["class", "c__Alphaproteobacteria"], ["order", "o__Nisaeales"], ["family", "f__Nisaeaceae"], ["genus", "g__UBA7326"]], 1]]], "TARA_PSE_MAG_00114_000000000377": [8482, 9, []], "TARA_PSE_MAG_00114_000000000378": [4134, 8, []], "TARA_PSE_MAG_00114_000000000379": [4158, 4, []], "TARA_PSE_MAG_00114_000000000380": [3803, 4, []], "TARA_PSE_MAG_00114_000000000381": [6477, 7, []], "TARA_PSE_MAG_00114_000000000382": [3709, 1, []], "TARA_PSE_MAG_00114_000000000383": [2594, 3, []], "TARA_PSE_MAG_00114_000000000384": [5643, 7, []], "TARA_PSE_MAG_00114_000000000385": [5519, 8, []], "TARA_PSE_MAG_00114_000000000386": [3587, 0, []], "TARA_PSE_MAG_00114_000000000387": [2643, 2, []], "TARA_PSE_MAG_00114_000000000388": [4183, 3, [[[["superkingdom", "d__Bacteria"], ["phylum", "p__Proteobacteria"], ["class", "c__Alphaproteobacteria"], ["order", "o__Nisaeales"], ["family", "f__Nisaeaceae"], ["genus", "g__UBA7326"]], 3]]], "TARA_PSE_MAG_00114_000000000389": [3759, 2, []], "TARA_PSE_MAG_00114_000000000390": [4213, 5, []], "TARA_PSE_MAG_00114_000000000391": [7217, 5, []], "TARA_PSE_MAG_00114_000000000392": [2791, 3, []], "TARA_PSE_MAG_00114_000000000393": [4933, 5, []], "TARA_PSE_MAG_00114_000000000394": [2512, 0, []], "TARA_PSE_MAG_00114_000000000395": [6932, 7, []], "TARA_PSE_MAG_00114_000000000396": [3587, 1, []], "TARA_PSE_MAG_00114_000000000397": [4397, 4, []], "TARA_PSE_MAG_00114_000000000398": [4499, 3, []], "TARA_PSE_MAG_00114_000000000399": [3595, 2, []], "TARA_PSE_MAG_00114_000000000400": [2879, 2, []], "TARA_PSE_MAG_00114_000000000401": [4962, 2, []], "TARA_PSE_MAG_00114_000000000402": [2998, 3, []], "TARA_PSE_MAG_00114_000000000403": [9118, 12, []], "TARA_PSE_MAG_00114_000000000404": [3344, 2, []], "TARA_PSE_MAG_00114_000000000405": [3255, 4, []], "TARA_PSE_MAG_00114_000000000406": [11399, 14, [[[["superkingdom", "d__Bacteria"], ["phylum", "p__Proteobacteria"], ["class", "c__Alphaproteobacteria"], ["order", "o__Nisaeales"], ["family", "f__Nisaeaceae"], ["genus", "g__UBA7326"]], 13]]], "TARA_PSE_MAG_00114_000000000407": [3016, 4, [[[["superkingdom", "d__Bacteria"], ["phylum", "p__Proteobacteria"], ["class", "c__Alphaproteobacteria"], ["order", "o__Nisaeales"], ["family", "f__Nisaeaceae"], ["genus", "g__UBA7326"]], 3]]], "TARA_PSE_MAG_00114_000000000408": [2754, 4, []], "TARA_PSE_MAG_00114_000000000409": [2549, 2, []], "TARA_PSE_MAG_00114_000000000410": [8706, 15, []], "TARA_PSE_MAG_00114_000000000411": [3048, 3, [[[["superkingdom", "d__Bacteria"], ["phylum", "p__Bacteroidota"], ["class", "c__Bacteroidia"], ["order", "o__Flavobacteriales"], ["family", "f__Flavobacteriaceae"], ["genus", "g__Sinomicrobium"]], 2]]], "TARA_PSE_MAG_00114_000000000412": [9283, 16, []], "TARA_PSE_MAG_00114_000000000413": [6125, 8, []], "TARA_PSE_MAG_00114_000000000414": [4228, 3, []], "TARA_PSE_MAG_00114_000000000415": [4459, 9, []], "TARA_PSE_MAG_00114_000000000416": [2536, 5, []], "TARA_PSE_MAG_00114_000000000417": [2946, 3, []], "TARA_PSE_MAG_00114_000000000418": [14996, 18, []], "TARA_PSE_MAG_00114_000000000419": [2814, 1, []], "TARA_PSE_MAG_00114_000000000420": [5202, 5, []], "TARA_PSE_MAG_00114_000000000421": [7160, 9, []], "TARA_PSE_MAG_00114_000000000422": [2823, 3, []], "TARA_PSE_MAG_00114_000000000423": [3364, 5, []], "TARA_PSE_MAG_00114_000000000424": [2722, 2, []], "TARA_PSE_MAG_00114_000000000425": [3508, 5, [[[["superkingdom", "d__Bacteria"], ["phylum", "p__Bacteroidota"], ["class", "c__Bacteroidia"], ["order", "o__Flavobacteriales"], ["family", "f__Flavobacteriaceae"], ["genus", "g__Zunongwangia"]], 1]]], "TARA_PSE_MAG_00114_000000000426": [6915, 4, []], "TARA_PSE_MAG_00114_000000000427": [3623, 4, []], "TARA_PSE_MAG_00114_000000000428": [2997, 2, []], "TARA_PSE_MAG_00114_000000000429": [3040, 4, []], "TARA_PSE_MAG_00114_000000000430": [7632, 11, []], "TARA_PSE_MAG_00114_000000000431": [3933, 5, []], "TARA_PSE_MAG_00114_000000000432": [4466, 1, []], "TARA_PSE_MAG_00114_000000000433": [3468, 3, []], "TARA_PSE_MAG_00114_000000000434": [3208, 4, []], "TARA_PSE_MAG_00114_000000000435": [5670, 6, []], "TARA_PSE_MAG_00114_000000000436": [3197, 2, []], "TARA_PSE_MAG_00114_000000000437": [6510, 16, []], "TARA_PSE_MAG_00114_000000000438": [11273, 18, []], "TARA_PSE_MAG_00114_000000000439": [7506, 5, []], "TARA_PSE_MAG_00114_000000000440": [5095, 9, []], "TARA_PSE_MAG_00114_000000000441": [3161, 3, []], "TARA_PSE_MAG_00114_000000000442": [3139, 4, []], "TARA_PSE_MAG_00114_000000000443": [4277, 4, []], "TARA_PSE_MAG_00114_000000000444": [2540, 3, []], "TARA_PSE_MAG_00114_000000000445": [3229, 3, []], "TARA_PSE_MAG_00114_000000000446": [2656, 3, []], "TARA_PSE_MAG_00114_000000000447": [3011, 4, [[[["superkingdom", "d__Bacteria"], ["phylum", "p__Proteobacteria"], ["class", "c__Alphaproteobacteria"], ["order", "o__Nisaeales"], ["family", "f__Nisaeaceae"], ["genus", "g__UBA7326"]], 4]]], "TARA_PSE_MAG_00114_000000000448": [5468, 8, []], "TARA_PSE_MAG_00114_000000000449": [9263, 8, []], "TARA_PSE_MAG_00114_000000000450": [4407, 2, []], "TARA_PSE_MAG_00114_000000000451": [3359, 3, []], "TARA_PSE_MAG_00114_000000000452": [6277, 5, [[[["superkingdom", "d__Bacteria"], ["phylum", "p__Proteobacteria"], ["class", "c__Gammaproteobacteria"], ["order", "o__Woeseiales"], ["family", "f__Woeseiaceae"], ["genus", "g__GCA-2685275"]], 1]]], "TARA_PSE_MAG_00114_000000000453": [4560, 4, []], "TARA_PSE_MAG_00114_000000000454": [8294, 9, []], "TARA_PSE_MAG_00114_000000000455": [6672, 14, []], "TARA_PSE_MAG_00114_000000000456": [3455, 5, []], "TARA_PSE_MAG_00114_000000000457": [4618, 3, []], "TARA_PSE_MAG_00114_000000000458": [5627, 7, []], "TARA_PSE_MAG_00114_000000000459": [3828, 3, []], "TARA_PSE_MAG_00114_000000000460": [2612, 4, []], "TARA_PSE_MAG_00114_000000000461": [3029, 5, [[[["superkingdom", "d__Bacteria"], ["phylum", "p__Bacteroidota"], ["class", "c__Bacteroidia"], ["order", "o__Flavobacteriales"], ["family", "f__Flavobacteriaceae"], ["genus", "g__Salegentibacter"]], 1]]], "TARA_PSE_MAG_00114_000000000462": [3674, 10, []], "TARA_PSE_MAG_00114_000000000463": [9281, 6, []], "TARA_PSE_MAG_00114_000000000464": [3890, 4, []], "TARA_PSE_MAG_00114_000000000465": [2687, 3, []], "TARA_PSE_MAG_00114_000000000466": [5043, 8, []], "TARA_PSE_MAG_00114_000000000467": [3729, 8, []], "TARA_PSE_MAG_00114_000000000468": [3168, 5, [[[["superkingdom", "d__Bacteria"], ["phylum", "p__Bacteroidota"], ["class", "c__Bacteroidia"], ["order", "o__Flavobacteriales"], ["family", "f__Flavobacteriaceae"], ["genus", "g__Zunongwangia"]], 5]]], "TARA_PSE_MAG_00114_000000000469": [4483, 2, []], "TARA_PSE_MAG_00114_000000000470": [3914, 1, []], "TARA_PSE_MAG_00114_000000000471": [7070, 5, []], "TARA_PSE_MAG_00114_000000000472": [3980, 4, []], "TARA_PSE_MAG_00114_000000000473": [2605, 2, []], "TARA_PSE_MAG_00114_000000000474": [7541, 9, []], "TARA_PSE_MAG_00114_000000000475": [4214, 7, [[[["superkingdom", "d__Bacteria"], ["phylum", "p__Bacteroidota"], ["class", "c__Bacteroidia"], ["order", "o__Flavobacteriales"], ["family", "f__Flavobacteriaceae"], ["genus", "g__Bizionia_B"]], 3]]], "TARA_PSE_MAG_00114_000000000476": [4073, 4, []], "TARA_PSE_MAG_00114_000000000477": [5044, 9, []], "TARA_PSE_MAG_00114_000000000478": [3413, 2, []], "TARA_PSE_MAG_00114_000000000479": [9696, 9, []], "TARA_PSE_MAG_00114_000000000480": [7374, 3, [[[["superkingdom", "d__Bacteria"], ["phylum", "p__Bacteroidota"], ["class", "c__Bacteroidia"], ["order", "o__Flavobacteriales"], ["family", "f__Flavobacteriaceae"], ["genus", "g__Muricauda"]], 2]]], "TARA_PSE_MAG_00114_000000000481": [3174, 6, [[[["superkingdom", "d__Bacteria"], ["phylum", "p__Proteobacteria"], ["class", "c__Alphaproteobacteria"], ["order", "o__Nisaeales"], ["family", "f__Nisaeaceae"], ["genus", "g__UBA7326"]], 5]]], "TARA_PSE_MAG_00114_000000000482": [6978, 6, [[[["superkingdom", "d__Bacteria"], ["phylum", "p__Bacteroidota"], ["class", "c__Bacteroidia"], ["order", "o__Flavobacteriales"], ["family", "f__Flavobacteriaceae"], ["genus", "g__Zunongwangia"]], 3]]], "TARA_PSE_MAG_00114_000000000483": [3345, 2, []], "TARA_PSE_MAG_00114_000000000484": [4728, 3, []], "TARA_PSE_MAG_00114_000000000485": [3362, 2, []], "TARA_PSE_MAG_00114_000000000486": [4517, 3, []], "TARA_PSE_MAG_00114_000000000487": [2809, 0, []], "TARA_PSE_MAG_00114_000000000488": [5314, 4, []], "TARA_PSE_MAG_00114_000000000489": [4814, 4, []], "TARA_PSE_MAG_00114_000000000490": [8558, 8, []], "TARA_PSE_MAG_00114_000000000491": [8102, 4, [[[["superkingdom", "d__Bacteria"], ["phylum", "p__Bacteroidota"], ["class", "c__Bacteroidia"], ["order", "o__Flavobacteriales"], ["family", "f__UBA7430"], ["genus", "g__UBA6772"]], 4]]], "TARA_PSE_MAG_00114_000000000492": [8926, 6, []], "TARA_PSE_MAG_00114_000000000493": [3584, 4, []], "TARA_PSE_MAG_00114_000000000494": [13385, 16, []], "TARA_PSE_MAG_00114_000000000495": [2893, 4, []], "TARA_PSE_MAG_00114_000000000496": [2702, 3, []], "TARA_PSE_MAG_00114_000000000497": [7113, 6, [[[["superkingdom", "d__Bacteria"], ["phylum", "p__Bacteroidota"], ["class", "c__Bacteroidia"], ["order", "o__Flavobacteriales"], ["family", "f__Flavobacteriaceae"], ["genus", "g__Salegentibacter"]], 6]]], "TARA_PSE_MAG_00114_000000000498": [2535, 2, []], "TARA_PSE_MAG_00114_000000000499": [3912, 2, []], "TARA_PSE_MAG_00114_000000000500": [5826, 7, []], "TARA_PSE_MAG_00114_000000000501": [2623, 1, []], "TARA_PSE_MAG_00114_000000000502": [13955, 13, []]}