{"TARA_ASW_MAG_00014_000000000001": [2797, 0, []], "TARA_ASW_MAG_00014_000000000002": [2914, 0, []], "TARA_ASW_MAG_00014_000000000003": [5385, 5, [[[["superkingdom", "d__Bacteria"], ["phylum", "p__Proteobacteria"], ["class", "c__Gammaproteobacteria"], ["order", "o__Pseudomonadales"], ["family", "f__HTCC2089"], ["genus", "g__UBA4421"]], 1]]], "TARA_ASW_MAG_00014_000000000004": [3402, 1, [[[["superkingdom", "d__Bacteria"], ["phylum", "p__Proteobacteria"], ["class", "c__Gammaproteobacteria"], ["order", "o__Pseudomonadales"], ["family", "f__HTCC2089"], ["genus", "g__UBA4421"]], 1]]], "TARA_ASW_MAG_00014_000000000005": [2511, 1, []], "TARA_ASW_MAG_00014_000000000006": [3274, 5, [[[["superkingdom", "d__Bacteria"], ["phylum", "p__Proteobacteria"], ["class", "c__Gammaproteobacteria"], ["order", "o__Pseudomonadales"], ["family", "f__HTCC2089"], ["genus", "g__UBA4421"]], 1]]], "TARA_ASW_MAG_00014_000000000007": [4828, 10, [[[["superkingdom", "d__Bacteria"], ["phylum", "p__Proteobacteria"], ["class", "c__Gammaproteobacteria"], ["order", "o__Pseudomonadales"], ["family", "f__HTCC2089"], ["genus", "g__UBA4421"]], 2]]], "TARA_ASW_MAG_00014_000000000008": [4640, 3, []], "TARA_ASW_MAG_00014_000000000009": [2985, 3, []], "TARA_ASW_MAG_00014_000000000010": [2763, 6, []], "TARA_ASW_MAG_00014_000000000011": [2834, 5, []], "TARA_ASW_MAG_00014_000000000012": [4896, 5, [[[["superkingdom", "d__Bacteria"], ["phylum", "p__Proteobacteria"], ["class", "c__Gammaproteobacteria"], ["order", "o__Pseudomonadales"], ["family", "f__HTCC2089"], ["genus", "g__UBA4421"]], 2]]], "TARA_ASW_MAG_00014_000000000013": [3117, 4, [[[["superkingdom", "d__Bacteria"], ["phylum", "p__Proteobacteria"], ["class", "c__Gammaproteobacteria"], ["order", "o__Pseudomonadales"], ["family", "f__HTCC2089"], ["genus", "g__UBA4421"]], 1]]], "TARA_ASW_MAG_00014_000000000014": [4493, 6, [[[["superkingdom", "d__Bacteria"], ["phylum", "p__Proteobacteria"], ["class", "c__Gammaproteobacteria"], ["order", "o__Pseudomonadales"], ["family", "f__HTCC2089"], ["genus", "g__UBA4421"]], 1]]], "TARA_ASW_MAG_00014_000000000015": [6524, 5, []], "TARA_ASW_MAG_00014_000000000016": [12478, 12, [[[["superkingdom", "d__Bacteria"], ["phylum", "p__Proteobacteria"], ["class", "c__Gammaproteobacteria"], ["order", "o__Pseudomonadales"], ["family", "f__HTCC2089"], ["genus", "g__UBA4421"]], 3]]], "TARA_ASW_MAG_00014_000000000017": [3553, 2, []], "TARA_ASW_MAG_00014_000000000018": [3207, 2, []], "TARA_ASW_MAG_00014_000000000019": [4305, 6, []], "TARA_ASW_MAG_00014_000000000020": [4310, 3, [[[["superkingdom", "d__Bacteria"], ["phylum", "p__Proteobacteria"], ["class", "c__Gammaproteobacteria"], ["order", "o__Pseudomonadales"], ["family", "f__HTCC2089"], ["genus", "g__UBA4421"]], 2]]], "TARA_ASW_MAG_00014_000000000021": [10239, 7, [[[["superkingdom", "d__Bacteria"], ["phylum", "p__Proteobacteria"], ["class", "c__Gammaproteobacteria"], ["order", "o__Pseudomonadales"], ["family", "f__HTCC2089"], ["genus", "g__UBA4421"]], 5]]], "TARA_ASW_MAG_00014_000000000022": [2693, 0, []], "TARA_ASW_MAG_00014_000000000023": [3261, 0, []], "TARA_ASW_MAG_00014_000000000024": [7047, 7, []], "TARA_ASW_MAG_00014_000000000025": [2645, 2, [[[["superkingdom", "d__Bacteria"], ["phylum", "p__Proteobacteria"], ["class", "c__Gammaproteobacteria"], ["order", "o__Pseudomonadales"], ["family", "f__HTCC2089"], ["genus", "g__UBA4421"]], 2]]], "TARA_ASW_MAG_00014_000000000026": [7707, 6, [[[["superkingdom", "d__Bacteria"], ["phylum", "p__Proteobacteria"], ["class", "c__Gammaproteobacteria"], ["order", "o__Pseudomonadales"], ["family", "f__HTCC2089"], ["genus", "g__UBA4421"]], 1]]], "TARA_ASW_MAG_00014_000000000027": [3938, 4, [[[["superkingdom", "d__Bacteria"], ["phylum", "p__Proteobacteria"], ["class", "c__Gammaproteobacteria"], ["order", "o__Pseudomonadales"], ["family", "f__HTCC2089"], ["genus", "g__UBA4421"]], 1]]], "TARA_ASW_MAG_00014_000000000028": [3781, 5, [[[["superkingdom", "d__Bacteria"], ["phylum", "p__Proteobacteria"], ["class", "c__Gammaproteobacteria"], ["order", "o__Pseudomonadales"], ["family", "f__HTCC2089"], ["genus", "g__UBA4421"]], 2]]], "TARA_ASW_MAG_00014_000000000029": [3069, 2, []], "TARA_ASW_MAG_00014_000000000030": [3317, 3, []], "TARA_ASW_MAG_00014_000000000031": [11352, 14, [[[["superkingdom", "d__Bacteria"], ["phylum", "p__Proteobacteria"], ["class", "c__Gammaproteobacteria"], ["order", "o__Pseudomonadales"], ["family", "f__HTCC2089"], ["genus", "g__UBA4421"]], 1]]], "TARA_ASW_MAG_00014_000000000032": [7596, 9, []], "TARA_ASW_MAG_00014_000000000033": [3496, 4, [[[["superkingdom", "d__Bacteria"], ["phylum", "p__Proteobacteria"], ["class", "c__Gammaproteobacteria"], ["order", "o__Pseudomonadales"], ["family", "f__HTCC2089"], ["genus", "g__UBA4421"]], 1]]], "TARA_ASW_MAG_00014_000000000034": [5695, 8, [[[["superkingdom", "d__Bacteria"], ["phylum", "p__Proteobacteria"], ["class", "c__Gammaproteobacteria"], ["order", "o__Pseudomonadales"], ["family", "f__HTCC2089"], ["genus", "g__UBA4421"]], 2]]], "TARA_ASW_MAG_00014_000000000035": [3252, 5, [[[["superkingdom", "d__Bacteria"], ["phylum", "p__Proteobacteria"], ["class", "c__Gammaproteobacteria"], ["order", "o__Pseudomonadales"], ["family", "f__HTCC2089"], ["genus", "g__UBA4421"]], 1]]], "TARA_ASW_MAG_00014_000000000036": [5679, 5, [[[["superkingdom", "d__Bacteria"], ["phylum", "p__Proteobacteria"], ["class", "c__Gammaproteobacteria"], ["order", "o__Pseudomonadales"], ["family", "f__HTCC2089"], ["genus", "g__UBA4421"]], 1]]], "TARA_ASW_MAG_00014_000000000037": [4309, 5, [[[["superkingdom", "d__Bacteria"], ["phylum", "p__Proteobacteria"], ["class", "c__Gammaproteobacteria"], ["order", "o__Pseudomonadales"], ["family", "f__HTCC2089"], ["genus", "g__UBA4421"]], 2]]], "TARA_ASW_MAG_00014_000000000038": [3246, 3, [[[["superkingdom", "d__Bacteria"], ["phylum", "p__Proteobacteria"], ["class", "c__Gammaproteobacteria"], ["order", "o__Pseudomonadales"], ["family", "f__HTCC2089"], ["genus", "g__UBA4421"]], 1]]], "TARA_ASW_MAG_00014_000000000039": [4378, 5, []], "TARA_ASW_MAG_00014_000000000040": [2989, 3, [[[["superkingdom", "d__Bacteria"], ["phylum", "p__Proteobacteria"], ["class", "c__Gammaproteobacteria"], ["order", "o__Pseudomonadales"], ["family", "f__HTCC2089"], ["genus", "g__UBA4421"]], 1]]], "TARA_ASW_MAG_00014_000000000041": [3105, 3, [[[["superkingdom", "d__Bacteria"], ["phylum", "p__Proteobacteria"], ["class", "c__Gammaproteobacteria"], ["order", "o__Pseudomonadales"], ["family", "f__HTCC2089"], ["genus", "g__UBA4421"]], 2]]], "TARA_ASW_MAG_00014_000000000042": [5184, 10, [[[["superkingdom", "d__Bacteria"], ["phylum", "p__Proteobacteria"], ["class", "c__Gammaproteobacteria"], ["order", "o__Pseudomonadales"], ["family", "f__HTCC2089"], ["genus", "g__UBA4421"]], 2]]], "TARA_ASW_MAG_00014_000000000043": [2695, 3, []], "TARA_ASW_MAG_00014_000000000044": [5197, 7, [[[["superkingdom", "d__Bacteria"], ["phylum", "p__Proteobacteria"], ["class", "c__Gammaproteobacteria"], ["order", "o__Pseudomonadales"], ["family", "f__HTCC2089"], ["genus", "g__UBA4421"]], 1]]], "TARA_ASW_MAG_00014_000000000045": [2532, 1, []], "TARA_ASW_MAG_00014_000000000046": [16254, 18, []], "TARA_ASW_MAG_00014_000000000047": [6740, 8, []], "TARA_ASW_MAG_00014_000000000048": [4980, 5, []], "TARA_ASW_MAG_00014_000000000049": [4615, 4, [[[["superkingdom", "d__Bacteria"], ["phylum", "p__Proteobacteria"], ["class", "c__Gammaproteobacteria"], ["order", "o__Pseudomonadales"], ["family", "f__HTCC2089"], ["genus", "g__UBA4421"]], 1]]], "TARA_ASW_MAG_00014_000000000050": [6382, 3, [[[["superkingdom", "d__Bacteria"], ["phylum", "p__Proteobacteria"], ["class", "c__Gammaproteobacteria"], ["order", "o__Pseudomonadales"], ["family", "f__HTCC2089"], ["genus", "g__UBA4421"]], 1]]], "TARA_ASW_MAG_00014_000000000051": [3613, 1, [[[["superkingdom", "d__Bacteria"], ["phylum", "p__Proteobacteria"], ["class", "c__Gammaproteobacteria"], ["order", "o__Pseudomonadales"], ["family", "f__HTCC2089"], ["genus", "g__UBA4421"]], 1]]], "TARA_ASW_MAG_00014_000000000052": [3516, 1, []], "TARA_ASW_MAG_00014_000000000053": [3310, 9, [[[["superkingdom", "d__Bacteria"], ["phylum", "p__Proteobacteria"], ["class", "c__Gammaproteobacteria"], ["order", "o__Pseudomonadales"], ["family", "f__HTCC2089"], ["genus", "g__UBA4421"]], 2]]], "TARA_ASW_MAG_00014_000000000054": [2741, 1, []], "TARA_ASW_MAG_00014_000000000055": [5107, 10, [[[["superkingdom", "d__Bacteria"], ["phylum", "p__Proteobacteria"], ["class", "c__Gammaproteobacteria"], ["order", "o__Pseudomonadales"], ["family", "f__HTCC2089"], ["genus", "g__UBA4421"]], 1]]], "TARA_ASW_MAG_00014_000000000056": [4588, 6, [[[["superkingdom", "d__Bacteria"], ["phylum", "p__Proteobacteria"], ["class", "c__Gammaproteobacteria"], ["order", "o__Pseudomonadales"], ["family", "f__HTCC2089"], ["genus", "g__UBA4421"]], 2]]], "TARA_ASW_MAG_00014_000000000057": [2769, 3, []], "TARA_ASW_MAG_00014_000000000058": [3588, 3, []], "TARA_ASW_MAG_00014_000000000059": [2874, 3, []], "TARA_ASW_MAG_00014_000000000060": [4050, 6, []], "TARA_ASW_MAG_00014_000000000061": [3455, 3, []], "TARA_ASW_MAG_00014_000000000062": [3884, 2, []], "TARA_ASW_MAG_00014_000000000063": [3881, 3, []], "TARA_ASW_MAG_00014_000000000064": [4154, 3, [[[["superkingdom", "d__Bacteria"], ["phylum", "p__Proteobacteria"], ["class", "c__Gammaproteobacteria"], ["order", "o__Pseudomonadales"], ["family", "f__HTCC2089"], ["genus", "g__UBA4421"]], 1]]], "TARA_ASW_MAG_00014_000000000065": [3043, 5, [[[["superkingdom", "d__Bacteria"], ["phylum", "p__Proteobacteria"], ["class", "c__Gammaproteobacteria"], ["order", "o__Pseudomonadales"], ["family", "f__HTCC2089"], ["genus", "g__UBA4421"]], 2]]], "TARA_ASW_MAG_00014_000000000066": [2749, 2, [[[["superkingdom", "d__Bacteria"], ["phylum", "p__Proteobacteria"], ["class", "c__Gammaproteobacteria"], ["order", "o__Pseudomonadales"], ["family", "f__HTCC2089"], ["genus", "g__UBA4421"]], 1]]], "TARA_ASW_MAG_00014_000000000067": [3060, 4, [[[["superkingdom", "d__Bacteria"], ["phylum", "p__Proteobacteria"], ["class", "c__Gammaproteobacteria"], ["order", "o__Pseudomonadales"], ["family", "f__HTCC2089"], ["genus", "g__UBA4421"]], 2]]], "TARA_ASW_MAG_00014_000000000068": [3118, 1, []], "TARA_ASW_MAG_00014_000000000069": [3153, 4, []], "TARA_ASW_MAG_00014_000000000070": [9347, 5, [[[["superkingdom", "d__Bacteria"], ["phylum", "p__Proteobacteria"], ["class", "c__Gammaproteobacteria"], ["order", "o__Pseudomonadales"], ["family", "f__HTCC2089"], ["genus", "g__UBA4421"]], 1]]], "TARA_ASW_MAG_00014_000000000071": [7152, 12, [[[["superkingdom", "d__Bacteria"], ["phylum", "p__Proteobacteria"], ["class", "c__Gammaproteobacteria"], ["order", "o__Pseudomonadales"], ["family", "f__HTCC2089"], ["genus", "g__UBA4421"]], 2]]], "TARA_ASW_MAG_00014_000000000072": [2574, 2, []], "TARA_ASW_MAG_00014_000000000073": [5968, 10, [[[["superkingdom", "d__Bacteria"], ["phylum", "p__Proteobacteria"], ["class", "c__Gammaproteobacteria"], ["order", "o__Pseudomonadales"], ["family", "f__HTCC2089"], ["genus", "g__UBA4421"]], 3]]], "TARA_ASW_MAG_00014_000000000074": [5044, 4, []], "TARA_ASW_MAG_00014_000000000075": [6603, 10, [[[["superkingdom", "d__Bacteria"], ["phylum", "p__Proteobacteria"], ["class", "c__Gammaproteobacteria"], ["order", "o__Pseudomonadales"], ["family", "f__HTCC2089"], ["genus", "g__UBA4421"]], 2]]], "TARA_ASW_MAG_00014_000000000076": [3107, 1, []], "TARA_ASW_MAG_00014_000000000077": [2898, 1, []], "TARA_ASW_MAG_00014_000000000078": [14393, 8, [[[["superkingdom", "d__Bacteria"], ["phylum", "p__Proteobacteria"], ["class", "c__Gammaproteobacteria"], ["order", "o__Pseudomonadales"], ["family", "f__HTCC2089"], ["genus", "g__UBA4421"]], 2]]], "TARA_ASW_MAG_00014_000000000079": [7790, 4, [[[["superkingdom", "d__Bacteria"], ["phylum", "p__Proteobacteria"], ["class", "c__Gammaproteobacteria"], ["order", "o__Pseudomonadales"], ["family", "f__HTCC2089"], ["genus", "g__UBA4421"]], 1]]], "TARA_ASW_MAG_00014_000000000080": [4376, 4, []], "TARA_ASW_MAG_00014_000000000081": [2518, 5, [[[["superkingdom", "d__Bacteria"], ["phylum", "p__Proteobacteria"], ["class", "c__Gammaproteobacteria"], ["order", "o__Pseudomonadales"], ["family", "f__HTCC2089"], ["genus", "g__UBA4421"]], 4]]], "TARA_ASW_MAG_00014_000000000082": [2753, 0, []], "TARA_ASW_MAG_00014_000000000083": [3946, 5, []], "TARA_ASW_MAG_00014_000000000084": [4420, 9, [[[["superkingdom", "d__Bacteria"], ["phylum", "p__Proteobacteria"], ["class", "c__Gammaproteobacteria"], ["order", "o__Pseudomonadales"], ["family", "f__HTCC2089"], ["genus", "g__UBA4421"]], 2]]], "TARA_ASW_MAG_00014_000000000085": [3290, 4, [[[["superkingdom", "d__Bacteria"], ["phylum", "p__Proteobacteria"], ["class", "c__Gammaproteobacteria"], ["order", "o__Pseudomonadales"], ["family", "f__HTCC2089"], ["genus", "g__UBA4421"]], 1]]], "TARA_ASW_MAG_00014_000000000086": [3667, 3, []], "TARA_ASW_MAG_00014_000000000087": [3253, 3, []], "TARA_ASW_MAG_00014_000000000088": [5163, 2, [[[["superkingdom", "d__Bacteria"], ["phylum", "p__Proteobacteria"], ["class", "c__Gammaproteobacteria"], ["order", "o__Pseudomonadales"], ["family", "f__HTCC2089"], ["genus", "g__UBA4421"]], 1]]], "TARA_ASW_MAG_00014_000000000089": [2663, 4, []], "TARA_ASW_MAG_00014_000000000090": [6151, 5, []], "TARA_ASW_MAG_00014_000000000091": [2876, 1, []], "TARA_ASW_MAG_00014_000000000092": [3816, 5, [[[["superkingdom", "d__Bacteria"], ["phylum", "p__Proteobacteria"], ["class", "c__Gammaproteobacteria"], ["order", "o__Pseudomonadales"], ["family", "f__HTCC2089"], ["genus", "g__UBA4421"]], 3]]], "TARA_ASW_MAG_00014_000000000093": [9428, 6, [[[["superkingdom", "d__Bacteria"], ["phylum", "p__Proteobacteria"], ["class", "c__Gammaproteobacteria"], ["order", "o__Pseudomonadales"], ["family", "f__HTCC2089"], ["genus", "g__UBA4421"]], 2]]], "TARA_ASW_MAG_00014_000000000094": [2661, 1, []], "TARA_ASW_MAG_00014_000000000095": [11189, 9, [[[["superkingdom", "d__Bacteria"], ["phylum", "p__Proteobacteria"], ["class", "c__Gammaproteobacteria"], ["order", "o__Pseudomonadales"], ["family", "f__HTCC2089"], ["genus", "g__UBA4421"]], 2]]], "TARA_ASW_MAG_00014_000000000096": [2975, 2, []], "TARA_ASW_MAG_00014_000000000097": [2920, 6, [[[["superkingdom", "d__Bacteria"], ["phylum", "p__Proteobacteria"], ["class", "c__Gammaproteobacteria"], ["order", "o__Pseudomonadales"], ["family", "f__HTCC2089"], ["genus", "g__UBA4421"]], 3]]], "TARA_ASW_MAG_00014_000000000098": [4123, 9, []], "TARA_ASW_MAG_00014_000000000099": [3552, 4, [[[["superkingdom", "d__Bacteria"], ["phylum", "p__Proteobacteria"], ["class", "c__Gammaproteobacteria"], ["order", "o__Pseudomonadales"], ["family", "f__HTCC2089"], ["genus", "g__UBA4421"]], 1]]], "TARA_ASW_MAG_00014_000000000100": [9633, 15, [[[["superkingdom", "d__Bacteria"], ["phylum", "p__Proteobacteria"], ["class", "c__Gammaproteobacteria"], ["order", "o__Pseudomonadales"], ["family", "f__HTCC2089"], ["genus", "g__UBA4421"]], 2]]], "TARA_ASW_MAG_00014_000000000101": [8148, 9, [[[["superkingdom", "d__Bacteria"], ["phylum", "p__Proteobacteria"], ["class", "c__Gammaproteobacteria"], ["order", "o__Pseudomonadales"], ["family", "f__HTCC2089"], ["genus", "g__UBA4421"]], 1]]], "TARA_ASW_MAG_00014_000000000102": [2667, 3, []], "TARA_ASW_MAG_00014_000000000103": [4263, 4, []], "TARA_ASW_MAG_00014_000000000104": [2885, 5, []], "TARA_ASW_MAG_00014_000000000105": [5814, 5, [[[["superkingdom", "d__Bacteria"], ["phylum", "p__Proteobacteria"], ["class", "c__Gammaproteobacteria"], ["order", "o__Pseudomonadales"], ["family", "f__HTCC2089"], ["genus", "g__UBA4421"]], 1]]], "TARA_ASW_MAG_00014_000000000106": [3048, 4, []], "TARA_ASW_MAG_00014_000000000107": [5945, 7, [[[["superkingdom", "d__Bacteria"], ["phylum", "p__Proteobacteria"], ["class", "c__Gammaproteobacteria"], ["order", "o__Pseudomonadales"], ["family", "f__HTCC2089"], ["genus", "g__UBA4421"]], 3]]], "TARA_ASW_MAG_00014_000000000108": [6677, 8, [[[["superkingdom", "d__Bacteria"], ["phylum", "p__Proteobacteria"], ["class", "c__Gammaproteobacteria"], ["order", "o__Pseudomonadales"], ["family", "f__HTCC2089"], ["genus", "g__UBA4421"]], 3]]], "TARA_ASW_MAG_00014_000000000109": [4002, 2, [[[["superkingdom", "d__Bacteria"], ["phylum", "p__Proteobacteria"], ["class", "c__Gammaproteobacteria"], ["order", "o__Pseudomonadales"], ["family", "f__HTCC2089"], ["genus", "g__UBA4421"]], 2]]], "TARA_ASW_MAG_00014_000000000110": [5049, 9, []], "TARA_ASW_MAG_00014_000000000111": [4620, 5, []], "TARA_ASW_MAG_00014_000000000112": [6242, 8, [[[["superkingdom", "d__Bacteria"], ["phylum", "p__Proteobacteria"], ["class", "c__Gammaproteobacteria"], ["order", "o__Pseudomonadales"], ["family", "f__HTCC2089"], ["genus", "g__UBA4421"]], 2]]], "TARA_ASW_MAG_00014_000000000113": [3069, 3, []], "TARA_ASW_MAG_00014_000000000114": [5503, 4, [[[["superkingdom", "d__Bacteria"], ["phylum", "p__Proteobacteria"], ["class", "c__Gammaproteobacteria"], ["order", "o__Pseudomonadales"], ["family", "f__HTCC2089"], ["genus", "g__UBA4421"]], 1]]], "TARA_ASW_MAG_00014_000000000115": [4273, 7, [[[["superkingdom", "d__Bacteria"], ["phylum", "p__Proteobacteria"], ["class", "c__Gammaproteobacteria"], ["order", "o__Pseudomonadales"], ["family", "f__HTCC2089"], ["genus", "g__UBA4421"]], 2]]], "TARA_ASW_MAG_00014_000000000116": [5517, 6, []], "TARA_ASW_MAG_00014_000000000117": [2834, 3, [[[["superkingdom", "d__Bacteria"], ["phylum", "p__Proteobacteria"], ["class", "c__Gammaproteobacteria"], ["order", "o__Pseudomonadales"], ["family", "f__HTCC2089"], ["genus", "g__UBA4421"]], 1]]], "TARA_ASW_MAG_00014_000000000118": [4543, 2, []], "TARA_ASW_MAG_00014_000000000119": [3605, 4, []], "TARA_ASW_MAG_00014_000000000120": [7152, 8, [[[["superkingdom", "d__Bacteria"], ["phylum", "p__Proteobacteria"], ["class", "c__Gammaproteobacteria"], ["order", "o__Pseudomonadales"], ["family", "f__HTCC2089"], ["genus", "g__UBA4421"]], 4]]], "TARA_ASW_MAG_00014_000000000121": [2830, 0, []], "TARA_ASW_MAG_00014_000000000122": [3165, 7, [[[["superkingdom", "d__Bacteria"], ["phylum", "p__Proteobacteria"], ["class", "c__Gammaproteobacteria"], ["order", "o__Pseudomonadales"], ["family", "f__HTCC2089"], ["genus", "g__UBA4421"]], 1]]], "TARA_ASW_MAG_00014_000000000123": [4456, 4, [[[["superkingdom", "d__Bacteria"], ["phylum", "p__Proteobacteria"], ["class", "c__Gammaproteobacteria"], ["order", "o__Pseudomonadales"], ["family", "f__HTCC2089"], ["genus", "g__UBA4421"]], 1]]], "TARA_ASW_MAG_00014_000000000124": [3903, 5, [[[["superkingdom", "d__Bacteria"], ["phylum", "p__Proteobacteria"], ["class", "c__Gammaproteobacteria"], ["order", "o__Pseudomonadales"], ["family", "f__HTCC2089"], ["genus", "g__UBA4421"]], 1]]], "TARA_ASW_MAG_00014_000000000125": [2936, 4, [[[["superkingdom", "d__Bacteria"], ["phylum", "p__Proteobacteria"], ["class", "c__Gammaproteobacteria"], ["order", "o__Pseudomonadales"], ["family", "f__HTCC2089"], ["genus", "g__UBA4421"]], 1]]], "TARA_ASW_MAG_00014_000000000126": [5647, 2, []], "TARA_ASW_MAG_00014_000000000127": [2861, 0, []], "TARA_ASW_MAG_00014_000000000128": [3113, 3, []], "TARA_ASW_MAG_00014_000000000129": [3141, 1, []], "TARA_ASW_MAG_00014_000000000130": [4167, 5, []], "TARA_ASW_MAG_00014_000000000131": [13251, 12, [[[["superkingdom", "d__Bacteria"], ["phylum", "p__Proteobacteria"], ["class", "c__Gammaproteobacteria"], ["order", "o__Pseudomonadales"], ["family", "f__HTCC2089"], ["genus", "g__UBA4421"]], 4]]], "TARA_ASW_MAG_00014_000000000132": [3374, 3, [[[["superkingdom", "d__Bacteria"], ["phylum", "p__Proteobacteria"], ["class", "c__Gammaproteobacteria"], ["order", "o__Pseudomonadales"], ["family", "f__HTCC2089"], ["genus", "g__UBA4421"]], 1]]], "TARA_ASW_MAG_00014_000000000133": [6551, 4, [[[["superkingdom", "d__Bacteria"], ["phylum", "p__Proteobacteria"], ["class", "c__Gammaproteobacteria"], ["order", "o__Pseudomonadales"], ["family", "f__HTCC2089"], ["genus", "g__UBA4421"]], 1]]], "TARA_ASW_MAG_00014_000000000134": [3018, 4, [[[["superkingdom", "d__Bacteria"], ["phylum", "p__Proteobacteria"], ["class", "c__Gammaproteobacteria"], ["order", "o__Pseudomonadales"], ["family", "f__HTCC2089"], ["genus", "g__UBA4421"]], 2]]], "TARA_ASW_MAG_00014_000000000135": [4076, 3, [[[["superkingdom", "d__Bacteria"], ["phylum", "p__Proteobacteria"], ["class", "c__Gammaproteobacteria"], ["order", "o__Pseudomonadales"], ["family", "f__HTCC2089"], ["genus", "g__UBA4421"]], 1]]], "TARA_ASW_MAG_00014_000000000136": [3601, 11, []], "TARA_ASW_MAG_00014_000000000137": [3183, 5, [[[["superkingdom", "d__Bacteria"], ["phylum", "p__Proteobacteria"], ["class", "c__Gammaproteobacteria"], ["order", "o__Pseudomonadales"], ["family", "f__HTCC2089"], ["genus", "g__UBA4421"]], 4]]], "TARA_ASW_MAG_00014_000000000138": [4512, 7, []], "TARA_ASW_MAG_00014_000000000139": [3103, 6, []], "TARA_ASW_MAG_00014_000000000140": [6313, 8, [[[["superkingdom", "d__Bacteria"], ["phylum", "p__Proteobacteria"], ["class", "c__Gammaproteobacteria"], ["order", "o__Pseudomonadales"], ["family", "f__HTCC2089"], ["genus", "g__UBA4421"]], 1]]], "TARA_ASW_MAG_00014_000000000141": [5587, 4, [[[["superkingdom", "d__Bacteria"], ["phylum", "p__Proteobacteria"], ["class", "c__Gammaproteobacteria"], ["order", "o__Pseudomonadales"], ["family", "f__HTCC2089"], ["genus", "g__UBA4421"]], 1]]], "TARA_ASW_MAG_00014_000000000142": [2634, 3, []], "TARA_ASW_MAG_00014_000000000143": [2667, 3, []], "TARA_ASW_MAG_00014_000000000144": [3302, 3, [[[["superkingdom", "d__Bacteria"], ["phylum", "p__Proteobacteria"], ["class", "c__Gammaproteobacteria"], ["order", "o__Pseudomonadales"], ["family", "f__HTCC2089"], ["genus", "g__UBA4421"]], 1]]], "TARA_ASW_MAG_00014_000000000145": [5098, 3, []], "TARA_ASW_MAG_00014_000000000146": [3611, 5, []], "TARA_ASW_MAG_00014_000000000147": [5481, 4, []], "TARA_ASW_MAG_00014_000000000148": [4595, 3, [[[["superkingdom", "d__Bacteria"], ["phylum", "p__Proteobacteria"], ["class", "c__Gammaproteobacteria"], ["order", "o__Pseudomonadales"], ["family", "f__HTCC2089"], ["genus", "g__UBA4421"]], 1]]], "TARA_ASW_MAG_00014_000000000149": [21107, 23, [[[["superkingdom", "d__Bacteria"], ["phylum", "p__Proteobacteria"], ["class", "c__Gammaproteobacteria"], ["order", "o__Pseudomonadales"], ["family", "f__HTCC2089"], ["genus", "g__UBA4421"]], 6]]], "TARA_ASW_MAG_00014_000000000150": [3058, 4, []], "TARA_ASW_MAG_00014_000000000151": [10076, 16, [[[["superkingdom", "d__Bacteria"], ["phylum", "p__Proteobacteria"], ["class", "c__Gammaproteobacteria"], ["order", "o__Pseudomonadales"], ["family", "f__HTCC2089"], ["genus", "g__UBA4421"]], 1]]], "TARA_ASW_MAG_00014_000000000152": [2705, 0, []], "TARA_ASW_MAG_00014_000000000153": [3551, 3, [[[["superkingdom", "d__Bacteria"], ["phylum", "p__Proteobacteria"], ["class", "c__Gammaproteobacteria"], ["order", "o__Pseudomonadales"], ["family", "f__HTCC2089"], ["genus", "g__UBA4421"]], 1]]], "TARA_ASW_MAG_00014_000000000154": [4472, 2, [[[["superkingdom", "d__Bacteria"], ["phylum", "p__Proteobacteria"], ["class", "c__Gammaproteobacteria"], ["order", "o__Pseudomonadales"], ["family", "f__HTCC2089"], ["genus", "g__UBA4421"]], 1]]], "TARA_ASW_MAG_00014_000000000155": [4265, 3, []], "TARA_ASW_MAG_00014_000000000156": [8817, 6, []], "TARA_ASW_MAG_00014_000000000157": [3044, 9, []], "TARA_ASW_MAG_00014_000000000158": [2708, 2, []], "TARA_ASW_MAG_00014_000000000159": [8178, 5, []], "TARA_ASW_MAG_00014_000000000160": [4187, 4, [[[["superkingdom", "d__Bacteria"], ["phylum", "p__Proteobacteria"], ["class", "c__Gammaproteobacteria"], ["order", "o__Pseudomonadales"], ["family", "f__HTCC2089"], ["genus", "g__UBA4421"]], 2]]], "TARA_ASW_MAG_00014_000000000161": [9052, 13, [[[["superkingdom", "d__Bacteria"], ["phylum", "p__Proteobacteria"], ["class", "c__Gammaproteobacteria"], ["order", "o__Pseudomonadales"], ["family", "f__HTCC2089"], ["genus", "g__UBA4421"]], 3]]], "TARA_ASW_MAG_00014_000000000162": [3836, 4, [[[["superkingdom", "d__Bacteria"], ["phylum", "p__Proteobacteria"], ["class", "c__Gammaproteobacteria"], ["order", "o__Pseudomonadales"], ["family", "f__HTCC2089"], ["genus", "g__UBA4421"]], 1]]], "TARA_ASW_MAG_00014_000000000163": [3016, 4, []], "TARA_ASW_MAG_00014_000000000164": [2663, 2, []], "TARA_ASW_MAG_00014_000000000165": [2513, 3, []], "TARA_ASW_MAG_00014_000000000166": [4297, 4, [[[["superkingdom", "d__Bacteria"], ["phylum", "p__Proteobacteria"], ["class", "c__Gammaproteobacteria"], ["order", "o__Pseudomonadales"], ["family", "f__HTCC2089"], ["genus", "g__UBA4421"]], 2]]], "TARA_ASW_MAG_00014_000000000167": [4722, 7, []], "TARA_ASW_MAG_00014_000000000168": [3768, 4, []], "TARA_ASW_MAG_00014_000000000169": [4079, 6, [[[["superkingdom", "d__Bacteria"], ["phylum", "p__Proteobacteria"], ["class", "c__Gammaproteobacteria"], ["order", "o__Pseudomonadales"], ["family", "f__HTCC2089"], ["genus", "g__UBA4421"]], 4]]], "TARA_ASW_MAG_00014_000000000170": [4439, 11, [[[["superkingdom", "d__Bacteria"], ["phylum", "p__Proteobacteria"], ["class", "c__Gammaproteobacteria"], ["order", "o__Pseudomonadales"], ["family", "f__HTCC2089"], ["genus", "g__UBA4421"]], 5]]], "TARA_ASW_MAG_00014_000000000171": [2669, 3, [[[["superkingdom", "d__Bacteria"], ["phylum", "p__Proteobacteria"], ["class", "c__Gammaproteobacteria"], ["order", "o__Pseudomonadales"], ["family", "f__HTCC2089"], ["genus", "g__UBA4421"]], 1]]], "TARA_ASW_MAG_00014_000000000172": [2605, 4, []], "TARA_ASW_MAG_00014_000000000173": [5115, 8, [[[["superkingdom", "d__Bacteria"], ["phylum", "p__Proteobacteria"], ["class", "c__Gammaproteobacteria"], ["order", "o__Pseudomonadales"], ["family", "f__HTCC2089"], ["genus", "g__UBA4421"]], 1]]], "TARA_ASW_MAG_00014_000000000174": [2836, 2, []], "TARA_ASW_MAG_00014_000000000175": [4974, 2, []], "TARA_ASW_MAG_00014_000000000176": [2645, 4, []], "TARA_ASW_MAG_00014_000000000177": [2906, 2, []], "TARA_ASW_MAG_00014_000000000178": [5289, 2, []], "TARA_ASW_MAG_00014_000000000179": [6081, 10, []], "TARA_ASW_MAG_00014_000000000180": [5012, 8, [[[["superkingdom", "d__Bacteria"], ["phylum", "p__Proteobacteria"], ["class", "c__Gammaproteobacteria"], ["order", "o__Pseudomonadales"], ["family", "f__HTCC2089"], ["genus", "g__UBA4421"]], 2]]], "TARA_ASW_MAG_00014_000000000181": [4204, 3, []], "TARA_ASW_MAG_00014_000000000182": [3567, 2, []], "TARA_ASW_MAG_00014_000000000183": [3535, 3, []], "TARA_ASW_MAG_00014_000000000184": [2622, 3, []], "TARA_ASW_MAG_00014_000000000185": [2997, 1, []], "TARA_ASW_MAG_00014_000000000186": [2571, 3, []], "TARA_ASW_MAG_00014_000000000187": [3145, 0, []], "TARA_ASW_MAG_00014_000000000188": [5537, 5, [[[["superkingdom", "d__Bacteria"], ["phylum", "p__Proteobacteria"], ["class", "c__Gammaproteobacteria"], ["order", "o__Pseudomonadales"], ["family", "f__HTCC2089"], ["genus", "g__UBA4421"]], 2]]], "TARA_ASW_MAG_00014_000000000189": [5455, 6, [[[["superkingdom", "d__Bacteria"], ["phylum", "p__Proteobacteria"], ["class", "c__Gammaproteobacteria"], ["order", "o__Pseudomonadales"], ["family", "f__HTCC2089"], ["genus", "g__UBA4421"]], 2]]], "TARA_ASW_MAG_00014_000000000190": [3840, 6, [[[["superkingdom", "d__Bacteria"], ["phylum", "p__Proteobacteria"], ["class", "c__Gammaproteobacteria"], ["order", "o__Pseudomonadales"], ["family", "f__HTCC2089"], ["genus", "g__UBA4421"]], 4]]], "TARA_ASW_MAG_00014_000000000191": [10026, 15, [[[["superkingdom", "d__Bacteria"], ["phylum", "p__Proteobacteria"], ["class", "c__Gammaproteobacteria"], ["order", "o__Pseudomonadales"], ["family", "f__HTCC2089"], ["genus", "g__UBA4421"]], 2]]], "TARA_ASW_MAG_00014_000000000192": [3396, 3, [[[["superkingdom", "d__Bacteria"], ["phylum", "p__Proteobacteria"], ["class", "c__Gammaproteobacteria"], ["order", "o__Pseudomonadales"], ["family", "f__HTCC2089"], ["genus", "g__UBA4421"]], 2]]], "TARA_ASW_MAG_00014_000000000193": [3478, 2, []], "TARA_ASW_MAG_00014_000000000194": [2617, 0, []], "TARA_ASW_MAG_00014_000000000195": [7132, 8, [[[["superkingdom", "d__Bacteria"], ["phylum", "p__Proteobacteria"], ["class", "c__Gammaproteobacteria"], ["order", "o__Pseudomonadales"], ["family", "f__HTCC2089"], ["genus", "g__UBA4421"]], 1]]], "TARA_ASW_MAG_00014_000000000196": [3560, 3, [[[["superkingdom", "d__Bacteria"], ["phylum", "p__Proteobacteria"], ["class", "c__Gammaproteobacteria"], ["order", "o__Pseudomonadales"], ["family", "f__HTCC2089"], ["genus", "g__UBA4421"]], 1]]], "TARA_ASW_MAG_00014_000000000197": [2699, 0, []], "TARA_ASW_MAG_00014_000000000198": [9252, 13, []], "TARA_ASW_MAG_00014_000000000199": [3984, 5, []], "TARA_ASW_MAG_00014_000000000200": [4159, 8, [[[["superkingdom", "d__Bacteria"], ["phylum", "p__Proteobacteria"], ["class", "c__Gammaproteobacteria"], ["order", "o__Pseudomonadales"], ["family", "f__HTCC2089"], ["genus", "g__UBA4421"]], 1]]], "TARA_ASW_MAG_00014_000000000201": [3639, 3, [[[["superkingdom", "d__Bacteria"], ["phylum", "p__Proteobacteria"], ["class", "c__Gammaproteobacteria"], ["order", "o__Pseudomonadales"], ["family", "f__HTCC2089"], ["genus", "g__UBA4421"]], 2]]], "TARA_ASW_MAG_00014_000000000202": [3098, 1, []], "TARA_ASW_MAG_00014_000000000203": [2869, 3, []], "TARA_ASW_MAG_00014_000000000204": [5091, 4, []], "TARA_ASW_MAG_00014_000000000205": [2777, 1, []], "TARA_ASW_MAG_00014_000000000206": [2645, 6, [[[["superkingdom", "d__Bacteria"], ["phylum", "p__Proteobacteria"], ["class", "c__Gammaproteobacteria"], ["order", "o__Pseudomonadales"], ["family", "f__HTCC2089"], ["genus", "g__UBA4421"]], 3]]], "TARA_ASW_MAG_00014_000000000207": [4421, 8, []], "TARA_ASW_MAG_00014_000000000208": [8427, 10, [[[["superkingdom", "d__Bacteria"], ["phylum", "p__Proteobacteria"], ["class", "c__Gammaproteobacteria"], ["order", "o__Pseudomonadales"], ["family", "f__HTCC2089"], ["genus", "g__UBA4421"]], 4]]], "TARA_ASW_MAG_00014_000000000209": [5841, 6, []], "TARA_ASW_MAG_00014_000000000210": [2759, 2, [[[["superkingdom", "d__Bacteria"], ["phylum", "p__Proteobacteria"], ["class", "c__Gammaproteobacteria"], ["order", "o__Pseudomonadales"], ["family", "f__HTCC2089"], ["genus", "g__UBA4421"]], 1]]], "TARA_ASW_MAG_00014_000000000211": [5965, 10, [[[["superkingdom", "d__Bacteria"], ["phylum", "p__Proteobacteria"], ["class", "c__Gammaproteobacteria"], ["order", "o__Pseudomonadales"], ["family", "f__HTCC2089"], ["genus", "g__UBA4421"]], 1]]], "TARA_ASW_MAG_00014_000000000212": [2628, 3, [[[["superkingdom", "d__Bacteria"], ["phylum", "p__Proteobacteria"], ["class", "c__Gammaproteobacteria"], ["order", "o__Pseudomonadales"], ["family", "f__HTCC2089"], ["genus", "g__UBA4421"]], 1]]], "TARA_ASW_MAG_00014_000000000213": [4661, 6, [[[["superkingdom", "d__Bacteria"], ["phylum", "p__Proteobacteria"], ["class", "c__Gammaproteobacteria"], ["order", "o__Pseudomonadales"], ["family", "f__HTCC2089"], ["genus", "g__UBA4421"]], 2]]], "TARA_ASW_MAG_00014_000000000214": [3801, 3, [[[["superkingdom", "d__Bacteria"], ["phylum", "p__Proteobacteria"], ["class", "c__Gammaproteobacteria"], ["order", "o__Pseudomonadales"], ["family", "f__HTCC2089"], ["genus", "g__UBA4421"]], 3]]], "TARA_ASW_MAG_00014_000000000215": [5237, 6, [[[["superkingdom", "d__Bacteria"], ["phylum", "p__Proteobacteria"], ["class", "c__Gammaproteobacteria"], ["order", "o__Pseudomonadales"], ["family", "f__HTCC2089"], ["genus", "g__UBA4421"]], 2]]], "TARA_ASW_MAG_00014_000000000216": [3357, 4, [[[["superkingdom", "d__Bacteria"], ["phylum", "p__Proteobacteria"], ["class", "c__Gammaproteobacteria"], ["order", "o__Pseudomonadales"], ["family", "f__HTCC2089"], ["genus", "g__UBA4421"]], 1]]], "TARA_ASW_MAG_00014_000000000217": [2580, 1, []], "TARA_ASW_MAG_00014_000000000218": [2813, 3, [[[["superkingdom", "d__Bacteria"], ["phylum", "p__Proteobacteria"], ["class", "c__Gammaproteobacteria"], ["order", "o__Pseudomonadales"], ["family", "f__HTCC2089"], ["genus", "g__UBA4421"]], 1]]], "TARA_ASW_MAG_00014_000000000219": [2844, 1, [[[["superkingdom", "d__Bacteria"], ["phylum", "p__Proteobacteria"], ["class", "c__Gammaproteobacteria"], ["order", "o__Pseudomonadales"], ["family", "f__HTCC2089"], ["genus", "g__UBA4421"]], 1]]], "TARA_ASW_MAG_00014_000000000220": [3640, 1, []], "TARA_ASW_MAG_00014_000000000221": [11597, 15, []], "TARA_ASW_MAG_00014_000000000222": [4154, 3, []], "TARA_ASW_MAG_00014_000000000223": [2902, 1, [[[["superkingdom", "d__Bacteria"], ["phylum", "p__Proteobacteria"], ["class", "c__Gammaproteobacteria"], ["order", "o__Pseudomonadales"], ["family", "f__HTCC2089"], ["genus", "g__UBA4421"]], 1]]], "TARA_ASW_MAG_00014_000000000224": [3973, 6, [[[["superkingdom", "d__Bacteria"], ["phylum", "p__Proteobacteria"], ["class", "c__Gammaproteobacteria"], ["order", "o__Pseudomonadales"], ["family", "f__HTCC2089"], ["genus", "g__UBA4421"]], 1]]], "TARA_ASW_MAG_00014_000000000225": [4404, 2, []], "TARA_ASW_MAG_00014_000000000226": [3056, 5, [[[["superkingdom", "d__Bacteria"], ["phylum", "p__Proteobacteria"], ["class", "c__Gammaproteobacteria"], ["order", "o__Pseudomonadales"], ["family", "f__HTCC2089"], ["genus", "g__UBA4421"]], 1]]], "TARA_ASW_MAG_00014_000000000227": [4167, 7, [[[["superkingdom", "d__Bacteria"], ["phylum", "p__Proteobacteria"], ["class", "c__Gammaproteobacteria"], ["order", "o__Pseudomonadales"], ["family", "f__HTCC2089"], ["genus", "g__UBA4421"]], 1]]], "TARA_ASW_MAG_00014_000000000228": [15705, 9, [[[["superkingdom", "d__Bacteria"], ["phylum", "p__Proteobacteria"], ["class", "c__Gammaproteobacteria"], ["order", "o__Pseudomonadales"], ["family", "f__HTCC2089"], ["genus", "g__UBA4421"]], 3]]], "TARA_ASW_MAG_00014_000000000229": [6605, 7, [[[["superkingdom", "d__Bacteria"], ["phylum", "p__Proteobacteria"], ["class", "c__Gammaproteobacteria"], ["order", "o__Pseudomonadales"], ["family", "f__HTCC2089"], ["genus", "g__UBA4421"]], 1]]], "TARA_ASW_MAG_00014_000000000230": [2538, 1, []], "TARA_ASW_MAG_00014_000000000231": [2632, 0, []], "TARA_ASW_MAG_00014_000000000232": [6832, 5, [[[["superkingdom", "d__Bacteria"], ["phylum", "p__Proteobacteria"], ["class", "c__Gammaproteobacteria"], ["order", "o__Pseudomonadales"], ["family", "f__HTCC2089"], ["genus", "g__UBA4421"]], 3]]], "TARA_ASW_MAG_00014_000000000233": [2776, 1, []], "TARA_ASW_MAG_00014_000000000234": [9461, 6, [[[["superkingdom", "d__Bacteria"], ["phylum", "p__Proteobacteria"], ["class", "c__Gammaproteobacteria"], ["order", "o__Pseudomonadales"], ["family", "f__HTCC2089"], ["genus", "g__UBA4421"]], 1]]], "TARA_ASW_MAG_00014_000000000235": [5160, 4, [[[["superkingdom", "d__Bacteria"], ["phylum", "p__Proteobacteria"], ["class", "c__Gammaproteobacteria"], ["order", "o__Pseudomonadales"], ["family", "f__HTCC2089"], ["genus", "g__UBA4421"]], 1]]], "TARA_ASW_MAG_00014_000000000236": [4757, 2, []], "TARA_ASW_MAG_00014_000000000237": [5663, 7, [[[["superkingdom", "d__Bacteria"], ["phylum", "p__Proteobacteria"], ["class", "c__Gammaproteobacteria"], ["order", "o__Pseudomonadales"], ["family", "f__HTCC2089"], ["genus", "g__UBA4421"]], 2]]], "TARA_ASW_MAG_00014_000000000238": [5582, 6, []], "TARA_ASW_MAG_00014_000000000239": [3941, 3, []], "TARA_ASW_MAG_00014_000000000240": [2765, 3, []], "TARA_ASW_MAG_00014_000000000241": [5369, 2, []], "TARA_ASW_MAG_00014_000000000242": [2513, 3, []], "TARA_ASW_MAG_00014_000000000243": [3954, 4, [[[["superkingdom", "d__Bacteria"], ["phylum", "p__Proteobacteria"], ["class", "c__Gammaproteobacteria"], ["order", "o__Pseudomonadales"], ["family", "f__HTCC2089"], ["genus", "g__UBA4421"]], 1]]], "TARA_ASW_MAG_00014_000000000244": [7971, 8, [[[["superkingdom", "d__Bacteria"], ["phylum", "p__Proteobacteria"], ["class", "c__Gammaproteobacteria"], ["order", "o__Pseudomonadales"], ["family", "f__HTCC2089"], ["genus", "g__UBA4421"]], 2]]], "TARA_ASW_MAG_00014_000000000245": [2647, 1, []], "TARA_ASW_MAG_00014_000000000246": [3605, 4, []], "TARA_ASW_MAG_00014_000000000247": [2657, 4, [[[["superkingdom", "d__Bacteria"], ["phylum", "p__Proteobacteria"], ["class", "c__Gammaproteobacteria"], ["order", "o__Pseudomonadales"], ["family", "f__HTCC2089"], ["genus", "g__UBA4421"]], 1]]], "TARA_ASW_MAG_00014_000000000248": [6805, 5, []], "TARA_ASW_MAG_00014_000000000249": [4513, 4, []], "TARA_ASW_MAG_00014_000000000250": [3590, 5, [[[["superkingdom", "d__Bacteria"], ["phylum", "p__Proteobacteria"], ["class", "c__Gammaproteobacteria"], ["order", "o__Pseudomonadales"], ["family", "f__HTCC2089"], ["genus", "g__UBA4421"]], 2]]], "TARA_ASW_MAG_00014_000000000251": [6403, 3, [[[["superkingdom", "d__Bacteria"], ["phylum", "p__Proteobacteria"], ["class", "c__Gammaproteobacteria"], ["order", "o__Pseudomonadales"], ["family", "f__HTCC2089"], ["genus", "g__UBA4421"]], 1]]], "TARA_ASW_MAG_00014_000000000252": [2753, 2, []], "TARA_ASW_MAG_00014_000000000253": [4401, 3, []], "TARA_ASW_MAG_00014_000000000254": [2755, 4, [[[["superkingdom", "d__Bacteria"], ["phylum", "p__Proteobacteria"], ["class", "c__Gammaproteobacteria"], ["order", "o__Pseudomonadales"], ["family", "f__HTCC2089"], ["genus", "g__UBA4421"]], 1]]], "TARA_ASW_MAG_00014_000000000255": [4559, 2, []], "TARA_ASW_MAG_00014_000000000256": [3587, 5, [[[["superkingdom", "d__Bacteria"], ["phylum", "p__Proteobacteria"], ["class", "c__Gammaproteobacteria"], ["order", "o__Pseudomonadales"], ["family", "f__HTCC2089"], ["genus", "g__UBA4421"]], 2]]], "TARA_ASW_MAG_00014_000000000257": [4825, 5, [[[["superkingdom", "d__Bacteria"], ["phylum", "p__Proteobacteria"], ["class", "c__Gammaproteobacteria"], ["order", "o__Pseudomonadales"], ["family", "f__HTCC2089"], ["genus", "g__UBA4421"]], 1]]], "TARA_ASW_MAG_00014_000000000258": [3507, 3, []], "TARA_ASW_MAG_00014_000000000259": [3084, 3, []], "TARA_ASW_MAG_00014_000000000260": [2946, 2, []], "TARA_ASW_MAG_00014_000000000261": [4664, 3, [[[["superkingdom", "d__Bacteria"], ["phylum", "p__Proteobacteria"], ["class", "c__Gammaproteobacteria"], ["order", "o__Pseudomonadales"], ["family", "f__HTCC2089"], ["genus", "g__UBA4421"]], 1]]], "TARA_ASW_MAG_00014_000000000262": [7630, 5, []], "TARA_ASW_MAG_00014_000000000263": [2766, 1, []], "TARA_ASW_MAG_00014_000000000264": [2848, 2, []], "TARA_ASW_MAG_00014_000000000265": [2898, 6, [[[["superkingdom", "d__Bacteria"], ["phylum", "p__Proteobacteria"], ["class", "c__Gammaproteobacteria"], ["order", "o__Pseudomonadales"], ["family", "f__HTCC2089"], ["genus", "g__UBA4421"]], 1]]], "TARA_ASW_MAG_00014_000000000266": [2601, 4, []], "TARA_ASW_MAG_00014_000000000267": [9334, 10, [[[["superkingdom", "d__Bacteria"], ["phylum", "p__Proteobacteria"], ["class", "c__Gammaproteobacteria"], ["order", "o__Pseudomonadales"], ["family", "f__HTCC2089"], ["genus", "g__UBA4421"]], 1]]], "TARA_ASW_MAG_00014_000000000268": [4239, 4, [[[["superkingdom", "d__Bacteria"], ["phylum", "p__Proteobacteria"], ["class", "c__Gammaproteobacteria"], ["order", "o__Pseudomonadales"], ["family", "f__HTCC2089"], ["genus", "g__UBA4421"]], 2]]], "TARA_ASW_MAG_00014_000000000269": [2684, 3, []], "TARA_ASW_MAG_00014_000000000270": [4534, 5, [[[["superkingdom", "d__Bacteria"], ["phylum", "p__Proteobacteria"], ["class", "c__Gammaproteobacteria"], ["order", "o__Pseudomonadales"], ["family", "f__HTCC2089"], ["genus", "g__UBA4421"]], 2]]], "TARA_ASW_MAG_00014_000000000271": [3959, 3, [[[["superkingdom", "d__Bacteria"], ["phylum", "p__Proteobacteria"], ["class", "c__Gammaproteobacteria"], ["order", "o__Pseudomonadales"], ["family", "f__HTCC2089"], ["genus", "g__UBA4421"]], 3]]], "TARA_ASW_MAG_00014_000000000272": [2595, 2, []], "TARA_ASW_MAG_00014_000000000273": [9171, 10, [[[["superkingdom", "d__Bacteria"], ["phylum", "p__Proteobacteria"], ["class", "c__Gammaproteobacteria"], ["order", "o__Pseudomonadales"], ["family", "f__HTCC2089"], ["genus", "g__UBA4421"]], 1]]], "TARA_ASW_MAG_00014_000000000274": [3624, 5, [[[["superkingdom", "d__Bacteria"], ["phylum", "p__Proteobacteria"], ["class", "c__Gammaproteobacteria"], ["order", "o__Pseudomonadales"], ["family", "f__HTCC2089"], ["genus", "g__UBA4421"]], 1]]], "TARA_ASW_MAG_00014_000000000275": [3809, 2, [[[["superkingdom", "d__Bacteria"], ["phylum", "p__Proteobacteria"], ["class", "c__Gammaproteobacteria"], ["order", "o__Pseudomonadales"], ["family", "f__HTCC2089"], ["genus", "g__UBA4421"]], 1]]], "TARA_ASW_MAG_00014_000000000276": [3331, 6, [[[["superkingdom", "d__Bacteria"], ["phylum", "p__Proteobacteria"], ["class", "c__Gammaproteobacteria"], ["order", "o__Pseudomonadales"], ["family", "f__HTCC2089"], ["genus", "g__UBA4421"]], 3]]], "TARA_ASW_MAG_00014_000000000277": [3069, 4, []], "TARA_ASW_MAG_00014_000000000278": [2614, 2, [[[["superkingdom", "d__Bacteria"], ["phylum", "p__Proteobacteria"], ["class", "c__Gammaproteobacteria"], ["order", "o__Pseudomonadales"], ["family", "f__HTCC2089"], ["genus", "g__UBA4421"]], 2]]], "TARA_ASW_MAG_00014_000000000279": [3437, 2, []], "TARA_ASW_MAG_00014_000000000280": [2821, 4, []], "TARA_ASW_MAG_00014_000000000281": [9558, 11, [[[["superkingdom", "d__Bacteria"], ["phylum", "p__Proteobacteria"], ["class", "c__Gammaproteobacteria"], ["order", "o__Pseudomonadales"], ["family", "f__HTCC2089"], ["genus", "g__UBA4421"]], 5]]], "TARA_ASW_MAG_00014_000000000282": [2563, 2, []], "TARA_ASW_MAG_00014_000000000283": [3234, 3, []], "TARA_ASW_MAG_00014_000000000284": [2568, 2, [[[["superkingdom", "d__Bacteria"], ["phylum", "p__Proteobacteria"], ["class", "c__Gammaproteobacteria"], ["order", "o__Pseudomonadales"], ["family", "f__HTCC2089"], ["genus", "g__UBA4421"]], 1]]], "TARA_ASW_MAG_00014_000000000285": [4211, 2, []], "TARA_ASW_MAG_00014_000000000286": [3012, 0, []], "TARA_ASW_MAG_00014_000000000287": [2800, 1, [[[["superkingdom", "d__Bacteria"], ["phylum", "p__Proteobacteria"], ["class", "c__Gammaproteobacteria"], ["order", "o__Pseudomonadales"], ["family", "f__HTCC2089"], ["genus", "g__UBA4421"]], 1]]], "TARA_ASW_MAG_00014_000000000288": [3059, 7, [[[["superkingdom", "d__Bacteria"], ["phylum", "p__Proteobacteria"], ["class", "c__Gammaproteobacteria"], ["order", "o__Pseudomonadales"], ["family", "f__HTCC2089"], ["genus", "g__UBA4421"]], 6]]], "TARA_ASW_MAG_00014_000000000289": [5219, 3, [[[["superkingdom", "d__Bacteria"], ["phylum", "p__Proteobacteria"], ["class", "c__Gammaproteobacteria"], ["order", "o__Pseudomonadales"], ["family", "f__HTCC2089"], ["genus", "g__UBA4421"]], 1]]], "TARA_ASW_MAG_00014_000000000290": [3569, 6, []], "TARA_ASW_MAG_00014_000000000291": [5674, 7, [[[["superkingdom", "d__Bacteria"], ["phylum", "p__Proteobacteria"], ["class", "c__Gammaproteobacteria"], ["order", "o__Pseudomonadales"], ["family", "f__HTCC2089"], ["genus", "g__UBA4421"]], 1]]], "TARA_ASW_MAG_00014_000000000292": [2683, 4, []], "TARA_ASW_MAG_00014_000000000293": [3867, 4, []], "TARA_ASW_MAG_00014_000000000294": [4961, 7, [[[["superkingdom", "d__Bacteria"], ["phylum", "p__Proteobacteria"], ["class", "c__Gammaproteobacteria"], ["order", "o__Pseudomonadales"], ["family", "f__HTCC2089"], ["genus", "g__UBA4421"]], 1]]], "TARA_ASW_MAG_00014_000000000295": [4748, 2, []], "TARA_ASW_MAG_00014_000000000296": [3175, 3, []], "TARA_ASW_MAG_00014_000000000297": [2953, 1, []], "TARA_ASW_MAG_00014_000000000298": [2532, 4, []], "TARA_ASW_MAG_00014_000000000299": [2947, 3, []], "TARA_ASW_MAG_00014_000000000300": [3004, 4, [[[["superkingdom", "d__Bacteria"], ["phylum", "p__Proteobacteria"], ["class", "c__Gammaproteobacteria"], ["order", "o__Pseudomonadales"], ["family", "f__HTCC2089"], ["genus", "g__UBA4421"]], 1]]], "TARA_ASW_MAG_00014_000000000301": [4393, 2, []], "TARA_ASW_MAG_00014_000000000302": [2689, 3, []], "TARA_ASW_MAG_00014_000000000303": [3229, 2, []], "TARA_ASW_MAG_00014_000000000304": [2672, 4, [[[["superkingdom", "d__Bacteria"], ["phylum", "p__Proteobacteria"], ["class", "c__Gammaproteobacteria"], ["order", "o__Pseudomonadales"], ["family", "f__HTCC2089"], ["genus", "g__UBA4421"]], 1]]], "TARA_ASW_MAG_00014_000000000305": [3922, 1, []], "TARA_ASW_MAG_00014_000000000306": [3444, 3, []], "TARA_ASW_MAG_00014_000000000307": [2635, 4, [[[["superkingdom", "d__Bacteria"], ["phylum", "p__Proteobacteria"], ["class", "c__Gammaproteobacteria"], ["order", "o__Pseudomonadales"], ["family", "f__HTCC2089"], ["genus", "g__UBA4421"]], 2]]], "TARA_ASW_MAG_00014_000000000308": [3335, 4, [[[["superkingdom", "d__Bacteria"], ["phylum", "p__Proteobacteria"], ["class", "c__Gammaproteobacteria"], ["order", "o__Pseudomonadales"], ["family", "f__HTCC2089"], ["genus", "g__UBA4421"]], 2]]], "TARA_ASW_MAG_00014_000000000309": [4143, 5, []], "TARA_ASW_MAG_00014_000000000310": [2937, 7, []], "TARA_ASW_MAG_00014_000000000311": [5431, 8, [[[["superkingdom", "d__Bacteria"], ["phylum", "p__Proteobacteria"], ["class", "c__Gammaproteobacteria"], ["order", "o__Pseudomonadales"], ["family", "f__HTCC2089"], ["genus", "g__UBA4421"]], 1]]], "TARA_ASW_MAG_00014_000000000312": [5942, 5, []], "TARA_ASW_MAG_00014_000000000313": [14568, 15, [[[["superkingdom", "d__Bacteria"], ["phylum", "p__Proteobacteria"], ["class", "c__Gammaproteobacteria"], ["order", "o__Pseudomonadales"], ["family", "f__HTCC2089"], ["genus", "g__UBA4421"]], 1]]], "TARA_ASW_MAG_00014_000000000314": [2565, 2, []], "TARA_ASW_MAG_00014_000000000315": [13065, 17, [[[["superkingdom", "d__Bacteria"], ["phylum", "p__Proteobacteria"], ["class", "c__Gammaproteobacteria"], ["order", "o__Pseudomonadales"], ["family", "f__HTCC2089"], ["genus", "g__UBA4421"]], 1]]], "TARA_ASW_MAG_00014_000000000316": [4717, 5, [[[["superkingdom", "d__Bacteria"], ["phylum", "p__Proteobacteria"], ["class", "c__Gammaproteobacteria"], ["order", "o__Pseudomonadales"], ["family", "f__HTCC2089"], ["genus", "g__UBA4421"]], 1]]], "TARA_ASW_MAG_00014_000000000317": [3996, 6, [[[["superkingdom", "d__Bacteria"], ["phylum", "p__Proteobacteria"], ["class", "c__Gammaproteobacteria"], ["order", "o__Pseudomonadales"], ["family", "f__HTCC2089"], ["genus", "g__UBA4421"]], 4]]], "TARA_ASW_MAG_00014_000000000318": [6789, 5, [[[["superkingdom", "d__Bacteria"], ["phylum", "p__Proteobacteria"], ["class", "c__Gammaproteobacteria"], ["order", "o__Pseudomonadales"], ["family", "f__HTCC2089"], ["genus", "g__UBA4421"]], 4]]], "TARA_ASW_MAG_00014_000000000319": [2997, 2, [[[["superkingdom", "d__Bacteria"], ["phylum", "p__Proteobacteria"], ["class", "c__Gammaproteobacteria"], ["order", "o__Pseudomonadales"], ["family", "f__HTCC2089"], ["genus", "g__UBA4421"]], 1]]], "TARA_ASW_MAG_00014_000000000320": [4558, 2, []], "TARA_ASW_MAG_00014_000000000321": [5022, 5, [[[["superkingdom", "d__Bacteria"], ["phylum", "p__Proteobacteria"], ["class", "c__Gammaproteobacteria"], ["order", "o__Pseudomonadales"], ["family", "f__HTCC2089"], ["genus", "g__UBA4421"]], 1]]], "TARA_ASW_MAG_00014_000000000322": [4286, 5, []], "TARA_ASW_MAG_00014_000000000323": [6323, 5, []], "TARA_ASW_MAG_00014_000000000324": [3182, 6, [[[["superkingdom", "d__Bacteria"], ["phylum", "p__Proteobacteria"], ["class", "c__Gammaproteobacteria"], ["order", "o__Pseudomonadales"], ["family", "f__HTCC2089"], ["genus", "g__UBA4421"]], 1]]], "TARA_ASW_MAG_00014_000000000325": [2856, 4, []], "TARA_ASW_MAG_00014_000000000326": [4171, 2, []], "TARA_ASW_MAG_00014_000000000327": [7616, 13, []], "TARA_ASW_MAG_00014_000000000328": [9725, 8, [[[["superkingdom", "d__Bacteria"], ["phylum", "p__Proteobacteria"], ["class", "c__Gammaproteobacteria"], ["order", "o__Pseudomonadales"], ["family", "f__HTCC2089"], ["genus", "g__UBA4421"]], 2]]]}