{"TARA_PON_MAG_00064_000000000001": [3518, 3, [[[["superkingdom", "d__Bacteria"], ["phylum", "p__Chloroflexota"], ["class", "c__Dehalococcoidia"], ["order", "o__UBA1151"], ["family", "f__Bin127"], ["genus", "g__GCA-002725925"]], 1]]], "TARA_PON_MAG_00064_000000000002": [4590, 2, []], "TARA_PON_MAG_00064_000000000003": [4600, 3, [[[["superkingdom", "d__Bacteria"], ["phylum", "p__Nitrospinota"], ["class", "c__Nitrospinia"], ["order", "o__Nitrospinales"], ["family", "f__Nitrospinaceae"], ["genus", "g__SCGCAAA288-L16"]], 2]]], "TARA_PON_MAG_00064_000000000004": [3587, 4, [[[["superkingdom", "d__Bacteria"], ["phylum", "p__Nitrospinota"], ["class", "c__Nitrospinia"], ["order", "o__Nitrospinales"], ["family", "f__Nitrospinaceae"], ["genus", "g__SCGCAAA288-L16"]], 3]]], "TARA_PON_MAG_00064_000000000005": [3925, 3, [[[["superkingdom", "d__Bacteria"], ["phylum", "p__Proteobacteria"], ["class", "c__Gammaproteobacteria"], ["order", "o__Pseudomonadales"], ["family", "f__Pseudohongiellaceae"], ["genus", "g__UBA9145"]], 3]]], "TARA_PON_MAG_00064_000000000006": [3437, 2, [[[["superkingdom", "d__Bacteria"], ["phylum", "p__Nitrospinota"], ["class", "c__Nitrospinia"], ["order", "o__Nitrospinales"], ["family", "f__Nitrospinaceae"], ["genus", "g__SCGCAAA288-L16"]], 2]]], "TARA_PON_MAG_00064_000000000007": [4349, 9, []], "TARA_PON_MAG_00064_000000000008": [3110, 3, [[[["superkingdom", "d__Bacteria"], ["phylum", "p__Nitrospinota"], ["class", "c__Nitrospinia"], ["order", "o__Nitrospinales"], ["family", "f__Nitrospinaceae"], ["genus", "g__SCGCAAA288-L16"]], 1]]], "TARA_PON_MAG_00064_000000000009": [3041, 0, []], "TARA_PON_MAG_00064_000000000010": [3662, 4, []], "TARA_PON_MAG_00064_000000000011": [4904, 4, [[[["superkingdom", "d__Bacteria"], ["phylum", "p__Nitrospinota"], ["class", "c__Nitrospinia"], ["order", "o__Nitrospinales"], ["family", "f__Nitrospinaceae"], ["genus", "g__SCGCAAA288-L16"]], 4]]], "TARA_PON_MAG_00064_000000000012": [3838, 2, [[[["superkingdom", "d__Bacteria"], ["phylum", "p__Chloroflexota"], ["class", "c__Dehalococcoidia"], ["order", "o__UBA1151"], ["family", "f__Bin127"], ["genus", "g__GCA-002725925"]], 2]]], "TARA_PON_MAG_00064_000000000013": [3046, 4, []], "TARA_PON_MAG_00064_000000000014": [5767, 5, []], "TARA_PON_MAG_00064_000000000015": [5301, 5, []], "TARA_PON_MAG_00064_000000000016": [3031, 1, [[[["superkingdom", "d__Bacteria"], ["phylum", "p__Marinisomatota"], ["class", "c__Marinisomatia"], ["order", "o__Marinisomatales"], ["family", "f__UBA1611"], ["genus", "g__UBA2134"]], 1]]], "TARA_PON_MAG_00064_000000000017": [2651, 5, [[[["superkingdom", "d__Bacteria"], ["phylum", "p__Chloroflexota"], ["class", "c__Dehalococcoidia"], ["order", "o__UBA1151"], ["family", "f__Bin127"], ["genus", "g__GCA-002725925"]], 3]]], "TARA_PON_MAG_00064_000000000018": [5954, 6, [[[["superkingdom", "d__Bacteria"], ["phylum", "p__Nitrospinota"], ["class", "c__Nitrospinia"], ["order", "o__Nitrospinales"], ["family", "f__Nitrospinaceae"], ["genus", "g__SCGCAAA288-L16"]], 3]]], "TARA_PON_MAG_00064_000000000019": [4055, 5, [[[["superkingdom", "d__Bacteria"], ["phylum", "p__Nitrospinota"], ["class", "c__Nitrospinia"], ["order", "o__Nitrospinales"], ["family", "f__Nitrospinaceae"], ["genus", "g__SCGCAAA288-L16"]], 3]]], "TARA_PON_MAG_00064_000000000020": [6025, 6, []], "TARA_PON_MAG_00064_000000000021": [9534, 13, []], "TARA_PON_MAG_00064_000000000022": [4927, 5, [[[["superkingdom", "d__Bacteria"], ["phylum", "p__Nitrospinota"], ["class", "c__Nitrospinia"], ["order", "o__Nitrospinales"], ["family", "f__Nitrospinaceae"], ["genus", "g__SCGCAAA288-L16"]], 5]]], "TARA_PON_MAG_00064_000000000023": [2616, 3, [[[["superkingdom", "d__Bacteria"], ["phylum", "p__Nitrospinota"], ["class", "c__Nitrospinia"], ["order", "o__Nitrospinales"], ["family", "f__Nitrospinaceae"], ["genus", "g__SCGCAAA288-L16"]], 3]]], "TARA_PON_MAG_00064_000000000024": [6760, 7, [[[["superkingdom", "d__Bacteria"], ["phylum", "p__Nitrospinota"], ["class", "c__Nitrospinia"], ["order", "o__Nitrospinales"], ["family", "f__Nitrospinaceae"], ["genus", "g__SCGCAAA288-L16"]], 7]]], "TARA_PON_MAG_00064_000000000025": [3287, 3, []], "TARA_PON_MAG_00064_000000000026": [2615, 4, [[[["superkingdom", "d__Bacteria"], ["phylum", "p__Nitrospinota"], ["class", "c__Nitrospinia"], ["order", "o__Nitrospinales"], ["family", "f__Nitrospinaceae"], ["genus", "g__SCGCAAA288-L16"]], 1]]], "TARA_PON_MAG_00064_000000000027": [2791, 6, []], "TARA_PON_MAG_00064_000000000028": [3452, 5, []], "TARA_PON_MAG_00064_000000000029": [2894, 1, [[[["superkingdom", "d__Bacteria"], ["phylum", "p__Marinisomatota"], ["class", "c__Marinisomatia"], ["order", "o__Marinisomatales"], ["family", "f__UBA1611"], ["genus", "g__UBA2134"]], 1]]], "TARA_PON_MAG_00064_000000000030": [2642, 3, []], "TARA_PON_MAG_00064_000000000031": [2763, 2, []], "TARA_PON_MAG_00064_000000000032": [17045, 14, [[[["superkingdom", "d__Bacteria"], ["phylum", "p__Nitrospinota"], ["class", "c__Nitrospinia"], ["order", "o__Nitrospinales"], ["family", "f__Nitrospinaceae"], ["genus", "g__SCGCAAA288-L16"]], 12]]], "TARA_PON_MAG_00064_000000000033": [4524, 8, []], "TARA_PON_MAG_00064_000000000034": [3478, 2, []], "TARA_PON_MAG_00064_000000000035": [5628, 7, []], "TARA_PON_MAG_00064_000000000036": [3156, 6, []], "TARA_PON_MAG_00064_000000000037": [3891, 4, [[[["superkingdom", "d__Bacteria"], ["phylum", "p__Chloroflexota"], ["class", "c__Dehalococcoidia"], ["order", "o__UBA1151"], ["family", "f__Bin127"], ["genus", "g__GCA-002725925"]], 3]]], "TARA_PON_MAG_00064_000000000038": [3082, 0, []], "TARA_PON_MAG_00064_000000000039": [4718, 6, []], "TARA_PON_MAG_00064_000000000040": [4612, 2, []], "TARA_PON_MAG_00064_000000000041": [3233, 2, []], "TARA_PON_MAG_00064_000000000042": [3881, 3, []], "TARA_PON_MAG_00064_000000000043": [2611, 4, []], "TARA_PON_MAG_00064_000000000044": [4132, 7, []], "TARA_PON_MAG_00064_000000000045": [2772, 2, [[[["superkingdom", "d__Bacteria"], ["phylum", "p__Chloroflexota"], ["class", "c__Dehalococcoidia"], ["order", "o__UBA1151"], ["family", "f__Bin127"], ["genus", "g__GCA-002725925"]], 1]]], "TARA_PON_MAG_00064_000000000046": [2841, 8, []], "TARA_PON_MAG_00064_000000000047": [2544, 1, []], "TARA_PON_MAG_00064_000000000048": [2530, 2, []], "TARA_PON_MAG_00064_000000000049": [2646, 2, [[[["superkingdom", "d__Bacteria"], ["phylum", "p__Chloroflexota"], ["class", "c__Dehalococcoidia"], ["order", "o__UBA1151"], ["family", "f__Bin127"], ["genus", "g__GCA-002725925"]], 2]]], "TARA_PON_MAG_00064_000000000050": [7683, 7, [[[["superkingdom", "d__Bacteria"], ["phylum", "p__Nitrospinota"], ["class", "c__Nitrospinia"], ["order", "o__Nitrospinales"], ["family", "f__Nitrospinaceae"], ["genus", "g__SCGCAAA288-L16"]], 7]]], "TARA_PON_MAG_00064_000000000051": [3541, 5, []], "TARA_PON_MAG_00064_000000000052": [2705, 3, [[[["superkingdom", "d__Bacteria"], ["phylum", "p__Nitrospinota"], ["class", "c__Nitrospinia"], ["order", "o__Nitrospinales"], ["family", "f__Nitrospinaceae"], ["genus", "g__SCGCAAA288-L16"]], 2]]], "TARA_PON_MAG_00064_000000000053": [14562, 17, [[[["superkingdom", "d__Archaea"], ["phylum", "p__Thermoplasmatota"], ["class", "c__Poseidoniia"], ["order", "o__Poseidoniales"], ["family", "f__Thalassoarchaeaceae"], ["genus", "g__MGIIb-O1"]], 17]]], "TARA_PON_MAG_00064_000000000054": [2640, 3, []], "TARA_PON_MAG_00064_000000000055": [2531, 7, []], "TARA_PON_MAG_00064_000000000056": [4779, 3, [[[["superkingdom", "d__Archaea"], ["phylum", "p__Thermoplasmatota"], ["class", "c__Poseidoniia"], ["order", "o__MGIII"], ["family", "f__CG-Epi1"], ["genus", "g__CG-Epi1"]], 2]]], "TARA_PON_MAG_00064_000000000057": [2911, 4, []], "TARA_PON_MAG_00064_000000000058": [2821, 4, []], "TARA_PON_MAG_00064_000000000059": [4096, 8, [[[["superkingdom", "d__Bacteria"], ["phylum", "p__Nitrospinota"], ["class", "c__Nitrospinia"], ["order", "o__Nitrospinales"], ["family", "f__Nitrospinaceae"], ["genus", "g__SCGCAAA288-L16"]], 6]]], "TARA_PON_MAG_00064_000000000060": [6338, 7, [[[["superkingdom", "d__Bacteria"], ["phylum", "p__Nitrospinota"], ["class", "c__Nitrospinia"], ["order", "o__Nitrospinales"], ["family", "f__Nitrospinaceae"], ["genus", "g__SCGCAAA288-L16"]], 6]]], "TARA_PON_MAG_00064_000000000061": [2749, 0, []], "TARA_PON_MAG_00064_000000000062": [3847, 5, [[[["superkingdom", "d__Bacteria"], ["phylum", "p__Nitrospinota"], ["class", "c__Nitrospinia"], ["order", "o__Nitrospinales"], ["family", "f__Nitrospinaceae"], ["genus", "g__SCGCAAA288-L16"]], 4]]], "TARA_PON_MAG_00064_000000000063": [4900, 8, []], "TARA_PON_MAG_00064_000000000064": [17867, 15, [[[["superkingdom", "d__Bacteria"], ["phylum", "p__Chloroflexota"], ["class", "c__Dehalococcoidia"], ["order", "o__UBA1151"], ["family", "f__Bin127"], ["genus", "g__GCA-002725925"]], 11]]], "TARA_PON_MAG_00064_000000000065": [3606, 7, []], "TARA_PON_MAG_00064_000000000066": [2973, 3, []], "TARA_PON_MAG_00064_000000000067": [5270, 3, [[[["superkingdom", "d__Bacteria"], ["phylum", "p__Nitrospinota"], ["class", "c__Nitrospinia"], ["order", "o__Nitrospinales"], ["family", "f__Nitrospinaceae"], ["genus", "g__SCGCAAA288-L16"]], 2]]], "TARA_PON_MAG_00064_000000000068": [9898, 11, []], "TARA_PON_MAG_00064_000000000069": [4948, 2, []], "TARA_PON_MAG_00064_000000000070": [3845, 6, []], "TARA_PON_MAG_00064_000000000071": [6559, 3, [[[["superkingdom", "d__Bacteria"], ["phylum", "p__Nitrospinota"], ["class", "c__Nitrospinia"], ["order", "o__Nitrospinales"], ["family", "f__Nitrospinaceae"], ["genus", "g__SCGCAAA288-L16"]], 3]]], "TARA_PON_MAG_00064_000000000072": [3090, 2, [[[["superkingdom", "d__Bacteria"], ["phylum", "p__Nitrospinota"], ["class", "c__Nitrospinia"], ["order", "o__Nitrospinales"], ["family", "f__Nitrospinaceae"], ["genus", "g__SCGCAAA288-L16"]], 2]]], "TARA_PON_MAG_00064_000000000073": [2939, 2, []], "TARA_PON_MAG_00064_000000000074": [5267, 4, [[[["superkingdom", "d__Bacteria"], ["phylum", "p__Nitrospinota"], ["class", "c__Nitrospinia"], ["order", "o__Nitrospinales"], ["family", "f__Nitrospinaceae"], ["genus", "g__SCGCAAA288-L16"]], 3]]], "TARA_PON_MAG_00064_000000000075": [3419, 4, []], "TARA_PON_MAG_00064_000000000076": [2553, 1, [[[["superkingdom", "d__Bacteria"], ["phylum", "p__Nitrospinota"], ["class", "c__Nitrospinia"], ["order", "o__Nitrospinales"], ["family", "f__Nitrospinaceae"], ["genus", "g__SCGCAAA288-L16"]], 1]]], "TARA_PON_MAG_00064_000000000077": [4882, 6, [[[["superkingdom", "d__Bacteria"], ["phylum", "p__Nitrospinota"], ["class", "c__Nitrospinia"], ["order", "o__Nitrospinales"], ["family", "f__Nitrospinaceae"], ["genus", "g__SCGCAAA288-L16"]], 5]]], "TARA_PON_MAG_00064_000000000078": [4256, 5, [[[["superkingdom", "d__Bacteria"], ["phylum", "p__Proteobacteria"], ["class", "c__Alphaproteobacteria"], ["order", "o__GCA-2731375"], ["family", "f__GCA-2731375"], ["genus", "g__GCA-2731375"]], 4]]], "TARA_PON_MAG_00064_000000000079": [2528, 1, []], "TARA_PON_MAG_00064_000000000080": [3529, 4, [[[["superkingdom", "d__Bacteria"], ["phylum", "p__Nitrospinota"], ["class", "c__Nitrospinia"], ["order", "o__Nitrospinales"], ["family", "f__Nitrospinaceae"], ["genus", "g__SCGCAAA288-L16"]], 4]]], "TARA_PON_MAG_00064_000000000081": [5228, 7, []], "TARA_PON_MAG_00064_000000000082": [12599, 12, [[[["superkingdom", "d__Bacteria"], ["phylum", "p__Nitrospinota"], ["class", "c__Nitrospinia"], ["order", "o__Nitrospinales"], ["family", "f__Nitrospinaceae"], ["genus", "g__SCGCAAA288-L16"]], 10]]], "TARA_PON_MAG_00064_000000000083": [2676, 1, []], "TARA_PON_MAG_00064_000000000084": [2781, 1, []], "TARA_PON_MAG_00064_000000000085": [7332, 7, []], "TARA_PON_MAG_00064_000000000086": [2973, 2, []], "TARA_PON_MAG_00064_000000000087": [3603, 5, [[[["superkingdom", "d__Bacteria"], ["phylum", "p__Nitrospinota"], ["class", "c__Nitrospinia"], ["order", "o__Nitrospinales"], ["family", "f__Nitrospinaceae"], ["genus", "g__SCGCAAA288-L16"]], 4]]], "TARA_PON_MAG_00064_000000000088": [6245, 3, [[[["superkingdom", "d__Bacteria"], ["phylum", "p__Nitrospinota"], ["class", "c__Nitrospinia"], ["order", "o__Nitrospinales"], ["family", "f__Nitrospinaceae"], ["genus", "g__SCGCAAA288-L16"]], 3]]], "TARA_PON_MAG_00064_000000000089": [2866, 5, [[[["superkingdom", "d__Bacteria"], ["phylum", "p__Nitrospinota"], ["class", "c__Nitrospinia"], ["order", "o__Nitrospinales"], ["family", "f__Nitrospinaceae"], ["genus", "g__SCGCAAA288-L16"]], 5]]], "TARA_PON_MAG_00064_000000000090": [3060, 2, []], "TARA_PON_MAG_00064_000000000091": [5043, 9, []], "TARA_PON_MAG_00064_000000000092": [2715, 5, []], "TARA_PON_MAG_00064_000000000093": [10101, 6, [[[["superkingdom", "d__Bacteria"], ["phylum", "p__Nitrospinota"], ["class", "c__Nitrospinia"], ["order", "o__Nitrospinales"], ["family", "f__Nitrospinaceae"], ["genus", "g__SCGCAAA288-L16"]], 6]]], "TARA_PON_MAG_00064_000000000094": [5445, 4, []], "TARA_PON_MAG_00064_000000000095": [2919, 4, []], "TARA_PON_MAG_00064_000000000096": [2508, 5, [[[["superkingdom", "d__Bacteria"], ["phylum", "p__Chloroflexota"], ["class", "c__Dehalococcoidia"], ["order", "o__UBA1151"], ["family", "f__Bin127"], ["genus", "g__GCA-002725925"]], 4]]], "TARA_PON_MAG_00064_000000000097": [3587, 3, []], "TARA_PON_MAG_00064_000000000098": [5882, 8, [[[["superkingdom", "d__Bacteria"], ["phylum", "p__Nitrospinota"], ["class", "c__Nitrospinia"], ["order", "o__Nitrospinales"], ["family", "f__Nitrospinaceae"], ["genus", "g__SCGCAAA288-L16"]], 5]]], "TARA_PON_MAG_00064_000000000099": [3577, 6, []], "TARA_PON_MAG_00064_000000000100": [2536, 1, []], "TARA_PON_MAG_00064_000000000101": [7858, 15, [[[["superkingdom", "d__Archaea"], ["phylum", "p__Thermoplasmatota"], ["class", "c__Poseidoniia"], ["order", "o__MGIII"], ["family", "f__CG-Epi1"], ["genus", "g__CG-Epi1"]], 14]]], "TARA_PON_MAG_00064_000000000102": [10429, 14, [[[["superkingdom", "d__Bacteria"], ["phylum", "p__Nitrospinota"], ["class", "c__Nitrospinia"], ["order", "o__Nitrospinales"], ["family", "f__Nitrospinaceae"], ["genus", "g__SCGCAAA288-L16"]], 10]]], "TARA_PON_MAG_00064_000000000103": [2537, 6, [[[["superkingdom", "d__Bacteria"], ["phylum", "p__Chloroflexota"], ["class", "c__Dehalococcoidia"], ["order", "o__UBA1151"], ["family", "f__Bin127"], ["genus", "g__GCA-002725925"]], 5]]], "TARA_PON_MAG_00064_000000000104": [3480, 6, [[[["superkingdom", "d__Bacteria"], ["phylum", "p__Chloroflexota"], ["class", "c__Dehalococcoidia"], ["order", "o__UBA1151"], ["family", "f__Bin127"], ["genus", "g__GCA-002725925"]], 5]]], "TARA_PON_MAG_00064_000000000105": [3661, 5, []], "TARA_PON_MAG_00064_000000000106": [2784, 4, [[[["superkingdom", "d__Bacteria"], ["phylum", "p__Chloroflexota"], ["class", "c__Dehalococcoidia"], ["order", "o__UBA1151"], ["family", "f__Bin127"], ["genus", "g__GCA-002725925"]], 3]]], "TARA_PON_MAG_00064_000000000107": [4041, 6, []], "TARA_PON_MAG_00064_000000000108": [2664, 3, [[[["superkingdom", "d__Bacteria"], ["phylum", "p__Marinisomatota"], ["class", "c__Marinisomatia"], ["order", "o__Marinisomatales"], ["family", "f__UBA1611"], ["genus", "g__UBA2134"]], 3]]], "TARA_PON_MAG_00064_000000000109": [6587, 8, [[[["superkingdom", "d__Bacteria"], ["phylum", "p__Nitrospinota"], ["class", "c__Nitrospinia"], ["order", "o__Nitrospinales"], ["family", "f__Nitrospinaceae"], ["genus", "g__SCGCAAA288-L16"]], 7]]], "TARA_PON_MAG_00064_000000000110": [4586, 9, [[[["superkingdom", "d__Bacteria"], ["phylum", "p__Nitrospinota"], ["class", "c__Nitrospinia"], ["order", "o__Nitrospinales"], ["family", "f__Nitrospinaceae"], ["genus", "g__SCGCAAA288-L16"]], 9]]], "TARA_PON_MAG_00064_000000000111": [4246, 5, [[[["superkingdom", "d__Bacteria"], ["phylum", "p__Nitrospinota"], ["class", "c__Nitrospinia"], ["order", "o__Nitrospinales"], ["family", "f__Nitrospinaceae"], ["genus", "g__SCGCAAA288-L16"]], 5]]], "TARA_PON_MAG_00064_000000000112": [11729, 11, [[[["superkingdom", "d__Bacteria"], ["phylum", "p__Nitrospinota"], ["class", "c__Nitrospinia"], ["order", "o__Nitrospinales"], ["family", "f__Nitrospinaceae"], ["genus", "g__SCGCAAA288-L16"]], 10]]], "TARA_PON_MAG_00064_000000000113": [2529, 3, []], "TARA_PON_MAG_00064_000000000114": [3273, 3, [[[["superkingdom", "d__Bacteria"], ["phylum", "p__Chloroflexota"], ["class", "c__Dehalococcoidia"], ["order", "o__UBA1151"], ["family", "f__Bin127"], ["genus", "g__GCA-002725925"]], 3]]], "TARA_PON_MAG_00064_000000000115": [4482, 3, []], "TARA_PON_MAG_00064_000000000116": [3216, 2, [[[["superkingdom", "d__Bacteria"], ["phylum", "p__Chloroflexota"], ["class", "c__Dehalococcoidia"], ["order", "o__UBA1151"], ["family", "f__Bin127"], ["genus", "g__GCA-002725925"]], 2]]], "TARA_PON_MAG_00064_000000000117": [5064, 4, [[[["superkingdom", "d__Bacteria"], ["phylum", "p__Nitrospinota"], ["class", "c__Nitrospinia"], ["order", "o__Nitrospinales"], ["family", "f__Nitrospinaceae"], ["genus", "g__SCGCAAA288-L16"]], 3]]], "TARA_PON_MAG_00064_000000000118": [5502, 3, [[[["superkingdom", "d__Bacteria"], ["phylum", "p__Nitrospinota"], ["class", "c__Nitrospinia"], ["order", "o__Nitrospinales"], ["family", "f__Nitrospinaceae"], ["genus", "g__SCGCAAA288-L16"]], 2]]], "TARA_PON_MAG_00064_000000000119": [2904, 5, [[[["superkingdom", "d__Bacteria"], ["phylum", "p__Marinisomatota"], ["class", "c__Marinisomatia"], ["order", "o__Marinisomatales"], ["family", "f__UBA1611"], ["genus", "g__UBA2134"]], 4]]], "TARA_PON_MAG_00064_000000000120": [4227, 7, [[[["superkingdom", "d__Bacteria"], ["phylum", "p__Nitrospinota"], ["class", "c__Nitrospinia"], ["order", "o__Nitrospinales"], ["family", "f__Nitrospinaceae"], ["genus", "g__SCGCAAA288-L16"]], 7]]], "TARA_PON_MAG_00064_000000000121": [4144, 3, []], "TARA_PON_MAG_00064_000000000122": [4311, 5, []], "TARA_PON_MAG_00064_000000000123": [8077, 8, [[[["superkingdom", "d__Bacteria"], ["phylum", "p__Nitrospinota"], ["class", "c__Nitrospinia"], ["order", "o__Nitrospinales"], ["family", "f__Nitrospinaceae"], ["genus", "g__SCGCAAA288-L16"]], 8]]], "TARA_PON_MAG_00064_000000000124": [7299, 8, []], "TARA_PON_MAG_00064_000000000125": [4479, 6, []], "TARA_PON_MAG_00064_000000000126": [3263, 4, []], "TARA_PON_MAG_00064_000000000127": [3516, 3, []], "TARA_PON_MAG_00064_000000000128": [11926, 9, [[[["superkingdom", "d__Bacteria"], ["phylum", "p__Nitrospinota"], ["class", "c__Nitrospinia"], ["order", "o__Nitrospinales"], ["family", "f__Nitrospinaceae"], ["genus", "g__SCGCAAA288-L16"]], 8]]], "TARA_PON_MAG_00064_000000000129": [3684, 4, []], "TARA_PON_MAG_00064_000000000130": [2867, 0, []], "TARA_PON_MAG_00064_000000000131": [3544, 4, []], "TARA_PON_MAG_00064_000000000132": [6625, 6, [[[["superkingdom", "d__Bacteria"], ["phylum", "p__Marinisomatota"], ["class", "c__Marinisomatia"], ["order", "o__Marinisomatales"], ["family", "f__UBA1611"], ["genus", "g__UBA2134"]], 6]]], "TARA_PON_MAG_00064_000000000133": [4336, 10, []], "TARA_PON_MAG_00064_000000000134": [4064, 5, []], "TARA_PON_MAG_00064_000000000135": [3613, 1, [[[["superkingdom", "d__Bacteria"], ["phylum", "p__Nitrospinota"], ["class", "c__Nitrospinia"], ["order", "o__Nitrospinales"], ["family", "f__Nitrospinaceae"], ["genus", "g__SCGCAAA288-L16"]], 1]]], "TARA_PON_MAG_00064_000000000136": [4966, 6, []], "TARA_PON_MAG_00064_000000000137": [2901, 2, [[[["superkingdom", "d__Bacteria"], ["phylum", "p__Chloroflexota"], ["class", "c__Dehalococcoidia"], ["order", "o__UBA1151"], ["family", "f__Bin127"], ["genus", "g__GCA-002725925"]], 1]]], "TARA_PON_MAG_00064_000000000138": [3892, 2, [[[["superkingdom", "d__Archaea"], ["phylum", "p__Thermoplasmatota"], ["class", "c__Poseidoniia"], ["order", "o__MGIII"], ["family", "f__CG-Epi1"], ["genus", "g__CG-Epi1"]], 2]]], "TARA_PON_MAG_00064_000000000139": [6794, 7, [[[["superkingdom", "d__Bacteria"], ["phylum", "p__Nitrospinota"], ["class", "c__Nitrospinia"], ["order", "o__Nitrospinales"], ["family", "f__Nitrospinaceae"], ["genus", "g__SCGCAAA288-L16"]], 6]]], "TARA_PON_MAG_00064_000000000140": [9004, 10, []], "TARA_PON_MAG_00064_000000000141": [3719, 3, []], "TARA_PON_MAG_00064_000000000142": [2686, 1, []], "TARA_PON_MAG_00064_000000000143": [2804, 2, []], "TARA_PON_MAG_00064_000000000144": [2668, 2, []], "TARA_PON_MAG_00064_000000000145": [7122, 6, [[[["superkingdom", "d__Bacteria"], ["phylum", "p__Nitrospinota"], ["class", "c__Nitrospinia"], ["order", "o__Nitrospinales"], ["family", "f__Nitrospinaceae"], ["genus", "g__SCGCAAA288-L16"]], 1]]], "TARA_PON_MAG_00064_000000000146": [3347, 1, []], "TARA_PON_MAG_00064_000000000147": [3391, 3, [[[["superkingdom", "d__Bacteria"], ["phylum", "p__Chloroflexota"], ["class", "c__Dehalococcoidia"], ["order", "o__UBA1151"], ["family", "f__Bin127"], ["genus", "g__GCA-002725925"]], 2]]], "TARA_PON_MAG_00064_000000000148": [3153, 2, []], "TARA_PON_MAG_00064_000000000149": [6726, 6, [[[["superkingdom", "d__Bacteria"], ["phylum", "p__Proteobacteria"], ["class", "c__Alphaproteobacteria"], ["order", "o__Rhodospirillales_A"], ["family", "f__UBA2165"], ["genus", "g__UBA2165"]], 1]]], "TARA_PON_MAG_00064_000000000150": [5173, 6, [[[["superkingdom", "d__Bacteria"], ["phylum", "p__Chloroflexota"], ["class", "c__Dehalococcoidia"], ["order", "o__UBA1151"], ["family", "f__Bin127"], ["genus", "g__GCA-002725925"]], 2]]], "TARA_PON_MAG_00064_000000000151": [5497, 6, [[[["superkingdom", "d__Bacteria"], ["phylum", "p__Nitrospinota"], ["class", "c__Nitrospinia"], ["order", "o__Nitrospinales"], ["family", "f__Nitrospinaceae"], ["genus", "g__SCGCAAA288-L16"]], 5]]], "TARA_PON_MAG_00064_000000000152": [4835, 5, [[[["superkingdom", "d__Archaea"], ["phylum", "p__Thermoplasmatota"], ["class", "c__Poseidoniia"], ["order", "o__Poseidoniales"], ["family", "f__Thalassoarchaeaceae"], ["genus", "g__MGIIb-O1"]], 2]]], "TARA_PON_MAG_00064_000000000153": [2565, 3, [[[["superkingdom", "d__Bacteria"], ["phylum", "p__Nitrospinota"], ["class", "c__Nitrospinia"], ["order", "o__Nitrospinales"], ["family", "f__Nitrospinaceae"], ["genus", "g__SCGCAAA288-L16"]], 2]]], "TARA_PON_MAG_00064_000000000154": [3879, 5, []], "TARA_PON_MAG_00064_000000000155": [3864, 9, []], "TARA_PON_MAG_00064_000000000156": [4304, 5, [[[["superkingdom", "d__Bacteria"], ["phylum", "p__Marinisomatota"], ["class", "c__Marinisomatia"], ["order", "o__Marinisomatales"], ["family", "f__UBA1611"], ["genus", "g__UBA2134"]], 5]]], "TARA_PON_MAG_00064_000000000157": [3260, 5, []], "TARA_PON_MAG_00064_000000000158": [5546, 7, []], "TARA_PON_MAG_00064_000000000159": [3175, 4, []], "TARA_PON_MAG_00064_000000000160": [4260, 5, []], "TARA_PON_MAG_00064_000000000161": [8439, 5, [[[["superkingdom", "d__Bacteria"], ["phylum", "p__Nitrospinota"], ["class", "c__Nitrospinia"], ["order", "o__Nitrospinales"], ["family", "f__Nitrospinaceae"], ["genus", "g__SCGCAAA288-L16"]], 4]]], "TARA_PON_MAG_00064_000000000162": [2864, 7, []], "TARA_PON_MAG_00064_000000000163": [3747, 2, [[[["superkingdom", "d__Bacteria"], ["phylum", "p__Nitrospinota"], ["class", "c__Nitrospinia"], ["order", "o__Nitrospinales"], ["family", "f__Nitrospinaceae"], ["genus", "g__SCGCAAA288-L16"]], 1]]], "TARA_PON_MAG_00064_000000000164": [3919, 4, [[[["superkingdom", "d__Bacteria"], ["phylum", "p__Nitrospinota"], ["class", "c__Nitrospinia"], ["order", "o__Nitrospinales"], ["family", "f__Nitrospinaceae"], ["genus", "g__SCGCAAA288-L16"]], 4]]], "TARA_PON_MAG_00064_000000000165": [2653, 1, []], "TARA_PON_MAG_00064_000000000166": [2643, 5, [[[["superkingdom", "d__Bacteria"], ["phylum", "p__Proteobacteria"], ["class", "c__Alphaproteobacteria"], ["order", "o__Rhodospirillales_A"], ["family", "f__UBA2165"], ["genus", "g__UBA2165"]], 1]]], "TARA_PON_MAG_00064_000000000167": [2790, 3, [[[["superkingdom", "d__Bacteria"], ["phylum", "p__Marinisomatota"], ["class", "c__Marinisomatia"], ["order", "o__Marinisomatales"], ["family", "f__UBA1611"], ["genus", "g__UBA2134"]], 3]]], "TARA_PON_MAG_00064_000000000168": [2782, 1, [[[["superkingdom", "d__Bacteria"], ["phylum", "p__Proteobacteria"], ["class", "c__Alphaproteobacteria"], ["order", "o__Rhodospirillales_A"], ["family", "f__UBA2165"], ["genus", "g__UBA2165"]], 1]]], "TARA_PON_MAG_00064_000000000169": [2635, 3, []], "TARA_PON_MAG_00064_000000000170": [2512, 2, [[[["superkingdom", "d__Bacteria"], ["phylum", "p__Chloroflexota"], ["class", "c__Dehalococcoidia"], ["order", "o__UBA1151"], ["family", "f__Bin127"], ["genus", "g__GCA-002725925"]], 2]]], "TARA_PON_MAG_00064_000000000171": [3856, 4, [[[["superkingdom", "d__Bacteria"], ["phylum", "p__Nitrospinota"], ["class", "c__Nitrospinia"], ["order", "o__Nitrospinales"], ["family", "f__Nitrospinaceae"], ["genus", "g__SCGCAAA288-L16"]], 4]]], "TARA_PON_MAG_00064_000000000172": [2734, 2, []], "TARA_PON_MAG_00064_000000000173": [3536, 3, []], "TARA_PON_MAG_00064_000000000174": [4277, 6, [[[["superkingdom", "d__Bacteria"], ["phylum", "p__Nitrospinota"], ["class", "c__Nitrospinia"], ["order", "o__Nitrospinales"], ["family", "f__Nitrospinaceae"], ["genus", "g__SCGCAAA288-L16"]], 5]]], "TARA_PON_MAG_00064_000000000175": [11215, 18, []], "TARA_PON_MAG_00064_000000000176": [3962, 1, [[[["superkingdom", "d__Bacteria"], ["phylum", "p__Nitrospinota"], ["class", "c__Nitrospinia"], ["order", "o__Nitrospinales"], ["family", "f__Nitrospinaceae"], ["genus", "g__SCGCAAA288-L16"]], 1]]], "TARA_PON_MAG_00064_000000000177": [3636, 6, []], "TARA_PON_MAG_00064_000000000178": [3527, 3, []], "TARA_PON_MAG_00064_000000000179": [2509, 4, [[[["superkingdom", "d__Bacteria"], ["phylum", "p__Chloroflexota"], ["class", "c__Dehalococcoidia"], ["order", "o__UBA1151"], ["family", "f__Bin127"], ["genus", "g__GCA-002725925"]], 3]]], "TARA_PON_MAG_00064_000000000180": [5091, 7, []], "TARA_PON_MAG_00064_000000000181": [2966, 6, []], "TARA_PON_MAG_00064_000000000182": [5163, 3, [[[["superkingdom", "d__Bacteria"], ["phylum", "p__Nitrospinota"], ["class", "c__Nitrospinia"], ["order", "o__Nitrospinales"], ["family", "f__Nitrospinaceae"], ["genus", "g__SCGCAAA288-L16"]], 2]]], "TARA_PON_MAG_00064_000000000183": [3081, 2, [[[["superkingdom", "d__Bacteria"], ["phylum", "p__Proteobacteria"], ["class", "c__Gammaproteobacteria"], ["order", "o__Pseudomonadales"], ["family", "f__HTCC2089"], ["genus", "g__GCA-2725285"]], 2]]], "TARA_PON_MAG_00064_000000000184": [7580, 13, [[[["superkingdom", "d__Bacteria"], ["phylum", "p__Chloroflexota"], ["class", "c__Dehalococcoidia"], ["order", "o__UBA1151"], ["family", "f__Bin127"], ["genus", "g__GCA-002725925"]], 9]]], "TARA_PON_MAG_00064_000000000185": [5087, 3, []], "TARA_PON_MAG_00064_000000000186": [4468, 5, [[[["superkingdom", "d__Bacteria"], ["phylum", "p__Nitrospinota"], ["class", "c__Nitrospinia"], ["order", "o__Nitrospinales"], ["family", "f__Nitrospinaceae"], ["genus", "g__SCGCAAA288-L16"]], 5]]], "TARA_PON_MAG_00064_000000000187": [14467, 21, [[[["superkingdom", "d__Bacteria"], ["phylum", "p__Nitrospinota"], ["class", "c__Nitrospinia"], ["order", "o__Nitrospinales"], ["family", "f__Nitrospinaceae"], ["genus", "g__SCGCAAA288-L16"]], 13]]], "TARA_PON_MAG_00064_000000000188": [5821, 9, [[[["superkingdom", "d__Bacteria"], ["phylum", "p__SAR324"], ["class", "c__SAR324"], ["order", "o__SAR324"], ["family", "f__NAC60-12"], ["genus", "g__UBA1014"]], 9]]], "TARA_PON_MAG_00064_000000000189": [4528, 4, [[[["superkingdom", "d__Bacteria"], ["phylum", "p__Nitrospinota"], ["class", "c__Nitrospinia"], ["order", "o__Nitrospinales"], ["family", "f__Nitrospinaceae"], ["genus", "g__SCGCAAA288-L16"]], 3]]], "TARA_PON_MAG_00064_000000000190": [3616, 1, [[[["superkingdom", "d__Bacteria"], ["phylum", "p__Nitrospinota"], ["class", "c__Nitrospinia"], ["order", "o__Nitrospinales"], ["family", "f__Nitrospinaceae"], ["genus", "g__SCGCAAA288-L16"]], 1]]], "TARA_PON_MAG_00064_000000000191": [3001, 6, [[[["superkingdom", "d__Bacteria"], ["phylum", "p__Nitrospinota"], ["class", "c__Nitrospinia"], ["order", "o__Nitrospinales"], ["family", "f__Nitrospinaceae"], ["genus", "g__SCGCAAA288-L16"]], 6]]], "TARA_PON_MAG_00064_000000000192": [9902, 6, [[[["superkingdom", "d__Bacteria"], ["phylum", "p__Chloroflexota"], ["class", "c__Dehalococcoidia"], ["order", "o__UBA1151"], ["family", "f__Bin127"], ["genus", "g__GCA-002725925"]], 3]]], "TARA_PON_MAG_00064_000000000193": [4754, 2, [[[["superkingdom", "d__Bacteria"], ["phylum", "p__Nitrospinota"], ["class", "c__Nitrospinia"], ["order", "o__Nitrospinales"], ["family", "f__Nitrospinaceae"], ["genus", "g__SCGCAAA288-L16"]], 2]]], "TARA_PON_MAG_00064_000000000194": [3003, 2, [[[["superkingdom", "d__Bacteria"], ["phylum", "p__Nitrospinota"], ["class", "c__Nitrospinia"], ["order", "o__Nitrospinales"], ["family", "f__Nitrospinaceae"], ["genus", "g__SCGCAAA288-L16"]], 2]]], "TARA_PON_MAG_00064_000000000195": [3427, 3, [[[["superkingdom", "d__Bacteria"], ["phylum", "p__Nitrospinota"], ["class", "c__Nitrospinia"], ["order", "o__Nitrospinales"], ["family", "f__Nitrospinaceae"], ["genus", "g__SCGCAAA288-L16"]], 2]]], "TARA_PON_MAG_00064_000000000196": [2896, 3, [[[["superkingdom", "d__Bacteria"], ["phylum", "p__Chloroflexota"], ["class", "c__Dehalococcoidia"], ["order", "o__UBA1151"], ["family", "f__Bin127"], ["genus", "g__GCA-002725925"]], 3]]], "TARA_PON_MAG_00064_000000000197": [3884, 4, [[[["superkingdom", "d__Bacteria"], ["phylum", "p__Nitrospinota"], ["class", "c__Nitrospinia"], ["order", "o__Nitrospinales"], ["family", "f__Nitrospinaceae"], ["genus", "g__SCGCAAA288-L16"]], 4]]], "TARA_PON_MAG_00064_000000000198": [3016, 1, []], "TARA_PON_MAG_00064_000000000199": [3874, 5, []], "TARA_PON_MAG_00064_000000000200": [3618, 2, []], "TARA_PON_MAG_00064_000000000201": [5011, 7, [[[["superkingdom", "d__Bacteria"], ["phylum", "p__Chloroflexota"], ["class", "c__Dehalococcoidia"], ["order", "o__UBA1151"], ["family", "f__Bin127"], ["genus", "g__GCA-002725925"]], 6]]], "TARA_PON_MAG_00064_000000000202": [3159, 5, [[[["superkingdom", "d__Bacteria"], ["phylum", "p__Chloroflexota"], ["class", "c__Dehalococcoidia"], ["order", "o__UBA1151"], ["family", "f__Bin127"], ["genus", "g__GCA-002725925"]], 2]]], "TARA_PON_MAG_00064_000000000203": [4790, 5, [[[["superkingdom", "d__Bacteria"], ["phylum", "p__Nitrospinota"], ["class", "c__Nitrospinia"], ["order", "o__Nitrospinales"], ["family", "f__Nitrospinaceae"], ["genus", "g__SCGCAAA288-L16"]], 4]]], "TARA_PON_MAG_00064_000000000204": [3159, 3, []], "TARA_PON_MAG_00064_000000000205": [6100, 13, []], "TARA_PON_MAG_00064_000000000206": [3158, 3, [[[["superkingdom", "d__Bacteria"], ["phylum", "p__Marinisomatota"], ["class", "c__Marinisomatia"], ["order", "o__Marinisomatales"], ["family", "f__UBA1611"], ["genus", "g__UBA2134"]], 2]]], "TARA_PON_MAG_00064_000000000207": [2877, 2, [[[["superkingdom", "d__Bacteria"], ["phylum", "p__Nitrospinota"], ["class", "c__Nitrospinia"], ["order", "o__Nitrospinales"], ["family", "f__Nitrospinaceae"], ["genus", "g__SCGCAAA288-L16"]], 2]]], "TARA_PON_MAG_00064_000000000208": [8283, 11, []], "TARA_PON_MAG_00064_000000000209": [2731, 2, []], "TARA_PON_MAG_00064_000000000210": [4040, 3, [[[["superkingdom", "d__Bacteria"], ["phylum", "p__Nitrospinota"], ["class", "c__Nitrospinia"], ["order", "o__Nitrospinales"], ["family", "f__Nitrospinaceae"], ["genus", "g__SCGCAAA288-L16"]], 3]]], "TARA_PON_MAG_00064_000000000211": [3403, 1, []], "TARA_PON_MAG_00064_000000000212": [7659, 9, [[[["superkingdom", "d__Bacteria"], ["phylum", "p__Nitrospinota"], ["class", "c__Nitrospinia"], ["order", "o__Nitrospinales"], ["family", "f__Nitrospinaceae"], ["genus", "g__SCGCAAA288-L16"]], 8]]], "TARA_PON_MAG_00064_000000000213": [6333, 5, [[[["superkingdom", "d__Bacteria"], ["phylum", "p__Marinisomatota"], ["class", "c__Marinisomatia"], ["order", "o__Marinisomatales"], ["family", "f__UBA1611"], ["genus", "g__UBA2134"]], 3]]], "TARA_PON_MAG_00064_000000000214": [2546, 3, [[[["superkingdom", "d__Bacteria"], ["phylum", "p__Nitrospinota"], ["class", "c__Nitrospinia"], ["order", "o__Nitrospinales"], ["family", "f__Nitrospinaceae"], ["genus", "g__SCGCAAA288-L16"]], 2]]], "TARA_PON_MAG_00064_000000000215": [5446, 5, []], "TARA_PON_MAG_00064_000000000216": [3893, 1, [[[["superkingdom", "d__Bacteria"], ["phylum", "p__Nitrospinota"], ["class", "c__Nitrospinia"], ["order", "o__Nitrospinales"], ["family", "f__Nitrospinaceae"], ["genus", "g__SCGCAAA288-L16"]], 1]]], "TARA_PON_MAG_00064_000000000217": [3242, 2, [[[["superkingdom", "d__Bacteria"], ["phylum", "p__Nitrospinota"], ["class", "c__Nitrospinia"], ["order", "o__Nitrospinales"], ["family", "f__Nitrospinaceae"], ["genus", "g__SCGCAAA288-L16"]], 1]]], "TARA_PON_MAG_00064_000000000218": [4215, 2, [[[["superkingdom", "d__Bacteria"], ["phylum", "p__Chloroflexota"], ["class", "c__Dehalococcoidia"], ["order", "o__UBA1151"], ["family", "f__Bin127"], ["genus", "g__GCA-002725925"]], 1]]], "TARA_PON_MAG_00064_000000000219": [3839, 4, []], "TARA_PON_MAG_00064_000000000220": [5329, 9, []], "TARA_PON_MAG_00064_000000000221": [3325, 4, [[[["superkingdom", "d__Bacteria"], ["phylum", "p__Chloroflexota"], ["class", "c__Dehalococcoidia"], ["order", "o__UBA1151"], ["family", "f__Bin127"], ["genus", "g__GCA-002725925"]], 4]]], "TARA_PON_MAG_00064_000000000222": [3414, 3, [[[["superkingdom", "d__Bacteria"], ["phylum", "p__SAR324"], ["class", "c__SAR324"], ["order", "o__SAR324"], ["family", "f__NAC60-12"], ["genus", "g__UBA1014"]], 3]]], "TARA_PON_MAG_00064_000000000223": [5689, 7, []], "TARA_PON_MAG_00064_000000000224": [2893, 5, []], "TARA_PON_MAG_00064_000000000225": [2612, 1, []], "TARA_PON_MAG_00064_000000000226": [8269, 9, [[[["superkingdom", "d__Bacteria"], ["phylum", "p__Nitrospinota"], ["class", "c__Nitrospinia"], ["order", "o__Nitrospinales"], ["family", "f__Nitrospinaceae"], ["genus", "g__SCGCAAA288-L16"]], 5]]], "TARA_PON_MAG_00064_000000000227": [10353, 5, [[[["superkingdom", "d__Bacteria"], ["phylum", "p__Nitrospinota"], ["class", "c__Nitrospinia"], ["order", "o__Nitrospinales"], ["family", "f__Nitrospinaceae"], ["genus", "g__SCGCAAA288-L16"]], 4]]], "TARA_PON_MAG_00064_000000000228": [4059, 5, []], "TARA_PON_MAG_00064_000000000229": [3071, 5, []], "TARA_PON_MAG_00064_000000000230": [7205, 7, [[[["superkingdom", "d__Bacteria"], ["phylum", "p__Nitrospinota"], ["class", "c__Nitrospinia"], ["order", "o__Nitrospinales"], ["family", "f__Nitrospinaceae"], ["genus", "g__SCGCAAA288-L16"]], 6]]], "TARA_PON_MAG_00064_000000000231": [5868, 5, []], "TARA_PON_MAG_00064_000000000232": [3675, 5, []], "TARA_PON_MAG_00064_000000000233": [5433, 6, []], "TARA_PON_MAG_00064_000000000234": [5434, 7, []], "TARA_PON_MAG_00064_000000000235": [2539, 1, [[[["superkingdom", "d__Bacteria"], ["phylum", "p__Proteobacteria"], ["class", "c__Gammaproteobacteria"], ["order", "o__Pseudomonadales"], ["family", "f__HTCC2089"], ["genus", "g__GCA-2725285"]], 1]]], "TARA_PON_MAG_00064_000000000236": [8453, 9, []], "TARA_PON_MAG_00064_000000000237": [9895, 12, [[[["superkingdom", "d__Bacteria"], ["phylum", "p__Nitrospinota"], ["class", "c__Nitrospinia"], ["order", "o__Nitrospinales"], ["family", "f__Nitrospinaceae"], ["genus", "g__SCGCAAA288-L16"]], 12]]], "TARA_PON_MAG_00064_000000000238": [3822, 4, []], "TARA_PON_MAG_00064_000000000239": [8817, 7, [[[["superkingdom", "d__Bacteria"], ["phylum", "p__Nitrospinota"], ["class", "c__Nitrospinia"], ["order", "o__Nitrospinales"], ["family", "f__Nitrospinaceae"], ["genus", "g__SCGCAAA288-L16"]], 5]]], "TARA_PON_MAG_00064_000000000240": [7867, 7, [[[["superkingdom", "d__Bacteria"], ["phylum", "p__Nitrospinota"], ["class", "c__Nitrospinia"], ["order", "o__Nitrospinales"], ["family", "f__Nitrospinaceae"], ["genus", "g__SCGCAAA288-L16"]], 5]]], "TARA_PON_MAG_00064_000000000241": [4056, 4, []], "TARA_PON_MAG_00064_000000000242": [5870, 7, []], "TARA_PON_MAG_00064_000000000243": [5877, 5, []], "TARA_PON_MAG_00064_000000000244": [3066, 1, []], "TARA_PON_MAG_00064_000000000245": [4098, 5, [[[["superkingdom", "d__Bacteria"], ["phylum", "p__Nitrospinota"], ["class", "c__Nitrospinia"], ["order", "o__Nitrospinales"], ["family", "f__Nitrospinaceae"], ["genus", "g__SCGCAAA288-L16"]], 4]]], "TARA_PON_MAG_00064_000000000246": [2878, 1, []], "TARA_PON_MAG_00064_000000000247": [8481, 11, [[[["superkingdom", "d__Bacteria"], ["phylum", "p__Nitrospinota"], ["class", "c__Nitrospinia"], ["order", "o__Nitrospinales"], ["family", "f__Nitrospinaceae"], ["genus", "g__SCGCAAA288-L16"]], 10]]], "TARA_PON_MAG_00064_000000000248": [6533, 6, []], "TARA_PON_MAG_00064_000000000249": [3162, 2, []], "TARA_PON_MAG_00064_000000000250": [4271, 4, [[[["superkingdom", "d__Bacteria"], ["phylum", "p__Nitrospirota"], ["class", "c__Nitrospiria"], ["order", "o__Nitrospirales"], ["family", "f__UBA2166"], ["genus", "g__UBA2166"]], 4]]], "TARA_PON_MAG_00064_000000000251": [3556, 6, []], "TARA_PON_MAG_00064_000000000252": [2545, 4, [[[["superkingdom", "d__Bacteria"], ["phylum", "p__Chloroflexota"], ["class", "c__Dehalococcoidia"], ["order", "o__UBA1151"], ["family", "f__Bin127"], ["genus", "g__GCA-002725925"]], 1]]], "TARA_PON_MAG_00064_000000000253": [4920, 2, [[[["superkingdom", "d__Bacteria"], ["phylum", "p__Nitrospinota"], ["class", "c__Nitrospinia"], ["order", "o__Nitrospinales"], ["family", "f__Nitrospinaceae"], ["genus", "g__SCGCAAA288-L16"]], 1]]], "TARA_PON_MAG_00064_000000000254": [2520, 1, [[[["superkingdom", "d__Bacteria"], ["phylum", "p__Nitrospinota"], ["class", "c__Nitrospinia"], ["order", "o__Nitrospinales"], ["family", "f__Nitrospinaceae"], ["genus", "g__SCGCAAA288-L16"]], 1]]], "TARA_PON_MAG_00064_000000000255": [2715, 1, []], "TARA_PON_MAG_00064_000000000256": [3225, 2, []], "TARA_PON_MAG_00064_000000000257": [2502, 4, []], "TARA_PON_MAG_00064_000000000258": [3820, 8, [[[["superkingdom", "d__Bacteria"], ["phylum", "p__Marinisomatota"], ["class", "c__Marinisomatia"], ["order", "o__Marinisomatales"], ["family", "f__UBA1611"], ["genus", "g__UBA2134"]], 4]]], "TARA_PON_MAG_00064_000000000259": [4069, 4, []], "TARA_PON_MAG_00064_000000000260": [3001, 5, [[[["superkingdom", "d__Bacteria"], ["phylum", "p__Chloroflexota"], ["class", "c__Dehalococcoidia"], ["order", "o__UBA1151"], ["family", "f__Bin127"], ["genus", "g__GCA-002725925"]], 5]]], "TARA_PON_MAG_00064_000000000261": [4564, 1, [[[["superkingdom", "d__Bacteria"], ["phylum", "p__Nitrospinota"], ["class", "c__Nitrospinia"], ["order", "o__Nitrospinales"], ["family", "f__Nitrospinaceae"], ["genus", "g__SCGCAAA288-L16"]], 1]]], "TARA_PON_MAG_00064_000000000262": [2750, 2, []], "TARA_PON_MAG_00064_000000000263": [4774, 5, []], "TARA_PON_MAG_00064_000000000264": [10226, 6, [[[["superkingdom", "d__Bacteria"], ["phylum", "p__Nitrospinota"], ["class", "c__Nitrospinia"], ["order", "o__Nitrospinales"], ["family", "f__Nitrospinaceae"], ["genus", "g__SCGCAAA288-L16"]], 1]]], "TARA_PON_MAG_00064_000000000265": [4338, 4, []], "TARA_PON_MAG_00064_000000000266": [3454, 2, []], "TARA_PON_MAG_00064_000000000267": [13038, 11, [[[["superkingdom", "d__Bacteria"], ["phylum", "p__Nitrospinota"], ["class", "c__Nitrospinia"], ["order", "o__Nitrospinales"], ["family", "f__Nitrospinaceae"], ["genus", "g__SCGCAAA288-L16"]], 2]]], "TARA_PON_MAG_00064_000000000268": [3668, 2, [[[["superkingdom", "d__Bacteria"], ["phylum", "p__Chloroflexota"], ["class", "c__Dehalococcoidia"], ["order", "o__UBA1151"], ["family", "f__Bin127"], ["genus", "g__GCA-002725925"]], 2]]], "TARA_PON_MAG_00064_000000000269": [3000, 1, []], "TARA_PON_MAG_00064_000000000270": [6937, 10, [[[["superkingdom", "d__Bacteria"], ["phylum", "p__Nitrospinota"], ["class", "c__Nitrospinia"], ["order", "o__Nitrospinales"], ["family", "f__Nitrospinaceae"], ["genus", "g__SCGCAAA288-L16"]], 5]]], "TARA_PON_MAG_00064_000000000271": [8529, 6, [[[["superkingdom", "d__Bacteria"], ["phylum", "p__Proteobacteria"], ["class", "c__Gammaproteobacteria"], ["order", "o__Pseudomonadales"], ["family", "f__HTCC2089"], ["genus", "g__GCA-002726655"]], 6]]], "TARA_PON_MAG_00064_000000000272": [2986, 4, [[[["superkingdom", "d__Bacteria"], ["phylum", "p__Nitrospinota"], ["class", "c__Nitrospinia"], ["order", "o__Nitrospinales"], ["family", "f__Nitrospinaceae"], ["genus", "g__SCGCAAA288-L16"]], 3]]], "TARA_PON_MAG_00064_000000000273": [2610, 1, [[[["superkingdom", "d__Bacteria"], ["phylum", "p__Nitrospirota"], ["class", "c__Nitrospiria"], ["order", "o__Nitrospirales"], ["family", "f__UBA2166"], ["genus", "g__UBA2166"]], 1]]], "TARA_PON_MAG_00064_000000000274": [4118, 3, []], "TARA_PON_MAG_00064_000000000275": [2672, 2, [[[["superkingdom", "d__Bacteria"], ["phylum", "p__Chloroflexota"], ["class", "c__Dehalococcoidia"], ["order", "o__UBA1151"], ["family", "f__Bin127"], ["genus", "g__GCA-002725925"]], 1]]], "TARA_PON_MAG_00064_000000000276": [5381, 7, []], "TARA_PON_MAG_00064_000000000277": [9929, 6, [[[["superkingdom", "d__Bacteria"], ["phylum", "p__Nitrospinota"], ["class", "c__Nitrospinia"], ["order", "o__Nitrospinales"], ["family", "f__Nitrospinaceae"], ["genus", "g__SCGCAAA288-L16"]], 5]]], "TARA_PON_MAG_00064_000000000278": [7157, 6, [[[["superkingdom", "d__Bacteria"], ["phylum", "p__Nitrospinota"], ["class", "c__Nitrospinia"], ["order", "o__Nitrospinales"], ["family", "f__Nitrospinaceae"], ["genus", "g__SCGCAAA288-L16"]], 3]]], "TARA_PON_MAG_00064_000000000279": [9762, 11, [[[["superkingdom", "d__Bacteria"], ["phylum", "p__Nitrospinota"], ["class", "c__Nitrospinia"], ["order", "o__Nitrospinales"], ["family", "f__Nitrospinaceae"], ["genus", "g__SCGCAAA288-L16"]], 11]]], "TARA_PON_MAG_00064_000000000280": [3130, 1, []], "TARA_PON_MAG_00064_000000000281": [3696, 4, [[[["superkingdom", "d__Bacteria"], ["phylum", "p__Nitrospinota"], ["class", "c__Nitrospinia"], ["order", "o__Nitrospinales"], ["family", "f__Nitrospinaceae"], ["genus", "g__SCGCAAA288-L16"]], 4]]], "TARA_PON_MAG_00064_000000000282": [8341, 11, []], "TARA_PON_MAG_00064_000000000283": [5433, 1, [[[["superkingdom", "d__Bacteria"], ["phylum", "p__Chloroflexota"], ["class", "c__Dehalococcoidia"], ["order", "o__UBA1151"], ["family", "f__Bin127"], ["genus", "g__GCA-002725925"]], 1]]], "TARA_PON_MAG_00064_000000000284": [27930, 20, [[[["superkingdom", "d__Bacteria"], ["phylum", "p__Nitrospinota"], ["class", "c__Nitrospinia"], ["order", "o__Nitrospinales"], ["family", "f__Nitrospinaceae"], ["genus", "g__SCGCAAA288-L16"]], 15]]], "TARA_PON_MAG_00064_000000000285": [2926, 5, []], "TARA_PON_MAG_00064_000000000286": [2500, 4, []], "TARA_PON_MAG_00064_000000000287": [8761, 12, []], "TARA_PON_MAG_00064_000000000288": [14144, 12, []], "TARA_PON_MAG_00064_000000000289": [3217, 3, [[[["superkingdom", "d__Bacteria"], ["phylum", "p__Marinisomatota"], ["class", "c__Marinisomatia"], ["order", "o__Marinisomatales"], ["family", "f__UBA1611"], ["genus", "g__UBA2134"]], 3]]], "TARA_PON_MAG_00064_000000000290": [2964, 2, []], "TARA_PON_MAG_00064_000000000291": [3554, 5, []], "TARA_PON_MAG_00064_000000000292": [3541, 5, []], "TARA_PON_MAG_00064_000000000293": [5685, 12, [[[["superkingdom", "d__Bacteria"], ["phylum", "p__Nitrospinota"], ["class", "c__Nitrospinia"], ["order", "o__Nitrospinales"], ["family", "f__Nitrospinaceae"], ["genus", "g__SCGCAAA288-L16"]], 10]]], "TARA_PON_MAG_00064_000000000294": [3104, 5, []], "TARA_PON_MAG_00064_000000000295": [3275, 4, [[[["superkingdom", "d__Bacteria"], ["phylum", "p__Chloroflexota"], ["class", "c__Dehalococcoidia"], ["order", "o__UBA1151"], ["family", "f__Bin127"], ["genus", "g__GCA-002725925"]], 2]]], "TARA_PON_MAG_00064_000000000296": [8248, 6, [[[["superkingdom", "d__Bacteria"], ["phylum", "p__Nitrospinota"], ["class", "c__Nitrospinia"], ["order", "o__Nitrospinales"], ["family", "f__Nitrospinaceae"], ["genus", "g__SCGCAAA288-L16"]], 6]]], "TARA_PON_MAG_00064_000000000297": [4200, 6, [[[["superkingdom", "d__Bacteria"], ["phylum", "p__Nitrospinota"], ["class", "c__Nitrospinia"], ["order", "o__Nitrospinales"], ["family", "f__Nitrospinaceae"], ["genus", "g__SCGCAAA288-L16"]], 5]]], "TARA_PON_MAG_00064_000000000298": [3338, 2, [[[["superkingdom", "d__Bacteria"], ["phylum", "p__Nitrospinota"], ["class", "c__Nitrospinia"], ["order", "o__Nitrospinales"], ["family", "f__Nitrospinaceae"], ["genus", "g__SCGCAAA288-L16"]], 1]]], "TARA_PON_MAG_00064_000000000299": [3908, 4, []], "TARA_PON_MAG_00064_000000000300": [6970, 9, [[[["superkingdom", "d__Bacteria"], ["phylum", "p__Nitrospinota"], ["class", "c__Nitrospinia"], ["order", "o__Nitrospinales"], ["family", "f__Nitrospinaceae"], ["genus", "g__SCGCAAA288-L16"]], 5]]], "TARA_PON_MAG_00064_000000000301": [3270, 3, []], "TARA_PON_MAG_00064_000000000302": [3670, 6, []], "TARA_PON_MAG_00064_000000000303": [3676, 3, []], "TARA_PON_MAG_00064_000000000304": [3176, 7, [[[["superkingdom", "d__Bacteria"], ["phylum", "p__Nitrospinota"], ["class", "c__Nitrospinia"], ["order", "o__Nitrospinales"], ["family", "f__Nitrospinaceae"], ["genus", "g__SCGCAAA288-L16"]], 5]]], "TARA_PON_MAG_00064_000000000305": [4257, 7, [[[["superkingdom", "d__Bacteria"], ["phylum", "p__Nitrospinota"], ["class", "c__Nitrospinia"], ["order", "o__Nitrospinales"], ["family", "f__Nitrospinaceae"], ["genus", "g__SCGCAAA288-L16"]], 6]]], "TARA_PON_MAG_00064_000000000306": [2942, 1, []], "TARA_PON_MAG_00064_000000000307": [11766, 12, [[[["superkingdom", "d__Bacteria"], ["phylum", "p__Nitrospinota"], ["class", "c__Nitrospinia"], ["order", "o__Nitrospinales"], ["family", "f__Nitrospinaceae"], ["genus", "g__SCGCAAA288-L16"]], 8]]], "TARA_PON_MAG_00064_000000000308": [5200, 7, []], "TARA_PON_MAG_00064_000000000309": [9961, 11, [[[["superkingdom", "d__Bacteria"], ["phylum", "p__Nitrospinota"], ["class", "c__Nitrospinia"], ["order", "o__Nitrospinales"], ["family", "f__Nitrospinaceae"], ["genus", "g__SCGCAAA288-L16"]], 7]]], "TARA_PON_MAG_00064_000000000310": [3291, 3, []], "TARA_PON_MAG_00064_000000000311": [12757, 8, [[[["superkingdom", "d__Bacteria"], ["phylum", "p__Nitrospinota"], ["class", "c__Nitrospinia"], ["order", "o__Nitrospinales"], ["family", "f__Nitrospinaceae"], ["genus", "g__SCGCAAA288-L16"]], 7]]], "TARA_PON_MAG_00064_000000000312": [3990, 2, [[[["superkingdom", "d__Bacteria"], ["phylum", "p__Nitrospinota"], ["class", "c__Nitrospinia"], ["order", "o__Nitrospinales"], ["family", "f__Nitrospinaceae"], ["genus", "g__SCGCAAA288-L16"]], 2]]], "TARA_PON_MAG_00064_000000000313": [4461, 3, [[[["superkingdom", "d__Bacteria"], ["phylum", "p__Nitrospinota"], ["class", "c__Nitrospinia"], ["order", "o__Nitrospinales"], ["family", "f__Nitrospinaceae"], ["genus", "g__SCGCAAA288-L16"]], 3]]], "TARA_PON_MAG_00064_000000000314": [3482, 3, [[[["superkingdom", "d__Bacteria"], ["phylum", "p__Chloroflexota"], ["class", "c__Dehalococcoidia"], ["order", "o__UBA1151"], ["family", "f__Bin127"], ["genus", "g__GCA-002725925"]], 2]]], "TARA_PON_MAG_00064_000000000315": [5645, 6, []], "TARA_PON_MAG_00064_000000000316": [6925, 4, [[[["superkingdom", "d__Bacteria"], ["phylum", "p__Nitrospinota"], ["class", "c__Nitrospinia"], ["order", "o__Nitrospinales"], ["family", "f__Nitrospinaceae"], ["genus", "g__SCGCAAA288-L16"]], 4]]], "TARA_PON_MAG_00064_000000000317": [6656, 7, [[[["superkingdom", "d__Bacteria"], ["phylum", "p__Nitrospinota"], ["class", "c__Nitrospinia"], ["order", "o__Nitrospinales"], ["family", "f__Nitrospinaceae"], ["genus", "g__SCGCAAA288-L16"]], 6]]], "TARA_PON_MAG_00064_000000000318": [3886, 2, [[[["superkingdom", "d__Bacteria"], ["phylum", "p__Nitrospinota"], ["class", "c__Nitrospinia"], ["order", "o__Nitrospinales"], ["family", "f__Nitrospinaceae"], ["genus", "g__SCGCAAA288-L16"]], 2]]], "TARA_PON_MAG_00064_000000000319": [3429, 0, []], "TARA_PON_MAG_00064_000000000320": [7162, 3, []], "TARA_PON_MAG_00064_000000000321": [3760, 4, [[[["superkingdom", "d__Bacteria"], ["phylum", "p__Nitrospinota"], ["class", "c__Nitrospinia"], ["order", "o__Nitrospinales"], ["family", "f__Nitrospinaceae"], ["genus", "g__SCGCAAA288-L16"]], 4]]], "TARA_PON_MAG_00064_000000000322": [3249, 5, []], "TARA_PON_MAG_00064_000000000323": [18599, 26, []], "TARA_PON_MAG_00064_000000000324": [7431, 5, []], "TARA_PON_MAG_00064_000000000325": [6266, 9, [[[["superkingdom", "d__Bacteria"], ["phylum", "p__Nitrospinota"], ["class", "c__Nitrospinia"], ["order", "o__Nitrospinales"], ["family", "f__Nitrospinaceae"], ["genus", "g__SCGCAAA288-L16"]], 8]]], "TARA_PON_MAG_00064_000000000326": [2922, 2, [[[["superkingdom", "d__Bacteria"], ["phylum", "p__Nitrospinota"], ["class", "c__Nitrospinia"], ["order", "o__Nitrospinales"], ["family", "f__Nitrospinaceae"], ["genus", "g__SCGCAAA288-L16"]], 2]]], "TARA_PON_MAG_00064_000000000327": [4308, 3, [[[["superkingdom", "d__Bacteria"], ["phylum", "p__Nitrospinota"], ["class", "c__Nitrospinia"], ["order", "o__Nitrospinales"], ["family", "f__Nitrospinaceae"], ["genus", "g__SCGCAAA288-L16"]], 3]]], "TARA_PON_MAG_00064_000000000328": [3299, 3, []], "TARA_PON_MAG_00064_000000000329": [10568, 13, [[[["superkingdom", "d__Bacteria"], ["phylum", "p__Nitrospinota"], ["class", "c__Nitrospinia"], ["order", "o__Nitrospinales"], ["family", "f__Nitrospinaceae"], ["genus", "g__SCGCAAA288-L16"]], 12]]], "TARA_PON_MAG_00064_000000000330": [3822, 2, []], "TARA_PON_MAG_00064_000000000331": [4932, 8, []], "TARA_PON_MAG_00064_000000000332": [3106, 6, [[[["superkingdom", "d__Bacteria"], ["phylum", "p__Nitrospinota"], ["class", "c__Nitrospinia"], ["order", "o__Nitrospinales"], ["family", "f__Nitrospinaceae"], ["genus", "g__SCGCAAA288-L16"]], 6]]], "TARA_PON_MAG_00064_000000000333": [2748, 3, [[[["superkingdom", "d__Bacteria"], ["phylum", "p__Nitrospinota"], ["class", "c__Nitrospinia"], ["order", "o__Nitrospinales"], ["family", "f__Nitrospinaceae"], ["genus", "g__SCGCAAA288-L16"]], 2]]], "TARA_PON_MAG_00064_000000000334": [10173, 8, [[[["superkingdom", "d__Bacteria"], ["phylum", "p__Nitrospinota"], ["class", "c__Nitrospinia"], ["order", "o__Nitrospinales"], ["family", "f__Nitrospinaceae"], ["genus", "g__SCGCAAA288-L16"]], 7]]], "TARA_PON_MAG_00064_000000000335": [21842, 22, [[[["superkingdom", "d__Bacteria"], ["phylum", "p__Nitrospinota"], ["class", "c__Nitrospinia"], ["order", "o__Nitrospinales"], ["family", "f__Nitrospinaceae"], ["genus", "g__SCGCAAA288-L16"]], 20]]], "TARA_PON_MAG_00064_000000000336": [4379, 7, [[[["superkingdom", "d__Bacteria"], ["phylum", "p__Chloroflexota"], ["class", "c__Dehalococcoidia"], ["order", "o__UBA1151"], ["family", "f__Bin127"], ["genus", "g__GCA-002725925"]], 5]]], "TARA_PON_MAG_00064_000000000337": [7368, 9, [[[["superkingdom", "d__Bacteria"], ["phylum", "p__Nitrospinota"], ["class", "c__Nitrospinia"], ["order", "o__Nitrospinales"], ["family", "f__Nitrospinaceae"], ["genus", "g__SCGCAAA288-L16"]], 8]]], "TARA_PON_MAG_00064_000000000338": [11047, 13, []], "TARA_PON_MAG_00064_000000000339": [3517, 1, [[[["superkingdom", "d__Bacteria"], ["phylum", "p__Nitrospinota"], ["class", "c__Nitrospinia"], ["order", "o__Nitrospinales"], ["family", "f__Nitrospinaceae"], ["genus", "g__SCGCAAA288-L16"]], 1]]], "TARA_PON_MAG_00064_000000000340": [3280, 3, [[[["superkingdom", "d__Bacteria"], ["phylum", "p__Marinisomatota"], ["class", "c__Marinisomatia"], ["order", "o__Marinisomatales"], ["family", "f__UBA1611"], ["genus", "g__UBA2134"]], 3]]], "TARA_PON_MAG_00064_000000000341": [3664, 5, [[[["superkingdom", "d__Bacteria"], ["phylum", "p__Chloroflexota"], ["class", "c__Dehalococcoidia"], ["order", "o__UBA1151"], ["family", "f__Bin127"], ["genus", "g__GCA-002725925"]], 4]]], "TARA_PON_MAG_00064_000000000342": [3715, 4, [[[["superkingdom", "d__Bacteria"], ["phylum", "p__Nitrospinota"], ["class", "c__Nitrospinia"], ["order", "o__Nitrospinales"], ["family", "f__Nitrospinaceae"], ["genus", "g__SCGCAAA288-L16"]], 3]]], "TARA_PON_MAG_00064_000000000343": [8914, 8, [[[["superkingdom", "d__Bacteria"], ["phylum", "p__Nitrospinota"], ["class", "c__Nitrospinia"], ["order", "o__Nitrospinales"], ["family", "f__Nitrospinaceae"], ["genus", "g__SCGCAAA288-L16"]], 5]]], "TARA_PON_MAG_00064_000000000344": [3071, 2, []], "TARA_PON_MAG_00064_000000000345": [4879, 9, [[[["superkingdom", "d__Bacteria"], ["phylum", "p__Nitrospinota"], ["class", "c__Nitrospinia"], ["order", "o__Nitrospinales"], ["family", "f__Nitrospinaceae"], ["genus", "g__SCGCAAA288-L16"]], 9]]], "TARA_PON_MAG_00064_000000000346": [3211, 2, []], "TARA_PON_MAG_00064_000000000347": [3223, 4, []], "TARA_PON_MAG_00064_000000000348": [4732, 8, []], "TARA_PON_MAG_00064_000000000349": [5111, 5, [[[["superkingdom", "d__Bacteria"], ["phylum", "p__Nitrospinota"], ["class", "c__Nitrospinia"], ["order", "o__Nitrospinales"], ["family", "f__Nitrospinaceae"], ["genus", "g__SCGCAAA288-L16"]], 1]]], "TARA_PON_MAG_00064_000000000350": [3469, 4, [[[["superkingdom", "d__Bacteria"], ["phylum", "p__Chloroflexota"], ["class", "c__Dehalococcoidia"], ["order", "o__UBA1151"], ["family", "f__Bin127"], ["genus", "g__GCA-002725925"]], 3]]], "TARA_PON_MAG_00064_000000000351": [5390, 6, []], "TARA_PON_MAG_00064_000000000352": [3720, 4, []], "TARA_PON_MAG_00064_000000000353": [4649, 9, [[[["superkingdom", "d__Bacteria"], ["phylum", "p__Nitrospinota"], ["class", "c__Nitrospinia"], ["order", "o__Nitrospinales"], ["family", "f__Nitrospinaceae"], ["genus", "g__SCGCAAA288-L16"]], 8]]], "TARA_PON_MAG_00064_000000000354": [5423, 3, []], "TARA_PON_MAG_00064_000000000355": [2747, 4, [[[["superkingdom", "d__Bacteria"], ["phylum", "p__Chloroflexota"], ["class", "c__Dehalococcoidia"], ["order", "o__UBA1151"], ["family", "f__Bin127"], ["genus", "g__GCA-002725925"]], 3]]], "TARA_PON_MAG_00064_000000000356": [2728, 7, [[[["superkingdom", "d__Bacteria"], ["phylum", "p__Nitrospinota"], ["class", "c__Nitrospinia"], ["order", "o__Nitrospinales"], ["family", "f__Nitrospinaceae"], ["genus", "g__SCGCAAA288-L16"]], 7]]], "TARA_PON_MAG_00064_000000000357": [3466, 2, []], "TARA_PON_MAG_00064_000000000358": [3373, 4, [[[["superkingdom", "d__Bacteria"], ["phylum", "p__Nitrospinota"], ["class", "c__Nitrospinia"], ["order", "o__Nitrospinales"], ["family", "f__Nitrospinaceae"], ["genus", "g__SCGCAAA288-L16"]], 4]]], "TARA_PON_MAG_00064_000000000359": [2755, 4, [[[["superkingdom", "d__Bacteria"], ["phylum", "p__Marinisomatota"], ["class", "c__Marinisomatia"], ["order", "o__Marinisomatales"], ["family", "f__UBA1611"], ["genus", "g__UBA2134"]], 4]]], "TARA_PON_MAG_00064_000000000360": [4173, 5, [[[["superkingdom", "d__Bacteria"], ["phylum", "p__Nitrospinota"], ["class", "c__Nitrospinia"], ["order", "o__Nitrospinales"], ["family", "f__Nitrospinaceae"], ["genus", "g__SCGCAAA288-L16"]], 5]]], "TARA_PON_MAG_00064_000000000361": [2675, 1, []], "TARA_PON_MAG_00064_000000000362": [7683, 6, []], "TARA_PON_MAG_00064_000000000363": [5622, 6, []], "TARA_PON_MAG_00064_000000000364": [2680, 3, [[[["superkingdom", "d__Bacteria"], ["phylum", "p__Chloroflexota"], ["class", "c__Dehalococcoidia"], ["order", "o__UBA1151"], ["family", "f__Bin127"], ["genus", "g__GCA-002725925"]], 1]]], "TARA_PON_MAG_00064_000000000365": [5085, 11, []], "TARA_PON_MAG_00064_000000000366": [3255, 4, [[[["superkingdom", "d__Bacteria"], ["phylum", "p__Nitrospinota"], ["class", "c__Nitrospinia"], ["order", "o__Nitrospinales"], ["family", "f__Nitrospinaceae"], ["genus", "g__SCGCAAA288-L16"]], 4]]], "TARA_PON_MAG_00064_000000000367": [14624, 18, [[[["superkingdom", "d__Bacteria"], ["phylum", "p__Nitrospinota"], ["class", "c__Nitrospinia"], ["order", "o__Nitrospinales"], ["family", "f__Nitrospinaceae"], ["genus", "g__SCGCAAA288-L16"]], 16]]], "TARA_PON_MAG_00064_000000000368": [2559, 2, []], "TARA_PON_MAG_00064_000000000369": [2522, 3, []], "TARA_PON_MAG_00064_000000000370": [9299, 2, [[[["superkingdom", "d__Bacteria"], ["phylum", "p__Proteobacteria"], ["class", "c__Gammaproteobacteria"], ["order", "o__Pseudomonadales"], ["family", "f__Pseudohongiellaceae"], ["genus", "g__UBA9145"]], 1]]], "TARA_PON_MAG_00064_000000000371": [2752, 0, []], "TARA_PON_MAG_00064_000000000372": [6661, 9, [[[["superkingdom", "d__Bacteria"], ["phylum", "p__Nitrospinota"], ["class", "c__Nitrospinia"], ["order", "o__Nitrospinales"], ["family", "f__Nitrospinaceae"], ["genus", "g__SCGCAAA288-L16"]], 9]]], "TARA_PON_MAG_00064_000000000373": [8417, 8, [[[["superkingdom", "d__Bacteria"], ["phylum", "p__Chloroflexota"], ["class", "c__Dehalococcoidia"], ["order", "o__UBA1151"], ["family", "f__Bin127"], ["genus", "g__GCA-002725925"]], 7]]], "TARA_PON_MAG_00064_000000000374": [2952, 1, [[[["superkingdom", "d__Bacteria"], ["phylum", "p__Nitrospinota"], ["class", "c__Nitrospinia"], ["order", "o__Nitrospinales"], ["family", "f__Nitrospinaceae"], ["genus", "g__SCGCAAA288-L16"]], 1]]], "TARA_PON_MAG_00064_000000000375": [4324, 6, []], "TARA_PON_MAG_00064_000000000376": [5606, 3, [[[["superkingdom", "d__Bacteria"], ["phylum", "p__Nitrospinota"], ["class", "c__Nitrospinia"], ["order", "o__Nitrospinales"], ["family", "f__Nitrospinaceae"], ["genus", "g__SCGCAAA288-L16"]], 3]]], "TARA_PON_MAG_00064_000000000377": [2947, 2, [[[["superkingdom", "d__Bacteria"], ["phylum", "p__Nitrospinota"], ["class", "c__Nitrospinia"], ["order", "o__Nitrospinales"], ["family", "f__Nitrospinaceae"], ["genus", "g__SCGCAAA288-L16"]], 2]]], "TARA_PON_MAG_00064_000000000378": [3705, 2, [[[["superkingdom", "d__Bacteria"], ["phylum", "p__Chloroflexota"], ["class", "c__Dehalococcoidia"], ["order", "o__UBA1151"], ["family", "f__Bin127"], ["genus", "g__GCA-002725925"]], 2]]], "TARA_PON_MAG_00064_000000000379": [9499, 8, [[[["superkingdom", "d__Bacteria"], ["phylum", "p__Nitrospinota"], ["class", "c__Nitrospinia"], ["order", "o__Nitrospinales"], ["family", "f__Nitrospinaceae"], ["genus", "g__SCGCAAA288-L16"]], 7]]], "TARA_PON_MAG_00064_000000000380": [2696, 3, []], "TARA_PON_MAG_00064_000000000381": [2610, 5, []], "TARA_PON_MAG_00064_000000000382": [16688, 13, [[[["superkingdom", "d__Bacteria"], ["phylum", "p__Nitrospinota"], ["class", "c__Nitrospinia"], ["order", "o__Nitrospinales"], ["family", "f__Nitrospinaceae"], ["genus", "g__SCGCAAA288-L16"]], 11]]], "TARA_PON_MAG_00064_000000000383": [6362, 2, []], "TARA_PON_MAG_00064_000000000384": [2935, 1, [[[["superkingdom", "d__Bacteria"], ["phylum", "p__Proteobacteria"], ["class", "c__Gammaproteobacteria"], ["order", "o__Pseudomonadales"], ["family", "f__HTCC2089"], ["genus", "g__GCA-2725285"]], 1]]], "TARA_PON_MAG_00064_000000000385": [2605, 7, []], "TARA_PON_MAG_00064_000000000386": [14349, 14, [[[["superkingdom", "d__Bacteria"], ["phylum", "p__Nitrospinota"], ["class", "c__Nitrospinia"], ["order", "o__Nitrospinales"], ["family", "f__Nitrospinaceae"], ["genus", "g__SCGCAAA288-L16"]], 12]]], "TARA_PON_MAG_00064_000000000387": [4154, 3, [[[["superkingdom", "d__Bacteria"], ["phylum", "p__Nitrospinota"], ["class", "c__Nitrospinia"], ["order", "o__Nitrospinales"], ["family", "f__Nitrospinaceae"], ["genus", "g__SCGCAAA288-L16"]], 2]]], "TARA_PON_MAG_00064_000000000388": [9190, 12, []], "TARA_PON_MAG_00064_000000000389": [3450, 4, []], "TARA_PON_MAG_00064_000000000390": [3031, 0, []], "TARA_PON_MAG_00064_000000000391": [3193, 3, [[[["superkingdom", "d__Bacteria"], ["phylum", "p__Nitrospinota"], ["class", "c__Nitrospinia"], ["order", "o__Nitrospinales"], ["family", "f__Nitrospinaceae"], ["genus", "g__SCGCAAA288-L16"]], 3]]], "TARA_PON_MAG_00064_000000000392": [3848, 3, [[[["superkingdom", "d__Bacteria"], ["phylum", "p__Chloroflexota"], ["class", "c__Dehalococcoidia"], ["order", "o__UBA1151"], ["family", "f__Bin127"], ["genus", "g__GCA-002725925"]], 2]]], "TARA_PON_MAG_00064_000000000393": [5092, 8, []], "TARA_PON_MAG_00064_000000000394": [2961, 2, [[[["superkingdom", "d__Bacteria"], ["phylum", "p__Nitrospinota"], ["class", "c__Nitrospinia"], ["order", "o__Nitrospinales"], ["family", "f__Nitrospinaceae"], ["genus", "g__SCGCAAA288-L16"]], 2]]], "TARA_PON_MAG_00064_000000000395": [7308, 3, [[[["superkingdom", "d__Bacteria"], ["phylum", "p__Nitrospinota"], ["class", "c__Nitrospinia"], ["order", "o__Nitrospinales"], ["family", "f__Nitrospinaceae"], ["genus", "g__SCGCAAA288-L16"]], 3]]], "TARA_PON_MAG_00064_000000000396": [2987, 4, []], "TARA_PON_MAG_00064_000000000397": [5164, 8, [[[["superkingdom", "d__Bacteria"], ["phylum", "p__Nitrospinota"], ["class", "c__Nitrospinia"], ["order", "o__Nitrospinales"], ["family", "f__Nitrospinaceae"], ["genus", "g__SCGCAAA288-L16"]], 8]]], "TARA_PON_MAG_00064_000000000398": [5669, 5, [[[["superkingdom", "d__Bacteria"], ["phylum", "p__Chloroflexota"], ["class", "c__Dehalococcoidia"], ["order", "o__UBA1151"], ["family", "f__Bin127"], ["genus", "g__GCA-002725925"]], 3]]], "TARA_PON_MAG_00064_000000000399": [2877, 5, []], "TARA_PON_MAG_00064_000000000400": [5373, 5, [[[["superkingdom", "d__Bacteria"], ["phylum", "p__Chloroflexota"], ["class", "c__Dehalococcoidia"], ["order", "o__UBA1151"], ["family", "f__Bin127"], ["genus", "g__GCA-002725925"]], 3]]], "TARA_PON_MAG_00064_000000000401": [6284, 3, [[[["superkingdom", "d__Bacteria"], ["phylum", "p__Chloroflexota"], ["class", "c__Dehalococcoidia"], ["order", "o__UBA1151"], ["family", "f__Bin127"], ["genus", "g__GCA-002725925"]], 2]]], "TARA_PON_MAG_00064_000000000402": [2826, 2, []], "TARA_PON_MAG_00064_000000000403": [5349, 3, []], "TARA_PON_MAG_00064_000000000404": [8125, 5, [[[["superkingdom", "d__Bacteria"], ["phylum", "p__Nitrospinota"], ["class", "c__Nitrospinia"], ["order", "o__Nitrospinales"], ["family", "f__Nitrospinaceae"], ["genus", "g__SCGCAAA288-L16"]], 5]]], "TARA_PON_MAG_00064_000000000405": [3731, 4, []], "TARA_PON_MAG_00064_000000000406": [3429, 3, []], "TARA_PON_MAG_00064_000000000407": [4163, 5, [[[["superkingdom", "d__Bacteria"], ["phylum", "p__Chloroflexota"], ["class", "c__Dehalococcoidia"], ["order", "o__UBA1151"], ["family", "f__Bin127"], ["genus", "g__GCA-002725925"]], 3]]], "TARA_PON_MAG_00064_000000000408": [5503, 2, [[[["superkingdom", "d__Bacteria"], ["phylum", "p__Nitrospinota"], ["class", "c__Nitrospinia"], ["order", "o__Nitrospinales"], ["family", "f__Nitrospinaceae"], ["genus", "g__SCGCAAA288-L16"]], 2]]], "TARA_PON_MAG_00064_000000000409": [2934, 5, []], "TARA_PON_MAG_00064_000000000410": [2943, 2, []], "TARA_PON_MAG_00064_000000000411": [3898, 2, [[[["superkingdom", "d__Bacteria"], ["phylum", "p__Chloroflexota"], ["class", "c__Dehalococcoidia"], ["order", "o__UBA1151"], ["family", "f__Bin127"], ["genus", "g__GCA-002725925"]], 2]]], "TARA_PON_MAG_00064_000000000412": [14739, 20, [[[["superkingdom", "d__Bacteria"], ["phylum", "p__Nitrospinota"], ["class", "c__Nitrospinia"], ["order", "o__Nitrospinales"], ["family", "f__Nitrospinaceae"], ["genus", "g__SCGCAAA288-L16"]], 17]]], "TARA_PON_MAG_00064_000000000413": [5447, 4, []], "TARA_PON_MAG_00064_000000000414": [2913, 3, []], "TARA_PON_MAG_00064_000000000415": [4321, 3, []], "TARA_PON_MAG_00064_000000000416": [3213, 5, [[[["superkingdom", "d__Bacteria"], ["phylum", "p__Nitrospinota"], ["class", "c__Nitrospinia"], ["order", "o__Nitrospinales"], ["family", "f__Nitrospinaceae"], ["genus", "g__SCGCAAA288-L16"]], 1]]], "TARA_PON_MAG_00064_000000000417": [3105, 3, []], "TARA_PON_MAG_00064_000000000418": [2515, 1, []], "TARA_PON_MAG_00064_000000000419": [6569, 5, []], "TARA_PON_MAG_00064_000000000420": [3088, 3, []], "TARA_PON_MAG_00064_000000000421": [3224, 5, [[[["superkingdom", "d__Bacteria"], ["phylum", "p__Chloroflexota"], ["class", "c__Dehalococcoidia"], ["order", "o__UBA1151"], ["family", "f__Bin127"], ["genus", "g__GCA-002725925"]], 2]]], "TARA_PON_MAG_00064_000000000422": [3101, 4, [[[["superkingdom", "d__Bacteria"], ["phylum", "p__Nitrospinota"], ["class", "c__Nitrospinia"], ["order", "o__Nitrospinales"], ["family", "f__Nitrospinaceae"], ["genus", "g__SCGCAAA288-L16"]], 1]]], "TARA_PON_MAG_00064_000000000423": [3238, 2, [[[["superkingdom", "d__Bacteria"], ["phylum", "p__Chloroflexota"], ["class", "c__Dehalococcoidia"], ["order", "o__UBA1151"], ["family", "f__Bin127"], ["genus", "g__GCA-002725925"]], 1]]], "TARA_PON_MAG_00064_000000000424": [8372, 9, []], "TARA_PON_MAG_00064_000000000425": [2948, 1, []], "TARA_PON_MAG_00064_000000000426": [5820, 13, [[[["superkingdom", "d__Bacteria"], ["phylum", "p__Nitrospinota"], ["class", "c__Nitrospinia"], ["order", "o__Nitrospinales"], ["family", "f__Nitrospinaceae"], ["genus", "g__SCGCAAA288-L16"]], 11]]], "TARA_PON_MAG_00064_000000000427": [6115, 8, [[[["superkingdom", "d__Bacteria"], ["phylum", "p__Chloroflexota"], ["class", "c__Dehalococcoidia"], ["order", "o__UBA1151"], ["family", "f__Bin127"], ["genus", "g__GCA-002725925"]], 5]]], "TARA_PON_MAG_00064_000000000428": [3854, 5, [[[["superkingdom", "d__Bacteria"], ["phylum", "p__Nitrospinota"], ["class", "c__Nitrospinia"], ["order", "o__Nitrospinales"], ["family", "f__Nitrospinaceae"], ["genus", "g__SCGCAAA288-L16"]], 4]]], "TARA_PON_MAG_00064_000000000429": [2719, 1, []], "TARA_PON_MAG_00064_000000000430": [2739, 2, [[[["superkingdom", "d__Bacteria"], ["phylum", "p__Chloroflexota"], ["class", "c__Dehalococcoidia"], ["order", "o__UBA1151"], ["family", "f__Bin127"], ["genus", "g__GCA-002725925"]], 1]]], "TARA_PON_MAG_00064_000000000431": [2683, 2, [[[["superkingdom", "d__Bacteria"], ["phylum", "p__Chloroflexota"], ["class", "c__Dehalococcoidia"], ["order", "o__UBA1151"], ["family", "f__Bin127"], ["genus", "g__GCA-002725925"]], 2]]], "TARA_PON_MAG_00064_000000000432": [14833, 14, [[[["superkingdom", "d__Bacteria"], ["phylum", "p__Nitrospinota"], ["class", "c__Nitrospinia"], ["order", "o__Nitrospinales"], ["family", "f__Nitrospinaceae"], ["genus", "g__SCGCAAA288-L16"]], 13]]], "TARA_PON_MAG_00064_000000000433": [2910, 2, []], "TARA_PON_MAG_00064_000000000434": [3178, 3, [[[["superkingdom", "d__Bacteria"], ["phylum", "p__Nitrospinota"], ["class", "c__Nitrospinia"], ["order", "o__Nitrospinales"], ["family", "f__Nitrospinaceae"], ["genus", "g__SCGCAAA288-L16"]], 3]]], "TARA_PON_MAG_00064_000000000435": [9281, 6, [[[["superkingdom", "d__Bacteria"], ["phylum", "p__Nitrospinota"], ["class", "c__Nitrospinia"], ["order", "o__Nitrospinales"], ["family", "f__Nitrospinaceae"], ["genus", "g__SCGCAAA288-L16"]], 4]]], "TARA_PON_MAG_00064_000000000436": [9602, 5, [[[["superkingdom", "d__Bacteria"], ["phylum", "p__Nitrospinota"], ["class", "c__Nitrospinia"], ["order", "o__Nitrospinales"], ["family", "f__Nitrospinaceae"], ["genus", "g__SCGCAAA288-L16"]], 3]]], "TARA_PON_MAG_00064_000000000437": [3450, 0, []], "TARA_PON_MAG_00064_000000000438": [3405, 3, [[[["superkingdom", "d__Bacteria"], ["phylum", "p__Nitrospinota"], ["class", "c__Nitrospinia"], ["order", "o__Nitrospinales"], ["family", "f__Nitrospinaceae"], ["genus", "g__SCGCAAA288-L16"]], 2]]], "TARA_PON_MAG_00064_000000000439": [3256, 2, []]}